Workbook

Sheet IC Summary
A1: PMC PLATFORM — INVESTMENT COMMITTEE SUMMARY
A2: =" Base case shown unless a column is labelled otherwise. Controls: "&Controls!$B$77&" | "&Controls!$C$77&" | Release candidate v2.4.4, supervisor review then desktop Excel gate." -> Base case shown unless a column is labelled otherwise. Controls: 57 of 66 | REVIEW | Release candidate v2.4.4, supervisor review then desktop Excel gate.
A4: 1. WHAT WE ARE BUYING
A5: Anchor platform | C5: ='Acquisition Schedule'!F$6 -> 1000000
A6: Annual large tuck-ins, Years 1 to 7 | C6: =COUNTIF('Acquisition Schedule'!$B$6:$B$14,"Large tuck-in") -> 7
A7: Year-3 mid-market addition | C7: =INDEX(Assumptions!$D$37:$F$37,1,2) -> 1250000
A8: Total acquired EBITDA | C8: ='Acquisition Schedule'!F$15 -> 7500000
A9: Total acquisition enterprise value | C9: ='Acquisition Schedule'!N$15 -> 34500000
A10: Blended entry multiple | C10: =IF('Acquisition Schedule'!F$15=0,0,'Acquisition Schedule'!N$15/'Acquisition Schedule'!F$15) -> 4.6
A12: 2. SCALE AND RESULT
D13: Year 3 | E13: Year 5 | F13: Year 7 | G13: Year 10
A14: Managed units | D14: ='Operating Case'!G$50 -> 26492.36 | E14: ='Operating Case'!I$50 -> 44168.302 | F14: ='Operating Case'!K$50 -> 50000 | G14: ='Operating Case'!N$50 -> 50000
A15: Properties | D15: ='Operating Case'!G$51 -> 105.96944 | E15: ='Operating Case'!I$51 -> 176.67321 | F15: ='Operating Case'!K$51 -> 200 | G15: ='Operating Case'!N$51 -> 200
A16: Clients | D16: ='Operating Case'!G$52 -> 14.769785 | E16: ='Operating Case'!I$52 -> 24.875588 | F16: ='Operating Case'!K$52 -> 28.330667 | G16: ='Operating Case'!N$52 -> 28.330667
A17: Recurring revenue | D17: ='Operating Case'!G$54 -> 17312306 | E17: ='Operating Case'!I$54 -> 28863232 | F17: ='Operating Case'!K$54 -> 32674147 | G17: ='Operating Case'!N$54 -> 32674147
A18: Total platform revenue | D18: ='Operating Case'!G$54+'Operating Case'!G$50*INDEX(Assumptions!$D$30:$F$30,1,2)+'Operating Case'!G$67+'Operating Case'!G$69+'Operating Case'!G$71 -> 18054092 | E18: ='Operating Case'!I$54+'Operating Case'!I$50*INDEX(Assumptions!$D$30:$F$30,1,2)+'Operating Case'!I$67+'Operating Case'!I$69+'Operating Case'!I$71 -> 30099945 | F18: ='Operating Case'!K$54+'Operating Case'!K$50*INDEX(Assumptions!$D$30:$F$30,1,2)+'Operating Case'!K$67+'Operating Case'!K$69+'Operating Case'!K$71 -> 34074147 | G18: ='Operating Case'!N$54+'Operating Case'!N$50*INDEX(Assumptions!$D$30:$F$30,1,2)+'Operating Case'!N$67+'Operating Case'!N$69+'Operating Case'!N$71 -> 34074147
A19: Consolidated platform EBITDA | D19: ='Operating Case'!G$79 -> -645223.17 | E19: ='Operating Case'!I$79 -> 1989260.4 | F19: ='Operating Case'!K$79 -> 2910357.8 | G19: ='Operating Case'!N$79 -> 1641331.6
A20: Platform EBITDA margin | D20: ='Operating Case'!G$88 -> -0.035738335 | E20: ='Operating Case'!I$88 -> 0.066088507 | F20: ='Operating Case'!K$88 -> 0.085412491 | G20: ='Operating Case'!N$88 -> 0.048169412
A22: 3. WHERE THE YEAR-7 EBITDA COMES FROM
A23: Acquired book — contracted EBITDA | C23: ='Operating Case'!K$55 -> 5171512 | E23: ACQUIRED / RECURRING
A24: Organic new business | C24: ='Operating Case'!K$56 -> 1228488 | E24: BUYER-CREATED / REVENUE
A25: Centralisation — seller payroll removed | C25: ='Operating Case'!K$58 -> 8528944.6 | E25: BUYER-CREATED / COST
A26: less same-scope shared-services replacement | C26: =-'Org & Capacity'!$D$245 -> -3622536.8 | E26: BUYER-CREATED / COST
A27: of which nearshore delivery saving (memo) | C27: ='Org & Capacity'!$D$259 -> 1532367.6 | E27: MEMO — inside the two lines above
A28: Leadership redundancy — uncredited by decision | C28: ='Operating Case'!K$61 -> 0 | E28: [OQ] UNCREDITED UPSIDE
A29: New-function institutionalisation | C29: =-'Org & Capacity'!$D$247 -> -2547285.7 | E29: BUYER-CREATED / COST
A30: Organic-growth support capacity | C30: =-'Org & Capacity'!$D$249 -> -986816.58 | E30: BUYER-CREATED / COST
A31: Transition overlap, complexity and integration | C31: ='Operating Case'!K$60+'Operating Case'!K$62+'Operating Case'!K$64+'Operating Case'!K$65 -> -1480941.8 | E31: BUYER-CREATED / COST
A32: Platform services — Layers 1 to 3, net | C32: ='Operating Case'!K$67+'Operating Case'!K$68+'Operating Case'!K$69+'Operating Case'!K$70+'Operating Case'!K$71+'Operating Case'!K$72+'Operating Case'!K$63+'Operating Case'!K$73 -> -415602.31 | E32: BUYER-CREATED / REVENUE
A33: HoldCo payroll and non-payroll G&A | C33: ='Operating Case'!K$77+'Operating Case'!K$78 -> -2965403.6 | E33: BUYER-CREATED / COST
A34: CONSOLIDATED PLATFORM EBITDA — YEAR 7 | C34: ='Operating Case'!K$79 -> 2910357.8
A35: Bridge reconstruction difference — must be nil | C35: =C34-(C23+C24+C25+C26+C28+C29+C30+C31+C32+C33) -> 0
A37: 4. CAPITAL AND RETURNS
A38: Cumulative sponsor equity | C38: =Returns!$E$54 -> 38639177
A39: Senior debt at exit | C39: ='Transaction & Liquidity'!K$86 -> 5970441.3
A40: Total debt at exit | C40: ='Transaction & Liquidity'!K$86+'Transaction & Liquidity'!K$100 -> 9345441.3
A41: Total debt / consolidated EBITDA | C41: =IF('Operating Case'!K$79=0,0,('Transaction & Liquidity'!K$86+'Transaction & Liquidity'!K$100)/'Operating Case'!K$79) -> 3.2110971
A42: Consolidated coverage ratio | C42: =Controls!$B$74 -> 0.84736747
A43: Exit enterprise value | C43: =Returns!$E$42 -> 27648399
A44: Equity proceeds at exit | C44: =Returns!$E$51 -> 19249990
A45: 7-year MOIC | C45: =Returns!$E$56 -> 0.49819875
A46: True 7-year sponsor cash-flow IRR | C46: =Returns!$E$57 -> -0.15920531
A47: Multiple-arbitrage share of exit EV | C47: =Returns!$E$45 -> 0.63938195
A49: 5. STATUS AND VERDICT
A50: Control status | C50: =Controls!$B$77&" "&Controls!$C$77 -> 57 of 66 REVIEW
A51: Evidence-constrained Year-7 EBITDA — switch ON | C51: Run Assumptions D8 = 1; see Control 19
A52: Diagnostic status | C52: =IF(Controls!$C$77="FAIL","NOT UNDERWRITABLE — CONTROLS FAIL",IF(Controls!$C$77="REVIEW","DIAGNOSTIC ONLY — CONTROLS AT REVIEW","CONTROLS PASS")) -> DIAGNOSTIC ONLY — CONTROLS AT REVIEW
A53: Gate 1 verdict | C53: PAUSE PENDING NAMED EVIDENCE
A54: Top five assumptions by Year-7 EBITDA sensitivity
A55: 1. Column-W shared-services spans [E] — four reference calls on properties per central controller, accountant and AP clerk
A56: 2. ORG-20 target payroll structure [OQ] — one 6,000-unit target P&L, payroll register and employee census by role
A57: 3. Nearshore delivered cost index [A] 0.40x — a PMC-specific delivered quote; 0.46x comparable at Evidence & Market C38
A58: 4. Layer 1 to 3 pricing and adoption [A] — three owner willingness-to-pay conversations against the incumbent $42.45/unit
A59: 5. Leadership redundancy and roster duplication [OQ] — uncredited; requires target roster evidence
A60: =" One acquisition programme, three operating cases, identical at-close facts. | "&Assumptions!$E$8&" | "&Assumptions!$E$9&" | Gate 1: PAUSE PENDING NAMED EVIDENCE" -> One acquisition programme, three operating cases, identical at-close facts. | FULL CASE | | Gate 1: PAUSE PENDING NAMED EVIDENCE
A62: THE CENTRAL REQUIREMENT
A63: Target EBITDA per managed unit the strategy requires | C63: =INDEX(Assumptions!$D$32:$F$32,1,2) -> 128
A64: Implied normalized EBITDA margin on the evidenced revenue basis | C64: =INDEX(Assumptions!$D$32:$F$32,1,2)/(INDEX(Assumptions!$D$27:$F$27,1,2)+INDEX(Assumptions!$D$28:$F$28,1,2)+INDEX(Assumptions!$D$29:$F$29,1,2)+INDEX(Assumptions!$D$30:$F$30,1,2)) -> 0.19587351
A65: What this means | C65: ="The strategy as specified requires the target universe to average "&TEXT(C63,"$#,##0")&" of normalized EBITDA per unit, or "&TEXT(C64,"0.0%")&" on the Forum-derived revenue basis, to execute this acquisition cadence and remain within the 50,000-unit ceiling. That is an acquisition screen, not evidence that such targets exist." -> The strategy as specified requires the target universe to average $128 of normalized EBITDA per unit, or 19.6% on the Forum-derived revenue basis, to execute this acquisition cadence and remain within the 50,000-unit ceiling. That is an acquisition screen, not evidence that such targets exist.
A67: INVESTMENT BASIS
A68: Anchor normalized EBITDA | C68: ='Anchor QoE'!$D$17 -> 1000000
A69: Anchor units at close | C69: ='Anchor QoE'!$D$20 -> 7812.5
A70: Anchor properties at close | C70: ='Anchor QoE'!$D$21 -> 31.25
A71: Anchor clients at close | C71: ='Anchor QoE'!$D$22 -> 6
A72: Anchor entry multiple | C72: ='Anchor QoE'!$D$23 -> 6
A73: Anchor enterprise value | C73: ='Anchor QoE'!$D$24 -> 6000000
A74: Tuck-ins in the programme | C74: =COUNTIF('Acquisition Schedule'!$E$7:$E$14,">=0") -> 8 | G74: Seven annual large tuck-ins plus the declared Year-3 mid-market addition, sized in EBITDA as instructed.
A75: Total acquired EBITDA | C75: ='Acquisition Schedule'!$F$15 -> 7500000
A76: Total acquisition enterprise value | C76: ='Acquisition Schedule'!$N$15 -> 34500000
A77: Blended annual revenue retention | C77: ='Anchor QoE'!$F$12 -> 0.911
A78: Implied average contract life | C78: ='Anchor QoE'!$F$13 -> 11.235955
A80: OPERATING BUILD — BASE
A81: Metric | C81: Year 3 | D81: Year 5 | E81: Year 7 | F81: Year 10
A82: Managed units | C82: ='Operating Case'!G$50 -> 26492.36 | D82: ='Operating Case'!I$50 -> 44168.302 | E82: ='Operating Case'!K$50 -> 50000 | F82: ='Operating Case'!N$50 -> 50000
A83: Properties — derived from units | C83: ='Operating Case'!G$51 -> 105.96944 | D83: ='Operating Case'!I$51 -> 176.67321 | E83: ='Operating Case'!K$51 -> 200 | F83: ='Operating Case'!N$51 -> 200
A84: Clients — derived from the programme | C84: ='Operating Case'!G$52 -> 14.769785 | D84: ='Operating Case'!I$52 -> 24.875588 | E84: ='Operating Case'!K$52 -> 28.330667 | F84: ='Operating Case'!N$52 -> 28.330667
A85: Recurring revenue | C85: ='Operating Case'!G$54 -> 17312306 | D85: ='Operating Case'!I$54 -> 28863232 | E85: ='Operating Case'!K$54 -> 32674147 | F85: ='Operating Case'!N$54 -> 32674147
A86: Standalone acquired EBITDA | C86: ='Operating Case'!G$55 -> 3067380.7 | D86: ='Operating Case'!I$55 -> 4535738 | E86: ='Operating Case'!K$55 -> 5171512 | F86: ='Operating Case'!N$55 -> 4228547
A87: Integrated DealCo EBITDA | C87: ='Operating Case'!G$76 -> 1893784.4 | D87: ='Operating Case'!I$76 -> 4732208.3 | E87: ='Operating Case'!K$76 -> 5875761.4 | F87: ='Operating Case'!N$76 -> 4979305.6
A88: Consolidated platform EBITDA | C88: ='Operating Case'!G$79 -> -645223.17 | D88: ='Operating Case'!I$79 -> 1989260.4 | E88: ='Operating Case'!K$79 -> 2910357.8 | F88: ='Operating Case'!N$79 -> 1641331.6
A89: PMC-borne corporate FTE | C89: ='Operating Case'!G$84 -> 43.719389 | D89: ='Operating Case'!I$84 -> 63.133465 | E89: ='Operating Case'!K$84 -> 68.6 | F89: ='Operating Case'!N$84 -> 68.6
A90: Corporate payroll per managed unit | C90: ='Operating Case'!G$85 -> 257.97107 | D90: ='Operating Case'!I$85 -> 224.14802 | E90: ='Operating Case'!K$85 -> 224.95235 | F90: ='Operating Case'!N$85 -> 245.81151
A91: Owner-reimbursed onsite FTE — memo | C91: ='Org & Capacity'!G$199 -> 633 | D91: ='Org & Capacity'!I$199 -> 1056 | E91: ='Org & Capacity'!K$199 -> 1193 | F91: ='Org & Capacity'!N$199 -> 1193
A93: EXIT STATE — DERIVED, AGAINST THE PLANNING OBJECTIVES
A94: Measure | C94: Derived at exit | D94: Objective | E94: Variance
A95: Managed units | C95: =INDEX('Operating Case'!E$50:N$50,1,INDEX(Assumptions!$D$13:$F$13,1,2)) -> 50000 | D95: =INDEX(Assumptions!$D$16:$F$16,1,2) -> 50000 | E95: =C95-D95 -> 0 | G95: Ceiling, not a target. Capacity binds in every case.
A96: Properties | C96: =INDEX('Operating Case'!E$51:N$51,1,INDEX(Assumptions!$D$13:$F$13,1,2)) -> 200 | D96: =INDEX(Assumptions!$D$16:$F$16,1,2)/INDEX(Assumptions!$D$17:$F$17,1,2) -> 200 | E96: =C96-D96 -> 0 | G96: Arithmetic consequence of units and units per property. Never entered.
A97: Clients | C97: =INDEX('Operating Case'!E$52:N$52,1,INDEX(Assumptions!$D$13:$F$13,1,2)) -> 28.330667 | D97: =INDEX(Assumptions!$D$24:$F$24,1,2) -> 30 | E97: =C97-D97 -> -1.6693333 | G97: Derived from clients acquired per deal and retention. The objective scores it; it does not size anything.
A98: Consolidated platform EBITDA | C98: =INDEX('Operating Case'!E$79:N$79,1,INDEX(Assumptions!$D$13:$F$13,1,2)) -> 2910357.8 | D98: =INDEX(Assumptions!$D$23:$F$23,1,2) -> 10000000 | E98: =C98-D98 -> -7089642.2 | T98: WATERFALL HELPER — drives IC chart 1; mutually exclusive steps, nearshore appears once
T99: Step | U99: Invisible base | V99: Value
A100: CASE COMPARISON — SAME PROGRAMME, SAME AT-CLOSE FACTS | T100: Acquired contracted EBITDA | U100: =IF(W100>=0,0,0+W100) -> 0 | V100: =ABS(W100) -> 5171512 | W100: ='Operating Case'!K$55 -> 5171512 | X100: =0+W100 -> 5171512
A101: Metric | C101: Downside | D101: Base | E101: Upside | T101: Organic new business | U101: =IF(W101>=0,X100,X100+W101) -> 5171512 | V101: =ABS(W101) -> 1228488 | W101: ='Operating Case'!K$56 -> 1228488 | X101: =X100+W101 -> 6400000
A102: Year-7 platform EBITDA | C102: =INDEX('Operating Case'!E$36:N$36,1,INDEX(Assumptions!$D$13:$F$13,1,1)) -> 947024.46 | D102: =INDEX('Operating Case'!E$79:N$79,1,INDEX(Assumptions!$D$13:$F$13,1,2)) -> 2910357.8 | E102: =INDEX('Operating Case'!E$122:N$122,1,INDEX(Assumptions!$D$13:$F$13,1,3)) -> 4914779.8 | T102: Centralisation before nearshore | U102: =IF(W102>=0,X101,X101+W102) -> 6400000 | V102: =ABS(W102) -> 3374040.2 | W102: ='Operating Case'!K$58-'Org & Capacity'!$D$245-'Org & Capacity'!$D$259 -> 3374040.2 | X102: =X101+W102 -> 9774040.2
A103: Shortfall to the $10m target | C103: ='Operating Case'!E$138 -> -9052975.5 | D103: ='Operating Case'!F$138 -> -7089642.2 | E103: ='Operating Case'!G$138 -> -5085220.2 | T103: Nearshore delivery saving | U103: =IF(W103>=0,X102,X102+W103) -> 9774040.2 | V103: =ABS(W103) -> 1532367.6 | W103: ='Org & Capacity'!$D$259 -> 1532367.6 | X103: =X102+W103 -> 11306408
A104: Headroom to the 50,000-unit ceiling | C104: ='Operating Case'!E$147 -> 2759.2135 | D104: ='Operating Case'!F$147 -> 0 | E104: ='Operating Case'!G$147 -> 0 | G104: The ceiling is an operating-capacity constraint common to all three cases. Once full, the platform stops accepting incremental business. | T104: Institutionalisation | U104: =IF(W104>=0,X103,X103+W104) -> 8759122.1 | V104: =ABS(W104) -> 2547285.7 | W104: =-'Org & Capacity'!$D$247 -> -2547285.7 | X104: =X103+W104 -> 8759122.1
A105: Deferred / unserved pipeline units at Year 7 | C105: ='Revenue & Durability'!K$44 -> 0 | D105: ='Revenue & Durability'!K$107 -> 8649.934 | E105: ='Revenue & Durability'!K$170 -> 22565.6 | G105: Organic wins the platform could not serve within the ceiling. Contracted acquired units are never dropped. | T105: Organic-growth support | U105: =IF(W105>=0,X104,X104+W105) -> 7772305.5 | V105: =ABS(W105) -> 986816.58 | W105: =-'Org & Capacity'!$D$249 -> -986816.58 | X105: =X104+W105 -> 7772305.5
A106: MINIMUM TARGET EBITDA MARGIN for the ceiling to hold | C106: ='Operating Case'!E$151 -> 0.18506438 | D106: ='Operating Case'!F$151 -> 0.22975937 | E106: ='Operating Case'!G$151 -> 0.28427358 | G106: The minimum target quality at which the instructed EBITDA sizes and the 50,000-unit ceiling coexist. One cell on Assumptions. | T106: Transition, complexity, integration | U106: =IF(W106>=0,X105,X105+W106) -> 6291363.7 | V106: =ABS(W106) -> 1480941.8 | W106: ='Operating Case'!K$60+'Operating Case'!K$62+'Operating Case'!K$64+'Operating Case'!K$65 -> -1480941.8 | X106: =X105+W106 -> 6291363.7
A107: Minimum target EBITDA per managed unit | C107: ='Operating Case'!E$152 -> 120.93641 | D107: ='Operating Case'!F$152 -> 150.14383 | E107: ='Operating Case'!G$152 -> 185.76794 | T107: Platform services, net | U107: =IF(W107>=0,X106,X106+W107) -> 5875761.4 | V107: =ABS(W107) -> 415602.31 | W107: ='Operating Case'!K$67+'Operating Case'!K$68+'Operating Case'!K$69+'Operating Case'!K$70+'Operating Case'!K$71+'Operating Case'!K$72+'Operating Case'!K$63+'Operating Case'!K$73 -> -415602.31 | X107: =X106+W107 -> 5875761.4
A108: Target EBITDA per unit at the current margin | C108: ='Operating Case'!E$153 -> 128 | D108: ='Operating Case'!F$153 -> 128 | E108: ='Operating Case'!G$153 -> 128 | T108: HoldCo payroll and G&A | U108: =IF(W108>=0,X107,X107+W108) -> 2910357.8 | V108: =ABS(W108) -> 2965403.6 | W108: ='Operating Case'!K$77+'Operating Case'!K$78 -> -2965403.6 | X108: =X107+W108 -> 2910357.8
A109: Managed units at Year 7 | C109: =INDEX('Operating Case'!E$7:N$7,1,INDEX(Assumptions!$D$13:$F$13,1,1)) -> 47240.786 | D109: =INDEX('Operating Case'!E$50:N$50,1,INDEX(Assumptions!$D$13:$F$13,1,2)) -> 50000 | E109: =INDEX('Operating Case'!E$93:N$93,1,INDEX(Assumptions!$D$13:$F$13,1,3)) -> 50000 | T109: Consolidated platform EBITDA | U109: 0 | V109: ='Operating Case'!K$79 -> 2910357.8
...

Sheet Base Case Bridge
A1: BASE CASE BRIDGE — FROM ACQUIRED COMPANY ECONOMICS TO PLATFORM ECONOMICS
A2: Every source appears in exactly one category. The tags are display; Controls 62 and 65 reconstruct the same economics from engine primitives.
A4: YEAR-7 BRIDGE — BASE | E4: Origin | F4: Recurrence | G4: Type
A5: Acquired book — contracted EBITDA | C5: ='Operating Case'!K$55 -> 5171512 | E5: ACQUIRED | F5: RECURRING | G5: REVENUE
A6: Organic new business | C6: ='Operating Case'!K$56 -> 1228488 | E6: BUYER-CREATED | F6: RECURRING | G6: REVENUE
A7: Seller payroll removed by centralisation | C7: ='Operating Case'!K$58 -> 8528944.6 | E7: BUYER-CREATED | F7: RECURRING | G7: COST SAVING
A8: Same-scope shared-services replacement | C8: =-'Org & Capacity'!$D$245 -> -3622536.8 | E8: BUYER-CREATED | F8: RECURRING | G8: COST
A9: New-function institutionalisation | C9: =-'Org & Capacity'!$D$247 -> -2547285.7 | E9: BUYER-CREATED | F9: RECURRING | G9: COST
A10: Organic-growth support capacity | C10: =-'Org & Capacity'!$D$249 -> -986816.58 | E10: BUYER-CREATED | F10: RECURRING | G10: COST
A11: Leadership redundancy — uncredited by decision | C11: ='Operating Case'!K$61 -> 0 | E11: BUYER-CREATED | F11: RECURRING | G11: COST SAVING
A12: Transition overlap | C12: ='Operating Case'!K$60 -> -354398.25 | E12: BUYER-CREATED | F12: EPISODIC | G12: COST
A13: Customer-complexity payroll | C13: ='Operating Case'!K$62 -> -967793.57 | E13: BUYER-CREATED | F13: RECURRING | G13: COST
A14: Integration pods | C14: ='Operating Case'!K$64 -> -480000 | E14: BUYER-CREATED | F14: EPISODIC | G14: COST
A15: Other integration savings | C15: ='Operating Case'!K$65 -> 321250 | E15: BUYER-CREATED | F15: RECURRING | G15: COST SAVING
A16: Platform services — Layers 1 to 3, net of delivery | C16: ='Operating Case'!K$67+'Operating Case'!K$68+'Operating Case'!K$69+'Operating Case'!K$70+'Operating Case'!K$71+'Operating Case'!K$72+'Operating Case'!K$63+'Operating Case'!K$73 -> -415602.31 | E16: BUYER-CREATED | F16: RECURRING | G16: REVENUE
A17: HoldCo payroll | C17: ='Operating Case'!K$77 -> -1972440.2 | E17: BUYER-CREATED | F17: RECURRING | G17: COST
A18: HoldCo non-payroll G&A | C18: ='Operating Case'!K$78 -> -992963.38 | E18: BUYER-CREATED | F18: RECURRING | G18: COST
A19: CONSOLIDATED PLATFORM EBITDA — YEAR 7 | C19: ='Operating Case'!K$79 -> 2910357.8
A20: Tagged rows reconstruct the total — must be nil | C20: =C19-SUM(C5:C18) -> 0
A21: Nearshore delivery saving is inside the replacement line above and is never a separate bridge row | C21: ='Org & Capacity'!$D$259 -> 1532367.6
A23: Value creation by category, Year 7
A24: Acquired, recurring | C24: =C5 -> 5171512
A25: Buyer-created revenue | C25: =C6+C16 -> 812885.67
A26: Buyer-created cost savings | C26: =C7+C11+C15 -> 8850194.6
A27: Buyer-created cost | C27: =C8+C9+C10+C13+C17+C18 -> -11089836
A28: Episodic | C28: =C12+C14 -> -834398.25
A29: =" Case shown: Base | "&Assumptions!$E$8&" | "&Assumptions!$E$9 -> Case shown: Base | FULL CASE |
A31: 1. OPERATING SNAPSHOT
A32: Line | D32: Close | E32: Year 1 | F32: Year 2 | G32: Year 3 | H32: Year 4 | I32: Year 5 | J32: Year 6 | K32: Year 7 | L32: Year 8 | M32: Year 9 | N32: Year 10
A33: Managed units | B33: units | C33: [C] | D33: ='Operating Case'!D$50 -> 7343.75 | E33: ='Operating Case'!E$50 -> 10097.656 | F33: ='Operating Case'!F$50 -> 15888.497 | G33: ='Operating Case'!G$50 -> 26492.36 | H33: ='Operating Case'!H$50 -> 37328.004 | I33: ='Operating Case'!I$50 -> 44168.302 | J33: ='Operating Case'!J$50 -> 50000 | K33: ='Operating Case'!K$50 -> 50000 | ... N33: ='Operating Case'!N$50 -> 50000
A34: Properties | B34: props | C34: [C] | D34: ='Operating Case'!D$51 -> 29.375 | E34: ='Operating Case'!E$51 -> 40.390625 | F34: ='Operating Case'!F$51 -> 63.553988 | G34: ='Operating Case'!G$51 -> 105.96944 | H34: ='Operating Case'!H$51 -> 149.31202 | I34: ='Operating Case'!I$51 -> 176.67321 | J34: ='Operating Case'!J$51 -> 200 | K34: ='Operating Case'!K$51 -> 200 | ... N34: ='Operating Case'!N$51 -> 200
A35: Clients | B35: clients | C35: [OQ] | D35: ='Operating Case'!D$52 -> 5.64 | E35: ='Operating Case'!E$52 -> 6.9425714 | F35: ='Operating Case'!F$52 -> 10.412685 | G35: ='Operating Case'!G$52 -> 14.769785 | H35: ='Operating Case'!H$52 -> 20.932123 | I35: ='Operating Case'!I$52 -> 24.875588 | J35: ='Operating Case'!J$52 -> 28.254815 | K35: ='Operating Case'!K$52 -> 28.330667 | ... N35: ='Operating Case'!N$52 -> 28.330667
A36: Equivalent regimes above baseline | B36: regimes | C36: [E] | D36: ='Operating Case'!D$53 -> 0.7625 | E36: ='Operating Case'!E$53 -> 1.1695536 | F36: ='Operating Case'!F$53 -> 2.2539642 | G36: ='Operating Case'!G$53 -> 3.6155579 | H36: ='Operating Case'!H$53 -> 5.5412883 | I36: ='Operating Case'!I$53 -> 6.7736212 | J36: ='Operating Case'!J$53 -> 7.8296296 | K36: ='Operating Case'!K$53 -> 7.8533333 | ... N36: ='Operating Case'!N$53 -> 7.8533333
A37: Recurring revenue | B37: $ | C37: [C] | D37: ='Operating Case'!D$54 -> 4799015.4 | E37: ='Operating Case'!E$54 -> 6598646.1 | F37: ='Operating Case'!F$54 -> 10382862 | G37: ='Operating Case'!G$54 -> 17312306 | H37: ='Operating Case'!H$54 -> 24393214 | I37: ='Operating Case'!I$54 -> 28863232 | J37: ='Operating Case'!J$54 -> 32674147 | K37: ='Operating Case'!K$54 -> 32674147 | ... N37: ='Operating Case'!N$54 -> 32674147
A38: Standalone acquired EBITDA | B38: $ | C38: [C] | D38: ='Operating Case'!D$55 -> 940000 | E38: ='Operating Case'!E$55 -> 1292500 | F38: ='Operating Case'!F$55 -> 1913840 | G38: ='Operating Case'!G$55 -> 3067380.7 | H38: ='Operating Case'!H$55 -> 4170543.9 | I38: ='Operating Case'!I$55 -> 4535738 | J38: ='Operating Case'!J$55 -> 4868429.8 | K38: ='Operating Case'!K$55 -> 5171512 | ... N38: ='Operating Case'!N$55 -> 4228547
A39: Integrated DealCo EBITDA | B39: $ | C39: [C] | D39: ='Operating Case'!D$76 -> -416363.34 | E39: ='Operating Case'!E$76 -> -314237.59 | F39: ='Operating Case'!F$76 -> 619888.55 | G39: ='Operating Case'!G$76 -> 1893784.4 | H39: ='Operating Case'!H$76 -> 3379256.8 | I39: ='Operating Case'!I$76 -> 4732208.3 | J39: ='Operating Case'!J$76 -> 5366817 | K39: ='Operating Case'!K$76 -> 5875761.4 | ... N39: ='Operating Case'!N$76 -> 4979305.6
A40: Consolidated platform EBITDA | B40: $ | C40: [C] | D40: ='Operating Case'!D$79 -> -2562538.6 | E40: ='Operating Case'!E$79 -> -2666125.2 | F40: ='Operating Case'!F$79 -> -1823555.7 | G40: ='Operating Case'!G$79 -> -645223.17 | H40: ='Operating Case'!H$79 -> 740483.36 | I40: ='Operating Case'!I$79 -> 1989260.4 | J40: ='Operating Case'!J$79 -> 2515068.6 | K40: ='Operating Case'!K$79 -> 2910357.8 | ... N40: ='Operating Case'!N$79 -> 1641331.6
A41: PMC-borne corporate FTE | B41: FTE | C41: [C] | D41: ='Operating Case'!D$84 -> 19 | E41: ='Operating Case'!E$84 -> 27.407813 | F41: ='Operating Case'!F$84 -> 31.87108 | G41: ='Operating Case'!G$84 -> 43.719389 | H41: ='Operating Case'!H$84 -> 57.586241 | I41: ='Operating Case'!I$84 -> 63.133465 | J41: ='Operating Case'!J$84 -> 68.6 | K41: ='Operating Case'!K$84 -> 68.6 | ... N41: ='Operating Case'!N$84 -> 68.6
A42: Owner-reimbursed onsite FTE — memo | B42: FTE | C42: [F/C] | D42: ='Org & Capacity'!D$199 -> 178 | E42: ='Org & Capacity'!E$199 -> 244 | F42: ='Org & Capacity'!F$199 -> 382 | G42: ='Org & Capacity'!G$199 -> 633 | H42: ='Org & Capacity'!H$199 -> 894 | I42: ='Org & Capacity'!I$199 -> 1056 | J42: ='Org & Capacity'!J$199 -> 1193 | K42: ='Org & Capacity'!K$199 -> 1193 | ... N42: ='Org & Capacity'!N$199 -> 1193
A43: Recurring capex | B43: $ | C43: [A] | D43: ='Operating Case'!D$81 -> -183593.75 | E43: ='Operating Case'!E$81 -> -252441.41 | F43: ='Operating Case'!F$81 -> -397212.42 | G43: ='Operating Case'!G$81 -> -662309.01 | H43: ='Operating Case'!H$81 -> -933200.1 | I43: ='Operating Case'!I$81 -> -1104207.6 | J43: ='Operating Case'!J$81 -> -1250000 | K43: ='Operating Case'!K$81 -> -1250000 | ... N43: ='Operating Case'!N$81 -> -1250000
A44: Net debt | B44: $ | C44: [C] | D44: ='Transaction & Liquidity'!D$117 -> -600000 | E44: ='Transaction & Liquidity'!E$117 -> -150000 | F44: ='Transaction & Liquidity'!F$117 -> 690882.6 | G44: ='Transaction & Liquidity'!G$117 -> 5901794.3 | H44: ='Transaction & Liquidity'!H$117 -> 6995206.1 | I44: ='Transaction & Liquidity'!I$117 -> 7083617.8 | J44: ='Transaction & Liquidity'!J$117 -> 7517029.6 | K44: ='Transaction & Liquidity'!K$117 -> 7845441.3 | ... N44: ='Transaction & Liquidity'!N$117 -> 2890676.5
A45: Cumulative sponsor equity | B45: $ | C45: [C] | D45: ='Transaction & Liquidity'!D$116 -> 8437694.8 | E45: ='Transaction & Liquidity'!E$116 -> 14385597 | F45: ='Transaction & Liquidity'!F$116 -> 19361698 | G45: ='Transaction & Liquidity'!G$116 -> 27397568 | H45: ='Transaction & Liquidity'!H$116 -> 30740365 | I45: ='Transaction & Liquidity'!I$116 -> 33978631 | J45: ='Transaction & Liquidity'!J$116 -> 36500104 | K45: ='Transaction & Liquidity'!K$116 -> 38639177 | ... N45: ='Transaction & Liquidity'!N$116 -> 41416304
A47: 2. STANDALONE EBITDA BY ACQUISITION COHORT (before any buyer-created economics)
A48: Line | D48: Close | E48: Year 1 | F48: Year 2 | G48: Year 3 | H48: Year 4 | I48: Year 5 | J48: Year 6 | K48: Year 7 | L48: Year 8 | M48: Year 9 | N48: Year 10
A49: Anchor | B49: $ | C49: [C] | D49: ='Revenue & Durability'!D$81 -> 940000 | E49: ='Revenue & Durability'!E$81 -> 940000 | F49: ='Revenue & Durability'!F$81 -> 856340 | G49: ='Revenue & Durability'!G$81 -> 780125.74 | H49: ='Revenue & Durability'!H$81 -> 710694.55 | I49: ='Revenue & Durability'!I$81 -> 647442.73 | J49: ='Revenue & Durability'!J$81 -> 589820.33 | K49: ='Revenue & Durability'!K$81 -> 537326.32 | ... N49: ='Revenue & Durability'!N$81 -> 406249.88
A50: Vintage Year 1 | B50: $ | C50: [C] | D50: ='Revenue & Durability'!D$82 -> 0 | E50: ='Revenue & Durability'!E$82 -> 352500 | F50: ='Revenue & Durability'!F$82 -> 705000 | G50: ='Revenue & Durability'!G$82 -> 642255 | H50: ='Revenue & Durability'!H$82 -> 585094.31 | I50: ='Revenue & Durability'!I$82 -> 533020.91 | J50: ='Revenue & Durability'!J$82 -> 485582.05 | K50: ='Revenue & Durability'!K$82 -> 442365.25 | ... N50: ='Revenue & Durability'!N$82 -> 334453.8
A51: Vintage Year 2 | B51: $ | C51: [C] | D51: ='Revenue & Durability'!D$83 -> 0 | E51: ='Revenue & Durability'!E$83 -> 0 | F51: ='Revenue & Durability'!F$83 -> 352500 | G51: ='Revenue & Durability'!G$83 -> 705000 | H51: ='Revenue & Durability'!H$83 -> 642255 | I51: ='Revenue & Durability'!I$83 -> 585094.31 | J51: ='Revenue & Durability'!J$83 -> 533020.91 | K51: ='Revenue & Durability'!K$83 -> 485582.05 | ... N51: ='Revenue & Durability'!N$83 -> 367128.21
A52: Vintage Year 3 | B52: $ | C52: [C] | D52: ='Revenue & Durability'!D$84 -> 0 | E52: ='Revenue & Durability'!E$84 -> 0 | F52: ='Revenue & Durability'!F$84 -> 0 | G52: ='Revenue & Durability'!G$84 -> 940000 | H52: ='Revenue & Durability'!H$84 -> 1880000 | I52: ='Revenue & Durability'!I$84 -> 1712680 | J52: ='Revenue & Durability'!J$84 -> 1560251.5 | K52: ='Revenue & Durability'!K$84 -> 1421389.1 | ... N52: ='Revenue & Durability'!N$84 -> 1074652.6
A53: Vintage Year 4 | B53: $ | C53: [C] | D53: ='Revenue & Durability'!D$85 -> 0 | E53: ='Revenue & Durability'!E$85 -> 0 | F53: ='Revenue & Durability'!F$85 -> 0 | G53: ='Revenue & Durability'!G$85 -> 0 | H53: ='Revenue & Durability'!H$85 -> 352500 | I53: ='Revenue & Durability'!I$85 -> 705000 | J53: ='Revenue & Durability'!J$85 -> 642255 | K53: ='Revenue & Durability'!K$85 -> 585094.31 | ... N53: ='Revenue & Durability'!N$85 -> 442365.25
A54: Vintage Year 5 | B54: $ | C54: [C] | D54: ='Revenue & Durability'!D$86 -> 0 | E54: ='Revenue & Durability'!E$86 -> 0 | F54: ='Revenue & Durability'!F$86 -> 0 | G54: ='Revenue & Durability'!G$86 -> 0 | H54: ='Revenue & Durability'!H$86 -> 0 | I54: ='Revenue & Durability'!I$86 -> 352500 | J54: ='Revenue & Durability'!J$86 -> 705000 | K54: ='Revenue & Durability'!K$86 -> 642255 | ... N54: ='Revenue & Durability'!N$86 -> 485582.05
A55: Vintage Year 6 | B55: $ | C55: [C] | D55: ='Revenue & Durability'!D$87 -> 0 | E55: ='Revenue & Durability'!E$87 -> 0 | F55: ='Revenue & Durability'!F$87 -> 0 | G55: ='Revenue & Durability'!G$87 -> 0 | H55: ='Revenue & Durability'!H$87 -> 0 | I55: ='Revenue & Durability'!I$87 -> 0 | J55: ='Revenue & Durability'!J$87 -> 352500 | K55: ='Revenue & Durability'!K$87 -> 705000 | ... N55: ='Revenue & Durability'!N$87 -> 533020.91
A56: Vintage Year 7 | B56: $ | C56: [C] | D56: ='Revenue & Durability'!D$88 -> 0 | E56: ='Revenue & Durability'!E$88 -> 0 | F56: ='Revenue & Durability'!F$88 -> 0 | G56: ='Revenue & Durability'!G$88 -> 0 | H56: ='Revenue & Durability'!H$88 -> 0 | I56: ='Revenue & Durability'!I$88 -> 0 | J56: ='Revenue & Durability'!J$88 -> 0 | K56: ='Revenue & Durability'!K$88 -> 352500 | ... N56: ='Revenue & Durability'!N$88 -> 585094.31
A57: Total standalone EBITDA | B57: $ | C57: [C] | D57: =SUM(D49:D56) -> 940000 | E57: =SUM(E49:E56) -> 1292500 | F57: =SUM(F49:F56) -> 1913840 | G57: =SUM(G49:G56) -> 3067380.7 | H57: =SUM(H49:H56) -> 4170543.9 | I57: =SUM(I49:I56) -> 4535738 | J57: =SUM(J49:J56) -> 4868429.8 | K57: =SUM(K49:K56) -> 5171512 | ... N57: =SUM(N49:N56) -> 4228547
A58: Reconciliation to Operating Case | B58: $ | C58: [C] | D58: =D57-'Operating Case'!D$55 -> 0 | E58: =E57-'Operating Case'!E$55 -> 0 | F58: =F57-'Operating Case'!F$55 -> 0 | G58: =G57-'Operating Case'!G$55 -> 0 | H58: =H57-'Operating Case'!H$55 -> 0 | I58: =I57-'Operating Case'!I$55 -> 0 | J58: =J57-'Operating Case'!J$55 -> 0 | K58: =K57-'Operating Case'!K$55 -> 0 | ... N58: =N57-'Operating Case'!N$55 -> 0
A60: 3. COHORT EBITDA AFTER ALLOCATED SHARED SERVICES — DIAGNOSTIC ALLOCATION, NOT THE LIVE GROUP CALCULATION
A61: Group platform cost allocated pro rata on retained EBITDA so each deal can be seen standing on its own. The allocation is a diagnostic; the live group calculation is section 4.
A62: Line | D62: Close | E62: Year 1 | F62: Year 2 | G62: Year 3 | H62: Year 4 | I62: Year 5 | J62: Year 6 | K62: Year 7 | L62: Year 8 | M62: Year 9 | N62: Year 10
A63: Anchor | B63: $ | C63: [C] | D63: ='Revenue & Durability'!D$81+IF(D57=0,0,'Revenue & Durability'!D$81/D57*('Operating Case'!D$79-D57)) -> -2562538.6 | E63: ='Revenue & Durability'!E$81+IF(E57=0,0,'Revenue & Durability'!E$81/E57*('Operating Case'!E$79-E57)) -> -1939000.2 | F63: ='Revenue & Durability'!F$81+IF(F57=0,0,'Revenue & Durability'!F$81/F57*('Operating Case'!F$79-F57)) -> -815942.66 | G63: ='Revenue & Durability'!G$81+IF(G57=0,0,'Revenue & Durability'!G$81/G57*('Operating Case'!G$79-G57)) -> -164099.36 | H63: ='Revenue & Durability'!H$81+IF(H57=0,0,'Revenue & Durability'!H$81/H57*('Operating Case'!H$79-H57)) -> 126184.38 | I63: ='Revenue & Durability'!I$81+IF(I57=0,0,'Revenue & Durability'!I$81/I57*('Operating Case'!I$79-I57)) -> 283952.07 | J63: ='Revenue & Durability'!J$81+IF(J57=0,0,'Revenue & Durability'!J$81/J57*('Operating Case'!J$79-J57)) -> 304705.76 | K63: ='Revenue & Durability'!K$81+IF(K57=0,0,'Revenue & Durability'!K$81/K57*('Operating Case'!K$79-K57)) -> 302389.68 | ... N63: ='Revenue & Durability'!N$81+IF(N57=0,0,'Revenue & Durability'!N$81/N57*('Operating Case'!N$79-N57)) -> 157687.92
A64: Vintage Year 1 | B64: $ | C64: [C] | D64: ='Revenue & Durability'!D$82+IF(D57=0,0,'Revenue & Durability'!D$82/D57*('Operating Case'!D$79-D57)) -> 0 | E64: ='Revenue & Durability'!E$82+IF(E57=0,0,'Revenue & Durability'!E$82/E57*('Operating Case'!E$79-E57)) -> -727125.06 | F64: ='Revenue & Durability'!F$82+IF(F57=0,0,'Revenue & Durability'!F$82/F57*('Operating Case'!F$79-F57)) -> -671742.03 | G64: ='Revenue & Durability'!G$82+IF(G57=0,0,'Revenue & Durability'!G$82/G57*('Operating Case'!G$79-G57)) -> -135098.26 | H64: ='Revenue & Durability'!H$82+IF(H57=0,0,'Revenue & Durability'!H$82/H57*('Operating Case'!H$79-H57)) -> 103883.96 | I64: ='Revenue & Durability'!I$82+IF(I57=0,0,'Revenue & Durability'!I$82/I57*('Operating Case'!I$79-I57)) -> 233769.54 | J64: ='Revenue & Durability'!J$82+IF(J57=0,0,'Revenue & Durability'!J$82/J57*('Operating Case'!J$79-J57)) -> 250855.45 | K64: ='Revenue & Durability'!K$82+IF(K57=0,0,'Revenue & Durability'!K$82/K57*('Operating Case'!K$79-K57)) -> 248948.69 | ... N64: ='Revenue & Durability'!N$82+IF(N57=0,0,'Revenue & Durability'!N$82/N57*('Operating Case'!N$79-N57)) -> 129819.91
A65: Vintage Year 2 | B65: $ | C65: [C] | D65: ='Revenue & Durability'!D$83+IF(D57=0,0,'Revenue & Durability'!D$83/D57*('Operating Case'!D$79-D57)) -> 0 | E65: ='Revenue & Durability'!E$83+IF(E57=0,0,'Revenue & Durability'!E$83/E57*('Operating Case'!E$79-E57)) -> 0 | F65: ='Revenue & Durability'!F$83+IF(F57=0,0,'Revenue & Durability'!F$83/F57*('Operating Case'!F$79-F57)) -> -335871.02 | G65: ='Revenue & Durability'!G$83+IF(G57=0,0,'Revenue & Durability'!G$83/G57*('Operating Case'!G$79-G57)) -> -148296.66 | H65: ='Revenue & Durability'!H$83+IF(H57=0,0,'Revenue & Durability'!H$83/H57*('Operating Case'!H$79-H57)) -> 114032.88 | I65: ='Revenue & Durability'!I$83+IF(I57=0,0,'Revenue & Durability'!I$83/I57*('Operating Case'!I$79-I57)) -> 256607.62 | J65: ='Revenue & Durability'!J$83+IF(J57=0,0,'Revenue & Durability'!J$83/J57*('Operating Case'!J$79-J57)) -> 275362.73 | K65: ='Revenue & Durability'!K$83+IF(K57=0,0,'Revenue & Durability'!K$83/K57*('Operating Case'!K$79-K57)) -> 273269.69 | ... N65: ='Revenue & Durability'!N$83+IF(N57=0,0,'Revenue & Durability'!N$83/N57*('Operating Case'!N$79-N57)) -> 142502.65
A66: Vintage Year 3 | B66: $ | C66: [C] | D66: ='Revenue & Durability'!D$84+IF(D57=0,0,'Revenue & Durability'!D$84/D57*('Operating Case'!D$79-D57)) -> 0 | E66: ='Revenue & Durability'!E$84+IF(E57=0,0,'Revenue & Durability'!E$84/E57*('Operating Case'!E$79-E57)) -> 0 | F66: ='Revenue & Durability'!F$84+IF(F57=0,0,'Revenue & Durability'!F$84/F57*('Operating Case'!F$79-F57)) -> 0 | G66: ='Revenue & Durability'!G$84+IF(G57=0,0,'Revenue & Durability'!G$84/G57*('Operating Case'!G$79-G57)) -> -197728.89 | H66: ='Revenue & Durability'!H$84+IF(H57=0,0,'Revenue & Durability'!H$84/H57*('Operating Case'!H$79-H57)) -> 333795.48 | I66: ='Revenue & Durability'!I$84+IF(I57=0,0,'Revenue & Durability'!I$84/I57*('Operating Case'!I$79-I57)) -> 751138.3 | J66: ='Revenue & Durability'!J$84+IF(J57=0,0,'Revenue & Durability'!J$84/J57*('Operating Case'!J$79-J57)) -> 806038.01 | K66: ='Revenue & Durability'!K$84+IF(K57=0,0,'Revenue & Durability'!K$84/K57*('Operating Case'!K$79-K57)) -> 799911.28 | ... N66: ='Revenue & Durability'!N$84+IF(N57=0,0,'Revenue & Durability'!N$84/N57*('Operating Case'!N$79-N57)) -> 417131.78
A67: Vintage Year 4 | B67: $ | C67: [C] | D67: ='Revenue & Durability'!D$85+IF(D57=0,0,'Revenue & Durability'!D$85/D57*('Operating Case'!D$79-D57)) -> 0 | E67: ='Revenue & Durability'!E$85+IF(E57=0,0,'Revenue & Durability'!E$85/E57*('Operating Case'!E$79-E57)) -> 0 | F67: ='Revenue & Durability'!F$85+IF(F57=0,0,'Revenue & Durability'!F$85/F57*('Operating Case'!F$79-F57)) -> 0 | G67: ='Revenue & Durability'!G$85+IF(G57=0,0,'Revenue & Durability'!G$85/G57*('Operating Case'!G$79-G57)) -> 0 | H67: ='Revenue & Durability'!H$85+IF(H57=0,0,'Revenue & Durability'!H$85/H57*('Operating Case'!H$79-H57)) -> 62586.653 | I67: ='Revenue & Durability'!I$85+IF(I57=0,0,'Revenue & Durability'!I$85/I57*('Operating Case'!I$79-I57)) -> 309195.24 | J67: ='Revenue & Durability'!J$85+IF(J57=0,0,'Revenue & Durability'!J$85/J57*('Operating Case'!J$79-J57)) -> 331793.91 | K67: ='Revenue & Durability'!K$85+IF(K57=0,0,'Revenue & Durability'!K$85/K57*('Operating Case'!K$79-K57)) -> 329271.93 | ... N67: ='Revenue & Durability'!N$85+IF(N57=0,0,'Revenue & Durability'!N$85/N57*('Operating Case'!N$79-N57)) -> 171706.28
A68: Vintage Year 5 | B68: $ | C68: [C] | D68: ='Revenue & Durability'!D$86+IF(D57=0,0,'Revenue & Durability'!D$86/D57*('Operating Case'!D$79-D57)) -> 0 | E68: ='Revenue & Durability'!E$86+IF(E57=0,0,'Revenue & Durability'!E$86/E57*('Operating Case'!E$79-E57)) -> 0 | F68: ='Revenue & Durability'!F$86+IF(F57=0,0,'Revenue & Durability'!F$86/F57*('Operating Case'!F$79-F57)) -> 0 | G68: ='Revenue & Durability'!G$86+IF(G57=0,0,'Revenue & Durability'!G$86/G57*('Operating Case'!G$79-G57)) -> 0 | H68: ='Revenue & Durability'!H$86+IF(H57=0,0,'Revenue & Durability'!H$86/H57*('Operating Case'!H$79-H57)) -> 0 | I68: ='Revenue & Durability'!I$86+IF(I57=0,0,'Revenue & Durability'!I$86/I57*('Operating Case'!I$79-I57)) -> 154597.62 | J68: ='Revenue & Durability'!J$86+IF(J57=0,0,'Revenue & Durability'!J$86/J57*('Operating Case'!J$79-J57)) -> 364208.46 | K68: ='Revenue & Durability'!K$86+IF(K57=0,0,'Revenue & Durability'!K$86/K57*('Operating Case'!K$79-K57)) -> 361440.1 | ... N68: ='Revenue & Durability'!N$86+IF(N57=0,0,'Revenue & Durability'!N$86/N57*('Operating Case'!N$79-N57)) -> 188481.1
A69: Vintage Year 6 | B69: $ | C69: [C] | D69: ='Revenue & Durability'!D$87+IF(D57=0,0,'Revenue & Durability'!D$87/D57*('Operating Case'!D$79-D57)) -> 0 | E69: ='Revenue & Durability'!E$87+IF(E57=0,0,'Revenue & Durability'!E$87/E57*('Operating Case'!E$79-E57)) -> 0 | F69: ='Revenue & Durability'!F$87+IF(F57=0,0,'Revenue & Durability'!F$87/F57*('Operating Case'!F$79-F57)) -> 0 | G69: ='Revenue & Durability'!G$87+IF(G57=0,0,'Revenue & Durability'!G$87/G57*('Operating Case'!G$79-G57)) -> 0 | H69: ='Revenue & Durability'!H$87+IF(H57=0,0,'Revenue & Durability'!H$87/H57*('Operating Case'!H$79-H57)) -> 0 | I69: ='Revenue & Durability'!I$87+IF(I57=0,0,'Revenue & Durability'!I$87/I57*('Operating Case'!I$79-I57)) -> 0 | J69: ='Revenue & Durability'!J$87+IF(J57=0,0,'Revenue & Durability'!J$87/J57*('Operating Case'!J$79-J57)) -> 182104.23 | K69: ='Revenue & Durability'!K$87+IF(K57=0,0,'Revenue & Durability'!K$87/K57*('Operating Case'!K$79-K57)) -> 396750.94 | ... N69: ='Revenue & Durability'!N$87+IF(N57=0,0,'Revenue & Durability'!N$87/N57*('Operating Case'!N$79-N57)) -> 206894.73
A70: Vintage Year 7 | B70: $ | C70: [C] | D70: ='Revenue & Durability'!D$88+IF(D57=0,0,'Revenue & Durability'!D$88/D57*('Operating Case'!D$79-D57)) -> 0 | E70: ='Revenue & Durability'!E$88+IF(E57=0,0,'Revenue & Durability'!E$88/E57*('Operating Case'!E$79-E57)) -> 0 | F70: ='Revenue & Durability'!F$88+IF(F57=0,0,'Revenue & Durability'!F$88/F57*('Operating Case'!F$79-F57)) -> 0 | G70: ='Revenue & Durability'!G$88+IF(G57=0,0,'Revenue & Durability'!G$88/G57*('Operating Case'!G$79-G57)) -> 0 | H70: ='Revenue & Durability'!H$88+IF(H57=0,0,'Revenue & Durability'!H$88/H57*('Operating Case'!H$79-H57)) -> 0 | I70: ='Revenue & Durability'!I$88+IF(I57=0,0,'Revenue & Durability'!I$88/I57*('Operating Case'!I$79-I57)) -> 0 | J70: ='Revenue & Durability'!J$88+IF(J57=0,0,'Revenue & Durability'!J$88/J57*('Operating Case'!J$79-J57)) -> 0 | K70: ='Revenue & Durability'!K$88+IF(K57=0,0,'Revenue & Durability'!K$88/K57*('Operating Case'!K$79-K57)) -> 198375.47 | ... N70: ='Revenue & Durability'!N$88+IF(N57=0,0,'Revenue & Durability'!N$88/N57*('Operating Case'!N$79-N57)) -> 227107.27
A71: Total after allocated shared services | B71: $ | C71: [C] | D71: =SUM(D63:D70) -> -2562538.6 | E71: =SUM(E63:E70) -> -2666125.2 | F71: =SUM(F63:F70) -> -1823555.7 | G71: =SUM(G63:G70) -> -645223.17 | H71: =SUM(H63:H70) -> 740483.36 | I71: =SUM(I63:I70) -> 1989260.4 | J71: =SUM(J63:J70) -> 2515068.6 | K71: =SUM(K63:K70) -> 2910357.8 | ... N71: =SUM(N63:N70) -> 1641331.6
A72: Reconciliation to consolidated platform EBITDA | B72: $ | C72: [C] | D72: =D71-'Operating Case'!D$79 -> 0 | E72: =E71-'Operating Case'!E$79 -> 0 | F72: =F71-'Operating Case'!F$79 -> 0 | G72: =G71-'Operating Case'!G$79 -> 0 | H72: =H71-'Operating Case'!H$79 -> 0 | I72: =I71-'Operating Case'!I$79 -> 0 | J72: =J71-'Operating Case'!J$79 -> 0 | K72: =K71-'Operating Case'!K$79 -> 0 | ... N72: =N71-'Operating Case'!N$79 -> 0
A74: 4. GROUP EBITDA BRIDGE — ACTUAL MODEL ECONOMICS
A75: Line | D75: Close | E75: Year 1 | F75: Year 2 | G75: Year 3 | H75: Year 4 | I75: Year 5 | J75: Year 6 | K75: Year 7 | L75: Year 8 | M75: Year 9 | N75: Year 10
A76: Contracted acquired EBITDA — all cohorts | B76: $ | C76: [C] | D76: ='Operating Case'!D$55 -> 940000 | E76: ='Operating Case'!E$55 -> 1292500 | F76: ='Operating Case'!F$55 -> 1913840 | G76: ='Operating Case'!G$55 -> 3067380.7 | H76: ='Operating Case'!H$55 -> 4170543.9 | I76: ='Operating Case'!I$55 -> 4535738 | J76: ='Operating Case'!J$55 -> 4868429.8 | K76: ='Operating Case'!K$55 -> 5171512 | ... N76: ='Operating Case'!N$55 -> 4228547
A77: Buyer-created organic new business | B77: $ | C77: [A] | D77: ='Operating Case'!D$56 -> 0 | E77: ='Operating Case'!E$56 -> 0 | F77: ='Operating Case'!F$56 -> 119887.6 | G77: ='Operating Case'!G$56 -> 323641.37 | H77: ='Operating Case'!H$56 -> 607440.65 | I77: ='Operating Case'!I$56 -> 1117804.7 | J77: ='Operating Case'!J$56 -> 1531570.2 | K77: ='Operating Case'!K$56 -> 1228488 | ... N77: ='Operating Case'!N$56 -> 2171453
A78: Local payroll removed by centralisation | B78: $ | C78: [C] | D78: ='Operating Case'!D$58 -> 1342318.7 | E78: ='Operating Case'!E$58 -> 1819819.1 | F78: ='Operating Case'!F$58 -> 2735014 | G78: ='Operating Case'!G$58 -> 4537674.5 | H78: ='Operating Case'!H$58 -> 6372007.1 | I78: ='Operating Case'!I$58 -> 7101738.5 | J78: ='Operating Case'!J$58 -> 7820148.1 | K78: ='Operating Case'!K$58 -> 8528944.6 | ... N78: ='Operating Case'!N$58 -> 7609399.9
A79: Replacement shared-services payroll | B79: $ | C79: [C] | D79: ='Operating Case'!D$59 -> -862012.63 | E79: ='Operating Case'!E$59 -> -1740982.3 | F79: ='Operating Case'!F$59 -> -2343782.8 | G79: ='Operating Case'!G$59 -> -3790121.1 | H79: ='Operating Case'!H$59 -> -5211901 | I79: ='Operating Case'!I$59 -> -6143522.1 | J79: ='Operating Case'!J$59 -> -6948193.3 | K79: ='Operating Case'!K$59 -> -7156639.1 | ... N79: ='Operating Case'!N$59 -> -7820252.8
A80: Transition-overlap duplicated payroll | B80: $ | C80: [D] | D80: ='Operating Case'!D$60 -> -671159.37 | E80: ='Operating Case'!E$60 -> -238750.17 | F80: ='Operating Case'!F$60 -> -457597.46 | G80: ='Operating Case'!G$60 -> -901330.26 | H80: ='Operating Case'!H$60 -> -917166.31 | I80: ='Operating Case'!I$60 -> -364865.68 | J80: ='Operating Case'!J$60 -> -359204.8 | K80: ='Operating Case'!K$60 -> -354398.25 | ... N80: ='Operating Case'!N$60 -> 0
A81: Leadership redundancy saving | B81: $ | C81: [A] | D81: ='Operating Case'!D$61 -> 0 | E81: ='Operating Case'!E$61 -> 0 | F81: ='Operating Case'!F$61 -> 0 | G81: ='Operating Case'!G$61 -> 0 | H81: ='Operating Case'!H$61 -> 0 | I81: ='Operating Case'!I$61 -> 0 | J81: ='Operating Case'!J$61 -> 0 | K81: ='Operating Case'!K$61 -> 0 | ... N81: ='Operating Case'!N$61 -> 0
A82: Customer-complexity payroll | B82: $ | C82: [E] | D82: ='Operating Case'!D$62 -> -685510.07 | E82: ='Operating Case'!E$62 -> -685510.07 | F82: ='Operating Case'!F$62 -> -706075.38 | G82: ='Operating Case'!G$62 -> -727257.64 | H82: ='Operating Case'!H$62 -> -885668.21 | I82: ='Operating Case'!I$62 -> -912238.26 | J82: ='Operating Case'!J$62 -> -939605.4 | K82: ='Operating Case'!K$62 -> -967793.57 | ... N82: ='Operating Case'!N$62 -> -1057534.2
A83: Layer 2 delivery payroll | B83: $ | C83: [A] | D83: ='Operating Case'!D$63 -> 0 | E83: ='Operating Case'!E$63 -> -343396 | F83: ='Operating Case'!F$63 -> -353697.88 | G83: ='Operating Case'!G$63 -> -564396.22 | H83: ='Operating Case'!H$63 -> -956566.18 | I83: ='Operating Case'!I$63 -> -985263.17 | J83: ='Operating Case'!J$63 -> -1117227.9 | K83: ='Operating Case'!K$63 -> -1150744.7 | ... N83: ='Operating Case'!N$63 -> -1257449.8
A84: Integration pod cost | B84: $ | C84: [A] | D84: ='Operating Case'!D$64 -> -480000 | E84: ='Operating Case'!E$64 -> -480000 | F84: ='Operating Case'!F$64 -> -480000 | G84: ='Operating Case'!G$64 -> -480000 | H84: ='Operating Case'!H$64 -> -480000 | I84: ='Operating Case'!I$64 -> -480000 | J84: ='Operating Case'!J$64 -> -480000 | K84: ='Operating Case'!K$64 -> -480000 | ... N84: ='Operating Case'!N$64 -> 0
A85: Other integration savings | B85: $ | C85: [A] | D85: ='Operating Case'!D$65 -> 0 | E85: ='Operating Case'!E$65 -> 28750 | F85: ='Operating Case'!F$65 -> 71250 | G85: ='Operating Case'!G$65 -> 115000 | H85: ='Operating Case'!H$65 -> 183750 | I85: ='Operating Case'!I$65 -> 246250 | J85: ='Operating Case'!J$65 -> 283750 | K85: ='Operating Case'!K$65 -> 321250 | ... N85: ='Operating Case'!N$65 -> 370000
A86: EBITDA after shared services, before products | B86: $ | C86: [C] | D86: =D76+D77+D78+D79+D80+D81+D82+D83+D84+D85 -> -416363.34 | E86: =E76+E77+E78+E79+E80+E81+E82+E83+E84+E85 -> -347569.44 | F86: =F76+F77+F78+F79+F80+F81+F82+F83+F84+F85 -> 498838.06 | G86: =G76+G77+G78+G79+G80+G81+G82+G83+G84+G85 -> 1580591.4 | H86: =H76+H77+H78+H79+H80+H81+H82+H83+H84+H85 -> 2882439.9 | I86: =I76+I77+I78+I79+I80+I81+I82+I83+I84+I85 -> 4115642 | J86: =J76+J77+J78+J79+J80+J81+J82+J83+J84+J85 -> 4659666.7 | K86: =K76+K77+K78+K79+K80+K81+K82+K83+K84+K85 -> 5140619 | ... N86: =N76+N77+N78+N79+N80+N81+N82+N83+N84+N85 -> 4244163.2
A87: Layer 1 net contribution | B87: $ | C87: [A] | D87: ='Operating Case'!D$67+'Operating Case'!D$68 -> 0 | E87: ='Operating Case'!E$67+'Operating Case'!E$68 -> 22618.75 | F87: ='Operating Case'!F$67+'Operating Case'!F$68 -> 71180.466 | G87: ='Operating Case'!G$67+'Operating Case'!G$68 -> 178028.66 | H87: ='Operating Case'!H$67+'Operating Case'!H$68 -> 250844.19 | I87: ='Operating Case'!I$67+'Operating Case'!I$68 -> 296810.99 | J87: ='Operating Case'!J$67+'Operating Case'!J$68 -> 336000 | K87: ='Operating Case'!K$67+'Operating Case'!K$68 -> 336000 | ... N87: ='Operating Case'!N$67+'Operating Case'!N$68 -> 336000
A88: Layer 2 net contribution before delivery payroll | B88: $ | C88: [A] | D88: ='Operating Case'!D$69+'Operating Case'!D$70 -> 0 | E88: ='Operating Case'!E$69+'Operating Case'!E$70 -> 16098.517 | F88: ='Operating Case'!F$69+'Operating Case'!F$70 -> 50661.507 | G88: ='Operating Case'!G$69+'Operating Case'!G$70 -> 126708.92 | H88: ='Operating Case'!H$69+'Operating Case'!H$70 -> 178534.16 | I88: ='Operating Case'!I$69+'Operating Case'!I$70 -> 211250.26 | J88: ='Operating Case'!J$69+'Operating Case'!J$70 -> 239142.38 | K88: ='Operating Case'!K$69+'Operating Case'!K$70 -> 239142.38 | ... N88: ='Operating Case'!N$69+'Operating Case'!N$70 -> 239142.38
A89: Layer 3 net contribution | B89: $ | C89: [A] | D89: ='Operating Case'!D$71+'Operating Case'!D$72 -> 0 | E89: ='Operating Case'!E$71+'Operating Case'!E$72 -> 10770.833 | F89: ='Operating Case'!F$71+'Operating Case'!F$72 -> 33895.46 | G89: ='Operating Case'!G$71+'Operating Case'!G$72 -> 84775.553 | H89: ='Operating Case'!H$71+'Operating Case'!H$72 -> 119449.61 | I89: ='Operating Case'!I$71+'Operating Case'!I$72 -> 141338.57 | J89: ='Operating Case'!J$71+'Operating Case'!J$72 -> 160000 | K89: ='Operating Case'!K$71+'Operating Case'!K$72 -> 160000 | ... N89: ='Operating Case'!N$71+'Operating Case'!N$72 -> 160000
A90: Product implementation cost | B90: $ | C90: [A] | D90: ='Operating Case'!D$73 -> 0 | E90: ='Operating Case'!E$73 -> -16156.25 | F90: ='Operating Case'!F$73 -> -34686.94 | G90: ='Operating Case'!G$73 -> -76320.139 | H90: ='Operating Case'!H$73 -> -52011.09 | I90: ='Operating Case'!I$73 -> -32833.431 | J90: ='Operating Case'!J$73 -> -27992.15 | K90: ='Operating Case'!K$73 -> 0 | ... N90: ='Operating Case'!N$73 -> 0
A91: INTEGRATED DEALCO EBITDA | B91: $ | C91: [C] | D91: =D86+D87+D88+D89+D90 -> -416363.34 | E91: =E86+E87+E88+E89+E90 -> -314237.59 | F91: =F86+F87+F88+F89+F90 -> 619888.55 | G91: =G86+G87+G88+G89+G90 -> 1893784.4 | H91: =H86+H87+H88+H89+H90 -> 3379256.8 | I91: =I86+I87+I88+I89+I90 -> 4732208.3 | J91: =J86+J87+J88+J89+J90 -> 5366817 | K91: =K86+K87+K88+K89+K90 -> 5875761.4 | ... N91: =N86+N87+N88+N89+N90 -> 4979305.6
A92: Incremental HoldCo payroll | B92: $ | C92: [C] | D92: ='Operating Case'!D$77 -> -1446175.2 | E92: ='Operating Case'!E$77 -> -1651887.6 | F92: ='Operating Case'!F$77 -> -1701444.3 | G92: ='Operating Case'!G$77 -> -1752487.6 | H92: ='Operating Case'!H$77 -> -1805062.2 | I92: ='Operating Case'!I$77 -> -1859214.1 | J92: ='Operating Case'!J$77 -> -1914990.5 | K92: ='Operating Case'!K$77 -> -1972440.2 | ... N92: ='Operating Case'!N$77 -> -2155338.7
A93: HoldCo non-payroll G&A | B93: $ | C93: [A] | D93: ='Operating Case'!D$78 -> -700000 | E93: ='Operating Case'!E$78 -> -700000 | F93: ='Operating Case'!F$78 -> -742000 | G93: ='Operating Case'!G$78 -> -786520 | H93: ='Operating Case'!H$78 -> -833711.2 | I93: ='Operating Case'!I$78 -> -883733.87 | J93: ='Operating Case'!J$78 -> -936757.9 | K93: ='Operating Case'!K$78 -> -992963.38 | ... N93: ='Operating Case'!N$78 -> -1182635.3
A94: CONSOLIDATED PLATFORM EBITDA | B94: $ | C94: [C] | D94: =D91+D92+D93 -> -2562538.6 | E94: =E91+E92+E93 -> -2666125.2 | F94: =F91+F92+F93 -> -1823555.7 | G94: =G91+G92+G93 -> -645223.17 | H94: =H91+H92+H93 -> 740483.36 | I94: =I91+I92+I93 -> 1989260.4 | J94: =J91+J92+J93 -> 2515068.6 | K94: =K91+K92+K93 -> 2910357.8 | ... N94: =N91+N92+N93 -> 1641331.6
A95: Recurring capex | B95: $ | C95: [A] | D95: ='Operating Case'!D$81 -> -183593.75 | E95: ='Operating Case'!E$81 -> -252441.41 | F95: ='Operating Case'!F$81 -> -397212.42 | G95: ='Operating Case'!G$81 -> -662309.01 | H95: ='Operating Case'!H$81 -> -933200.1 | I95: ='Operating Case'!I$81 -> -1104207.6 | J95: ='Operating Case'!J$81 -> -1250000 | K95: ='Operating Case'!K$81 -> -1250000 | ... N95: ='Operating Case'!N$81 -> -1250000
A96: EBITDA less capex | B96: $ | C96: [C] | D96: =D94+D95 -> -2746132.3 | E96: =E94+E95 -> -2918566.6 | F96: =F94+F95 -> -2220768.1 | G96: =G94+G95 -> -1307532.2 | H96: =H94+H95 -> -192716.74 | I96: =I94+I95 -> 885052.84 | J96: =J94+J95 -> 1265068.6 | K96: =K94+K95 -> 1660357.8 | ... N96: =N94+N95 -> 391331.63
A97: Reconciliation to Operating Case | B97: $ | C97: [C] | D97: =D94-'Operating Case'!D$79 -> 0 | E97: =E94-'Operating Case'!E$79 -> 0 | F97: =F94-'Operating Case'!F$79 -> 0 | G97: =G94-'Operating Case'!G$79 -> 0 | H97: =H94-'Operating Case'!H$79 -> 0 | I97: =I94-'Operating Case'!I$79 -> 0 | J97: =J94-'Operating Case'!J$79 -> 0 | K97: =K94-'Operating Case'!K$79 -> 0 | ... N97: =N94-'Operating Case'!N$79 -> -1.8626451e-09
A99: 5. SPONSOR CASH AND RETURN BRIDGE
A100: Line | D100: Close | E100: Year 1 | F100: Year 2 | G100: Year 3 | H100: Year 4 | I100: Year 5 | J100: Year 6 | K100: Year 7 | L100: Year 8 | M100: Year 9 | N100: Year 10
A101: Acquisition equity funded | B101: $ | C101: [C] | D101: ='Transaction & Liquidity'!D$110 -> -5100000 | E101: ='Transaction & Liquidity'!E$110 -> -2550000 | F101: ='Transaction & Liquidity'!F$110 -> -2159117.4 | G101: ='Transaction & Liquidity'!G$110 -> -5250000 | H101: ='Transaction & Liquidity'!H$110 -> -1500000 | I101: ='Transaction & Liquidity'!I$110 -> -1500000 | J101: ='Transaction & Liquidity'!J$110 -> -1500000 | K101: ='Transaction & Liquidity'!K$110 -> -1500000 | ... N101: ='Transaction & Liquidity'!N$110 -> 0
A102: Transaction and integration cost | B102: $ | C102: [A] | D102: ='Transaction & Liquidity'!D$111 -> -430000 | E102: ='Transaction & Liquidity'!E$111 -> -340000 | F102: ='Transaction & Liquidity'!F$111 -> -340000 | G102: ='Transaction & Liquidity'!G$111 -> -815000 | H102: ='Transaction & Liquidity'!H$111 -> -340000 | I102: ='Transaction & Liquidity'!I$111 -> -340000 | J102: ='Transaction & Liquidity'!J$111 -> -340000 | K102: ='Transaction & Liquidity'!K$111 -> -340000 | ... N102: ='Transaction & Liquidity'!N$111 -> 0
A103: Operating equity cure | B103: $ | C103: [C] | D103: =-'Transaction & Liquidity'!D$114 -> -8437694.8 | E103: =-'Transaction & Liquidity'!E$114 -> -5947902.6 | F103: =-'Transaction & Liquidity'!F$114 -> -4976100.9 | G103: =-'Transaction & Liquidity'!G$114 -> -8035870.1 | H103: =-'Transaction & Liquidity'!H$114 -> -3342796.7 | I103: =-'Transaction & Liquidity'!I$114 -> -3238266.1 | J103: =-'Transaction & Liquidity'!J$114 -> -2521472.8 | K103: =-'Transaction & Liquidity'!K$114 -> -2139072.8 | ... N103: =-'Transaction & Liquidity'!N$114 -> -1334883.8
A104: Cumulative sponsor capital | B104: $ | C104: [C] | D104: ='Transaction & Liquidity'!D$116 -> 8437694.8 | E104: ='Transaction & Liquidity'!E$116 -> 14385597 | F104: ='Transaction & Liquidity'!F$116 -> 19361698 | G104: ='Transaction & Liquidity'!G$116 -> 27397568 | H104: ='Transaction & Liquidity'!H$116 -> 30740365 | I104: ='Transaction & Liquidity'!I$116 -> 33978631 | J104: ='Transaction & Liquidity'!J$116 -> 36500104 | K104: ='Transaction & Liquidity'!K$116 -> 38639177 | ... N104: ='Transaction & Liquidity'!N$116 -> 41416304
A105: Exit proceeds | B105: $ | C105: [C] | D105: =IF(0=INDEX(Assumptions!$D$13:$F$13,1,2),Returns!$E$51,0) -> 0 | E105: =IF(1=INDEX(Assumptions!$D$13:$F$13,1,2),Returns!$E$51,0) -> 0 | F105: =IF(2=INDEX(Assumptions!$D$13:$F$13,1,2),Returns!$E$51,0) -> 0 | G105: =IF(3=INDEX(Assumptions!$D$13:$F$13,1,2),Returns!$E$51,0) -> 0 | H105: =IF(4=INDEX(Assumptions!$D$13:$F$13,1,2),Returns!$E$51,0) -> 0 | I105: =IF(5=INDEX(Assumptions!$D$13:$F$13,1,2),Returns!$E$51,0) -> 0 | J105: =IF(6=INDEX(Assumptions!$D$13:$F$13,1,2),Returns!$E$51,0) -> 0 | K105: =IF(7=INDEX(Assumptions!$D$13:$F$13,1,2),Returns!$E$51,0) -> 19249990 | L105: =IF(8=INDEX(Assumptions!$D$13:$F$13,1,2),Returns!$E$51,0) -> 0 | M105: =IF(9=INDEX(Assumptions!$D$13:$F$13,1,2),Returns!$E$51,0) -> 0 | N105: =IF(10=INDEX(Assumptions!$D$13:$F$13,1,2),Returns!$E$51,0) -> 0
A106: Net sponsor cash flow | B106: $ | C106: [C] | D106: =-'Transaction & Liquidity'!D$114+D105 -> -8437694.8 | E106: =-'Transaction & Liquidity'!E$114+E105 -> -5947902.6 | F106: =-'Transaction & Liquidity'!F$114+F105 -> -4976100.9 | G106: =-'Transaction & Liquidity'!G$114+G105 -> -8035870.1 | H106: =-'Transaction & Liquidity'!H$114+H105 -> -3342796.7 | I106: =-'Transaction & Liquidity'!I$114+I105 -> -3238266.1 | J106: =-'Transaction & Liquidity'!J$114+J105 -> -2521472.8 | K106: =-'Transaction & Liquidity'!K$114+K105 -> 17110917 | ... N106: =-'Transaction & Liquidity'!N$114+N105 -> -1334883.8
A107: 7-year MOIC | B107: x | C107: [C] | D107: =Returns!$E$56 -> 0.49819875
...

Sheet Evidence & Market
A1: EVIDENCE AND MARKET
A2: Owner GL, PMA fee architecture, density rules, the named target universe and the compensation source register. Everything downstream reads from here; nothing here reads from anywhere else.
A4: 1. OWNER GENERAL LEDGER — Forum on San Felipe, Jan–Jul 2026, Pinnacle / Cushman & Wakefield
A5: Provided by Galium Capital. Proves what the owner pays. It does not reveal the manager delivery cost, so it evidences gross revenue architecture and willingness to pay, never retained margin.
A6: PMA residential units | C6: 361 | H6: Executed Forum PMA, section 1.2
A7: GL software and service billing units | C7: 368 | H7: $566.72/$1.54 and $570.40/$1.55 both resolve to 368. Open with Galium.
A8: Months in the YTD extract | C8: 7 | H8: January to July 2026, accrual basis
A9: Annualisation factor | C9: =12/C8 -> 1.7142857
A11: Fee category | B11: Classification | C11: Grade | D11: YTD GL | E11: Annualised | F11: $/PMA unit/yr | H11: Note
A12: Core management fee | B12: Core recurring fee | C12: [F] | D12: 107491.87 | E12: =D12*$C$9 -> 184271.78 | F12: =E12/$C$6 -> 510.44814 | H12: Account 4223-000.
A13: Benefits and payroll administration | B13: Inherited retained service | C13: [F] | D13: 7527.29 | E13: =D13*$C$9 -> 12903.926 | F13: =E13/$C$6 -> 35.744947 | H13: Account 4158-000. Three percent of onsite payroll under the PMA.
A14: Revenue-management pricing advisory | B14: Inherited retained service | C14: [F] | D14: 3992.8 | E14: =D14*$C$9 -> 6844.8 | F14: =E14/$C$6 -> 18.960665 | H14: $1.55 per unit per month. Direct overlap with buyer-created Layer 2.
A15: Training and operating platform | B15: Inherited retained service | C15: [F] | D15: 3967.04 | E15: =D15*$C$9 -> 6800.64 | F15: =E15/$C$6 -> 18.838338 | H15: $1.54 per unit per month. Direct overlap with buyer-created Layer 1.
A16: Applications and IT support | B16: Inherited retained service | C16: [F] | D16: 980 | E16: =D16*$C$9 -> 1680 | F16: =E16/$C$6 -> 4.6537396 | H16: $140 per month under the PMA.
A17: IT infrastructure and email licensing | B17: Inherited retained service | C17: [F] | D17: 3755 | E17: =D17 -> 3755 | F17: =E17/$C$6 -> 10.401662 | H17: Annual charge, not annualised.
A18: Yardi licensing | B18: Third-party pass-through | C18: [F] | D18: 11463.2 | E18: =D18*$C$9 -> 19651.2 | F18: =E18/$C$6 -> 54.435457 | H18: $4.45 per unit per month. Software licensing incurred by the manager for the property. Zero retained margin by construction.
A20: 2. EVIDENCED REVENUE ARCHITECTURE — drives Assumptions
A21: Core management fee per unit per year | B21: $/unit | C21: =F12 -> 510.44814 | H21: Replaces the $484 placeholder. Observed.
A22: Inherited retained-service revenue per unit | B22: $/unit | C22: =SUM(F13:F17) -> 88.599351 | H22: Gross billed for services the manager delivers. Upper bound before delivery cost, never margin.
A23: Third-party pass-through per unit | B23: $/unit | C23: =F18 -> 54.435457 | H23: In revenue, never in EBITDA contribution. Zero manager margin.
A24: Episodic project / construction / consulting fees per unit | B24: $/unit | C24: =0 -> 0 | H24: The PMA permits a 5% project-management fee and $135/hour consulting. Absent from this extract. Zero in Base until target history supports it.
A25: Total RECURRING billed to the owner per unit — excludes episodic | B25: $/unit | C25: =C21+C22+C23 -> 653.48294
A26: Platform-like services the incumbent already bills | B26: $/unit | C26: =F14+F15+F16 -> 42.452742 | H26: Revenue management, training and IT support. Buyer-created Layers 1 and 2 displace these rather than adding to them.
A27: RealPage AI revenue-management software | B27: Third-party tooling | C27: =F27 -> 24.042881 | D27: 5063.03 | E27: =D27*$C$9 -> 8679.48 | F27: =E27/$C$6 -> 24.042881 | H27: $24.04 per unit per year. The Layer 2 delivery cost should not sit below this.
A28: Recurring buyer-created service revenue per unit | B28: $/unit | C28: =0 -> 0 | D28: Nil in Base. Exists so that project, construction and other episodic revenue can never enter the recurring base through one combined interface line. Episodic sits at C24 and is reported separately throughout.
A29: 3. PMA FEE ARCHITECTURE — classification from four executed agreements
A30: Reference and classification only. Not a live engine. Future target GL and PMA data overwrite the generic assumptions on the next tab.
A31: Revenue concept | B31: Economic treatment | C31: Evidence | H31: Note
A32: 1. Core management fee | B32: Recurring PMC revenue | C32: [F] | H32: Percentage of collected revenue, subject to property minimums. 2.25%-3.0% across the four PMAs.
A33: 2. Inherited retained recurring services | B33: Recurring PMC revenue, delivery cost unknown | C33: [F] | H33: Benefits administration, revenue management, training, IT support. Evidenced in all four PMAs and now in the Forum GL.
A34: 3. Third-party pass-through and owner reimbursements | B34: Never PMC revenue | C34: [F] | H34: Yardi and RealPage licensing, onsite payroll reimbursement. The platform administers; it does not margin on it.
A35: 4. Episodic project and construction fees | B35: Recurring only if target history supports it | C35: [C] | H35: 5% project-management fee, $135/hour consulting, repair supervision. Zero in Base.
A36: 5. Incentive fees | B36: Zero until contracted and earned | C36: [F] | H36: Dayrise and Greystar both carry incentive structures. No speculative credit.
A37: 6. Buyer-created Layers 1 to 3 | B37: Buyer-created; zeroed by the evidence switch | C37: [A] | H37: Must net inherited overlapping scope. The owner dollar cannot be monetised twice.
A38: Nearshore delivered employment cost index — evidence reference | B38: x | C38: 0.46 | D38: Abacus real-estate engagement: seven-person dedicated team invoiced at $401,264 against $878,020 estimated in Miami, 54% saving, covering accounting manager, FP&A, treasury, staff accountant/AP and compliance. [C] comparable. Not the Base operating assumption; Org & Capacity D25 carries the 0.40x Jack decision, and this index governs the evidence-constrained case.
A39: 4. DENSITY OPERATING RULES
A40: Density drives field supervision, local recruiting and training, client coverage, vendor and compliance coverage and travel. It does NOT drive property accounting, AP/AR/payroll or centralised technology, which are property, entity and transaction driven.
A41: Acquisition class | B41: Units per city | C41: Grade | D41: RPM span | E41: Maint. span | F41: Support x | H41: Use
A42: Infill | B42: Dense. >=500 units per city, ideally >=750 | C42: [E] | D42: 12 | E42: 60 | F42: 0.9 | H42: Inside existing RPM, vendor and shared-services geometry.
A43: Clustered | B43: Base. 350-600 units per city | C43: [E] | D43: 10 | E43: 50 | F43: 1 | H43: Base operating pattern. Several adjacent clusters.
A44: Extension | B44: Dispersed. <350 or a new market | C44: [E] | D44: 8 | E44: 40 | F44: 1.15 | H44: New regional, vendor, compliance and training infrastructure.
A46: Observed density tier | B46: Units per city | D46: Examples | F46: Base x
A47: Single-market / ultra-dense | B47: >=1,000 | D47: Elford; Thrive; Billingsley; 5812 | F47: 0.85
A48: Highly concentrated | B48: 600-999 | D48: Richdale; Sentinel Peak; S2; Savoy | F48: 0.92
A49: Regionally clustered | B49: 350-599 | D49: Oakwood; Tipton; NRP; Valiant; Luma | F49: 1
A50: Dispersed | B50: 150-349 | D50: Sunridge; Peak Capital; Cirrus | F50: 1.1
A51: Scattered | B51: <150 | D51: Green Alpha; Woda Cooper | F51: 1.2
A53: 5. NAMED TARGET UNIVERSE — Dallas and Columbus sub-30k cohorts
A54: Reference data so an Acquisition Schedule placeholder becomes a real target without rebuilding the workbook. Listing-derived, graded [C].
A55: Company | B55: Market | C55: Grade | D55: Units | E55: Communities | F55: Cities | G55: Units/city | H55: Density tier / caveat
A56: Sentinel Real Estate | B56: Dallas | C56: [C] | D56: 26689 | E56: 99 | F56: 76 | G56: =IF(F56=0,0,D56/F56) -> 351.17105 | H56: Regionally clustered
A57: Westdale | B57: Dallas | C57: [C] | D57: 24432 | E57: 88 | F57: 40 | G57: =IF(F57=0,0,D57/F57) -> 610.8 | H57: Highly concentrated; owner-operator likely
A58: Mill Creek Residential | B58: Dallas | C58: [C] | D58: 24090 | E58: 77 | F58: 49 | G58: =IF(F58=0,0,D58/F58) -> 491.63265 | H58: Regionally clustered
A59: Valiant Residential | B59: Dallas | C59: [C] | D59: 23740 | E59: 83 | F59: 48 | G59: =IF(F59=0,0,D59/F59) -> 494.58333 | H59: Regionally clustered
A60: Kairoi Residential | B60: Dallas | C60: [C] | D60: 22225 | E60: 79 | F60: 32 | G60: =IF(F60=0,0,D60/F60) -> 694.53125 | H60: Highly concentrated
A61: Gables Residential | B61: Dallas | C61: [C] | D61: 21644 | E61: 84 | F61: 38 | G61: =IF(F61=0,0,D61/F61) -> 569.57895 | H61: Regionally clustered
A62: Atlantic Pacific Companies | B62: Dallas | C62: [C] | D62: 20101 | E62: 82 | F62: 37 | G62: =IF(F62=0,0,D62/F62) -> 543.27027 | H62: Regionally clustered
A63: AMLI Residential | B63: Dallas | C63: [C] | D63: 19426 | E63: 54 | F63: 27 | G63: =IF(F63=0,0,D63/F63) -> 719.48148 | H63: Highly concentrated; owner-operator
A64: Portico Property Management | B64: Dallas | C64: [C] | D64: 16187 | E64: 61 | F64: 33 | G64: =IF(F64=0,0,D64/F64) -> 490.51515 | H64: Regionally clustered
A65: Sentinel Peak Capital Partners | B65: Dallas | C65: [C] | D65: 14897 | E65: 56 | F65: 15 | G65: =IF(F65=0,0,D65/F65) -> 993.13333 | H65: Highly concentrated; investment affiliation
A66: CAF Management | B66: Dallas | C66: [C] | D66: 14400 | E66: 43 | F66: 21 | G66: =IF(F66=0,0,D66/F66) -> 685.71429 | H66: Highly concentrated
A67: LDG Development | B67: Dallas | C67: [C] | D67: 14340 | E67: 62 | F67: 22 | G67: =IF(F67=0,0,D67/F67) -> 651.81818 | H67: Highly concentrated; developer affiliation
... A96: Elford Asset Management | B96: Columbus | C96: [C] | D96: 2217 | E96: 13 | F96: 1 | G96: =IF(F96=0,0,D96/F96) -> 2217 | H96: Ultra-dense; very small scale
A98: 6. COMPENSATION AND BURDEN SOURCE REGISTER
A99: Source | B99: What it supports | C99: Grade | H99: URL / note
A100: IRS Publication 15 (2026) | B100: Social Security 6.2%, Medicare 1.45%, FUTA | C100: [F] | H100: https://www.irs.gov/publications/p15
A101: SSA Contribution and Benefit Base | B101: 2026 Social Security taxable maximum $184,500 | C101: [F] | H101: https://www.ssa.gov/OACT/cola/cbb.html
A102: IRS retirement plan limits | B102: 2026 qualified-plan compensation limit $360,000 | C102: [F] | H102: https://www.irs.gov/retirement-plans
A103: KFF 2025 Employer Health Benefits Survey | B103: Premium benchmark and large-firm employer share | C103: [F] | H103: https://www.kff.org/health-costs/
A104: Mercer 2025 National Survey of Employer-Sponsored Health Plans | B104: Total health benefit cost per enrolled employee | C104: [F/C] | H104: https://www.mercer.com/
A105: Justworks PEO pricing | B105: PEO administration per FTE per year | C105: [F] | H105: https://www.justworks.com/pricing
A106: Executed Dayrise PMA — Tate Tanglewood | B106: 344-unit staffing exhibit, 7 onsite roles; 1:49 units per FTE | C106: [F] | H106: Project file
A107: NAA Staffing Considerations | B107: Onsite staffing rule and survey band | C107: [C] | H107: https://www.naahq.org/
A108: Anterra Management (7,648 units, 16 cities) | B108: Property Manager $68-70k; ACM $22-26/hr | C108: [C] | H108: Glassdoor / employer postings
A109: LUMA Residential (7,741 units, 17 cities) | B109: Multi-site luxury PM $85k+ plus bonus | C109: [C] | H109: Employer posting
A110: Unnamed DFW operator | B110: Regional Property Manager $86-100k | C110: [C] | H110: Captured posting
... A113: Apartments.com / CoStar Dallas and Columbus | B113: Named cohorts above; communities, cities, units | C113: [C] | H113: Listing-derived; not complete portfolios

Sheet Assumptions
A1: ASSUMPTIONS AND CASES
A2: Three operating cases run simultaneously. The acquisition programme and every at-close target fact are identical across them; only post-close operating outcomes vary.
A3: Blue on yellow is the only thing to edit. Green is linked to the evidence tab or derived. Constraints drive the model; objectives are scored against and drive nothing.
I4: Provenance
A5: CASE CONTROL
A6: Case | B6: Units | C6: Grade | D6: Downside | E6: Base | F6: Upside | H6: Note | I6: ASSUMPTION
A7: Case index | D7: 1 | E7: 2 | F7: 3
A8: EVIDENCE-CONSTRAINED SWITCH (1 = strip unevidenced economics from all three cases) | D8: 0 | E8: =IF($D$8=1,"EVIDENCE-CONSTRAINED","FULL CASE") -> FULL CASE | H8: Zeroes buyer-created organic wins, other integration savings, local payroll elimination, leadership redundancy, all three layers, adoption and implementation. Replacement shared-services cost, HoldCo cost and transition overlap are retained as required operating costs. Inherited contracted revenue and the acquisition programme are unchanged.
A11: HORIZON AND HARD CONSTRAINTS — these drive the model
A12: Target year | B12: year | C12: [D] | D12: 7 | E12: 7 | F12: 7 | I12: JACK DECISION
A13: Exit year | B13: year | C13: [D] | D13: 7 | E13: 7 | F13: 7 | I13: JACK DECISION
A14: Long-hold scenario year | B14: year | C14: [D] | D14: 10 | E14: 10 | F14: 10 | I14: JACK DECISION
A15: Sponsor hurdle IRR | B15: % | C15: [D] | D15: 0.25 | E15: 0.25 | F15: 0.25 | I15: JACK DECISION
A16: Managed-unit ceiling at the target year | B16: units | C16: [D] | D16: 50000 | E16: 50000 | F16: 50000 | H16: Hard planning constraint. Common to all three cases because at-close facts are frozen. | I16: JACK DECISION
A17: Average units per property | B17: units | C17: [D] | D17: 250 | E17: 250 | F17: 250 | H17: Authoritative Base across all cases. The 200 / 225 / 250 work remains a sensitivity on Org & Capacity, not an alternate Base. | I17: JACK DECISION
A18: Implied properties at the ceiling | B18: properties | C18: [C] | D18: =D16/D17 -> 200 | E18: =E16/E17 -> 200 | F18: =F16/F17 -> 200 | H18: Derived, not entered. The managed-unit ceiling divided by units per property. Actual properties at exit are reported downstream and are the arithmetic consequence of units, never a separate assumption. | I18: [C] COMPARABLE
A19: Exit EBITDA basis (1 reported / 2 exit run-rate) | B19: flag | C19: [D] | D19: 1 | E19: 1 | F19: 1 | I19: JACK DECISION
A20: Acquisition closing fraction of year | B20: % | C20: [D] | D20: 0.5 | E20: 0.5 | F20: 0.5 | I20: JACK DECISION
A22: PLANNING OBJECTIVES — the model is scored against these; they drive nothing
A23: Objective — consolidated platform EBITDA after HoldCo | B23: $ | C23: [D] | D23: 10000000 | E23: 10000000 | F23: 10000000 | H23: Design objective, not a driver. The programme is constrained by the unit ceiling and target quality, so the shortfall is a finding and is never engineered away. | I23: JACK DECISION
A24: Objective — clients at the exit year | B24: clients | C24: [D] | D24: 30 | E24: 30 | F24: 30 | H24: Scored against, never used to size anything. Actual clients are derived from clients acquired per deal and retention, and are reported on the Operating Case, Business Plan and IC Summary. | I24: JACK DECISION
A26: DEAL-LEVEL ACQUISITION FACTS — frozen across operating cases
A27: Core management fee per unit per year | B27: $/unit | C27: [C] | D27: ='Evidence & Market'!$C$21 -> 510.44814 | E27: ='Evidence & Market'!$C$21 -> 510.44814 | F27: ='Evidence & Market'!$C$21 -> 510.44814 | H27: Forum GL. [F] on the evidence tab; applied to unidentified targets it is a comparable. | I27: [C]
A28: Inherited retained-service revenue per unit | B28: $/unit | C28: [C] | D28: ='Evidence & Market'!$C$22 -> 88.599351 | E28: ='Evidence & Market'!$C$22 -> 88.599351 | F28: ='Evidence & Market'!$C$22 -> 88.599351 | I28: [C]
A29: Third-party pass-through per unit | B29: $/unit | C29: [C] | D29: ='Evidence & Market'!$C$23 -> 54.435457 | E29: ='Evidence & Market'!$C$23 -> 54.435457 | F29: ='Evidence & Market'!$C$23 -> 54.435457 | H29: In revenue, never in EBITDA contribution. | I29: [C]
A30: Episodic project and consulting fees per unit | B30: $/unit | C30: [C] | D30: ='Evidence & Market'!$C$24 -> 0 | E30: ='Evidence & Market'!$C$24 -> 0 | F30: ='Evidence & Market'!$C$24 -> 0 | H30: Zero in Base until target history supports it. | I30: [C]
A31: ORG-20 Target payroll structure — payroll share of operating cost | B31: % | C31: [OQ] | D31: =$E$31 -> 0.75 | E31: 0.75 | F31: =$E$31 -> 0.75 | H31: PRINCIPAL DECISION, 4 Sep 2026, set at 75%. Replaces the former non-payroll share of revenue. Target compensation is solved to this share of the acquired cost base rather than assumed from platform benchmarks. Total payroll share alone does not determine centralisation value: the dollars must sit in the roles the platform can actually eliminate. Resolving it requires a P&L and trial balance, a payroll register, an employee census by role and title with loaded employer cost, outsourced finance, legal and compliance spend, benefit and payroll-tax costs, and intercompany allocations — prioritising a 6,000-unit target because that is the repeated tuck-in archetype. Frozen across operating cases; applies to acquired targets only, never to HoldCo or shared services, which carry full platform rates. | I31: JACK DECISION
A32: Target normalized EBITDA per managed unit at close | B32: $/unit | C32: [OQ] | D32: =E32 -> 128 | E32: 128 | F32: =E32 -> 128 | H32: PRIMARY INPUT. With units per property and the evidenced revenue per unit, this is the only target-quality assumption in the model. Units, properties and the EBITDA margin are all derived from it. Set to the acquisition-quality screen: the minimum EBITDA per unit at which the instructed cadence, EBITDA sizes and 50,000-unit ceiling coexist. A screening criterion requiring target GL evidence, never an observed fact. | I32: OPEN QUESTION
A33: Implied target normalized EBITDA margin | B33: % | C33: [C] | D33: =D32/(D27+D28+D29+D30) -> 0.19587351 | E33: =E32/(E27+E28+E29+E30) -> 0.19587351 | F33: =F32/(F27+F28+F29+F30) -> 0.19587351 | H33: Set to the acquisition-quality screen derived on Operating Case: the minimum normalized margin at which the instructed cadence, EBITDA sizes and 50,000-unit ceiling coexist. It is a screening criterion for the target universe requiring target GL evidence, never an observed fact. One common at-close acquisition assumption. The same company is purchased in every case, so Downside and Upside read the Base cell by formula and cannot diverge. Acquisition quality is tested in the sensitivity block on Returns, never inside an operating scenario. | I33: [C] COMPARABLE
A34: Anchor acquired EBITDA | B34: $ | C34: [D] | D34: 1000000 | E34: 1000000 | F34: 1000000 | H34: Instructed minimum. Live on the EBITDA-led basis. | I34: JACK DECISION
A35: Acquired EBITDA — large tuck-in | B35: $ | C35: [D] | D35: 750000 | E35: 750000 | F35: 750000 | H35: One per year, as instructed. | I35: JACK DECISION
A36: Acquired EBITDA — small tuck-in | B36: $ | C36: [D] | D36: 500000 | E36: 500000 | F36: 500000 | H36: Filler size. Available but not used in the live Base programme because the unit ceiling leaves no room; the schedule reports this explicitly. | I36: JACK DECISION
A37: Acquired EBITDA — mid-market addition | B37: $ | C37: [D] | D37: 1250000 | E37: 1250000 | F37: 1250000 | H37: Year 3 only. At or above the $800k pricing threshold, so it prices off the larger-target convention at 6.0x. | I37: JACK DECISION
A38: Entry-multiple band threshold — acquired EBITDA | B38: $ | C38: [D] | D38: 800000 | E38: 800000 | F38: 800000 | H38: A target BELOW this EBITDA prices off the smaller-target convention; at or above it, off the larger-target convention. Applied automatically by deal size. No deal in the live programme sits on the boundary, so the convention carries no knife-edge risk. | I38: JACK DECISION
A39: Anchor entry multiple | B39: x | C39: [D] | D39: 6 | E39: 6 | F39: 6 | H39: The anchor is priced explicitly and does not use the band. | I39: JACK DECISION
A40: Entry multiple — targets below the threshold | B40: x | C40: [D] | D40: 4 | E40: 4 | F40: 4 | H40: Principal decision. The banker indication for smaller businesses was approximately 3-4x; 4.0x sits at the top of that range. The sensitivity band below is applied on Returns, never as an operating scenario. | I40: JACK DECISION
A41: Pricing sensitivity band — below the threshold | B41: x | C41: [A] | D41: 4.5 | E41: 4 | F41: 3.5 | H41: High 4.5x / Base 4.0x / Low 3.5x, applied on Returns as a purchase-price sensitivity. Graded [A]: the 4.5x high case sits above the 3-4x banker indication for smaller businesses and is not supported by it. | I41: ASSUMPTION
A42: Entry multiple — targets at or above the threshold | B42: x | C42: [D] | D42: 6 | E42: 6 | F42: 6 | H42: Principal decision. Larger targets are competitively priced and do not clear at 3-4x. | I42: JACK DECISION
A43: Clients acquired with the anchor | B43: clients | C43: [OQ] | D43: 6 | E43: 6 | F43: 6 | I43: OPEN QUESTION
A44: Clients acquired per tuck-in | B44: clients | C44: [OQ] | D44: 3.4 | E44: 3.4 | F44: 3.4 | H44: Set so retained clients land near the 30 instruction at Year 7 after change-of-control loss and ordinary churn. | I44: OPEN QUESTION
A45: Baseline reporting regimes across the portfolio | B45: regimes | C45: [E] | D45: 1 | E45: 1 | F45: 1 | H45: Distinct owner reporting and approval regimes, not client count. Only complexity above the baseline creates incremental FTE. | I45: ESTIMATE
A46: Distinct regimes per 10 clients | B46: regimes | C46: [E] | D46: 3 | E46: 2.5 | F46: 2 | I46: ESTIMATE
A47: Regime complexity factor for bespoke regimes | B47: x | C47: [E] | D47: 1.3 | E47: 1.25 | F47: 1.2 | I47: ESTIMATE
A49: POST-CLOSE OPERATING OUTCOMES — these are what the cases vary
A50: Share of revenue — institutional, 30-day termination | B50: % | C50: [C] | D50: 0.35 | E50: 0.35 | F50: 0.35 | I50: [C] COMPARABLE
A51: Annual retention — institutional | B51: % | C51: [A] | D51: 0.85 | E51: 0.88 | F51: 0.91 | I51: ASSUMPTION
A52: Share of revenue — regional owner, 60-90 day | B52: % | C52: [C] | D52: 0.4 | E52: 0.4 | F52: 0.4 | I52: [C] COMPARABLE
A53: Annual retention — regional owner | B53: % | C53: [A] | D53: 0.9 | E53: 0.92 | F53: 0.94 | I53: ASSUMPTION
A54: Share of revenue — developer / lease-up, term | B54: % | C54: [C] | D54: 0.25 | E54: 0.25 | F54: 0.25 | I54: [C] COMPARABLE
A55: Annual retention — developer / lease-up | B55: % | C55: [A] | D55: 0.92 | E55: 0.94 | F55: 0.96 | I55: ASSUMPTION
A56: Incremental change-of-control loss at close | B56: % | C56: [A] | D56: 0.09 | E56: 0.06 | F56: 0.04 | I56: ASSUMPTION
A57: Gross new-business wins — the target standalone capability | B57: % | C57: [C] | D57: 0.08 | E57: 0.1 | F57: 0.12 | H57: What the acquired PMC wins on its own each year: developer relationships, referrals, local reputation. This is capability being purchased, so the evidence switch does NOT remove it. A PMC with roughly 9% annual contract churn needs wins of this order simply to hold its book. | I57: [C] COMPARABLE
A58: Gross new-business wins — platform uplift | B58: % | C58: [A] | D58: 0.02 | E58: 0.04 | F58: 0.06 | H58: Incremental wins the target could not have achieved alone: dedicated business-development capacity, institutional owner reporting, balance sheet and credibility for larger mandates, developer lease-up assignments. Buyer-created, so the evidence switch zeroes it. | I58: ASSUMPTION
A59: Other integration savings — procurement, insurance, vendor | B59: % | C59: [A] | D59: 0.03 | E59: 0.05 | F59: 0.08 | H59: Share of acquired EBITDA. Separate from the named leadership and role-centralisation savings, which are built bottom-up. | I59: ASSUMPTION
A60: Synergy phasing — year of close | B60: % | C60: [A] | D60: 0 | E60: 0.1 | F60: 0.2 | I60: ASSUMPTION
A61: Synergy phasing — first full year | B61: % | C61: [A] | D61: 0.5 | E61: 0.6 | F61: 0.7 | I61: ASSUMPTION
A62: Synergy phasing — second full year onward | B62: % | C62: [A] | D62: 1 | E62: 1 | F62: 1 | I62: ASSUMPTION
A63: Integration cost per deal | B63: $ | C63: [A] | D63: 215000 | E63: 175000 | F63: 145000 | H63: One-off at close. Scope excludes pod payroll and transition overlap, both of which are charged separately. | I63: ASSUMPTION
A64: Fixed transaction cost per close | B64: $ | C64: [A] | D64: 95000 | E64: 75000 | F64: 60000 | H64: OPEN. Placeholder pending legal, QoE and insurance quotes. | I64: ASSUMPTION
A65: Transaction costs as share of EV | B65: % | C65: [A] | D65: 0.033 | E65: 0.03 | F65: 0.027 | I65: ASSUMPTION
A67: PLATFORM SERVICES — LAYERS 1 TO 3
A68: Layer 1 platform fee per unit per year | B68: $/unit | C68: [A] | D68: 25 | E68: 40 | F68: 55 | I68: ASSUMPTION
A69: Layer 2 module revenue per unit per year | B69: $/unit | C69: [A] | D69: 40 | E69: 60 | F69: 80 | I69: ASSUMPTION
A70: Layer 3 gainshare per unit per year | B70: $/unit | C70: [A] | D70: 5 | E70: 10 | F70: 16 | I70: ASSUMPTION
A71: Platform-like services the incumbent already bills | B71: $/unit | C71: [C] | D71: ='Evidence & Market'!$C$26 -> 42.452742 | E71: ='Evidence & Market'!$C$26 -> 42.452742 | F71: ='Evidence & Market'!$C$26 -> 42.452742 | H71: Revenue management, training and IT support, from the Forum GL. | I71: [C] COMPARABLE
A72: Share of Layers 1 and 2 that displaces incumbent scope | B72: % | C72: [A] | D72: 0.5 | E72: 0.4 | F72: 0.3 | H72: Netted off before delivery cost. The same owner dollar cannot be monetised twice. | I72: ASSUMPTION
A73: Layer 1 direct COGS share | B73: % | C73: [A] | D73: 0.38 | E73: 0.3 | F73: 0.24 | I73: ASSUMPTION
A74: Layer 2 third-party tooling per adopted unit | B74: $/unit | C74: [F] | D74: ='Evidence & Market'!$C$27 -> 24.042881 | E74: ='Evidence & Market'!$C$27 -> 24.042881 | F74: ='Evidence & Market'!$C$27 -> 24.042881 | H74: Observed RealPage cost. Delivery labour is named separately on Org & Capacity. | I74: [F] FACT
A75: Layer 3 direct COGS share | B75: % | C75: [A] | D75: 0.26 | E75: 0.2 | F75: 0.16 | I75: ASSUMPTION
A76: Adoption at full ramp | B76: % | C76: [A] | D76: 0.28 | E76: 0.4 | F76: 0.52 | I76: ASSUMPTION
A77: Years to full adoption | B77: years | C77: [A] | D77: 4 | E77: 3 | F77: 3 | I77: ASSUMPTION
A78: Product implementation cost per unit onboarded | B78: $/unit | C78: [A] | D78: 15 | E78: 12 | F78: 9 | I78: ASSUMPTION
A79: Recurring buyer-created service revenue per unit | B79: $/unit | C79: [A] | D79: ='Evidence & Market'!$C$28 -> 0 | E79: ='Evidence & Market'!$C$28 -> 0 | F79: ='Evidence & Market'!$C$28 -> 0 | H79: Recurring buyer-created revenue, separate from the episodic line at row 30. Nil in Base. | I79: [A]
A80: TRANSITION AND CAPACITY
A81: Payroll overlap window | B81: years | C81: [D] | D81: 1 | E81: 1 | F81: 1 | H81: User convention, do not revert. | I81: JACK DECISION
A82: First-year payroll overlap share | B82: % | C82: [D] | D82: 0.5 | E82: 0.5 | F82: 0.5 | I82: JACK DECISION
A83: Second-year overlap factor | B83: % | C83: [D] | D83: 0 | E83: 0 | F83: 0 | I83: JACK DECISION
A84: Deals one integration pod can absorb per year | B84: deals | C84: [A] | D84: 2 | E84: 3 | F84: 4 | I84: ASSUMPTION
A85: Fully loaded cost per integration pod | B85: $ | C85: [A] | D85: 540000 | E85: 480000 | F85: 430000 | I85: ASSUMPTION
A86: HoldCo non-payroll G&A — year 1 | B86: $ | C86: [A] | D86: 820000 | E86: 700000 | F86: 610000 | H86: Technology, insurance, professional fees, premises. Payroll is built bottom-up and is not in this line. | I86: ASSUMPTION
A87: HoldCo non-payroll G&A growth | B87: % | C87: [A] | D87: 0.07 | E87: 0.06 | F87: 0.05 | I87: ASSUMPTION
A88: Annual compensation inflation | B88: % | C88: [A] | D88: 0.035 | E88: 0.03 | F88: 0.026 | I88: ASSUMPTION
A89: Recurring corporate capex per managed unit | B89: $/unit | C89: [A] | D89: 28 | E89: 25 | F89: 22 | I89: ASSUMPTION
A90: PMC-funded working capital per managed unit | B90: $/unit | C90: [A] | D90: 26 | E90: 22 | F90: 18 | I90: ASSUMPTION
A91: Leadership redundancy credited in the underwriting | B91: % | C91: [D] | D91: 0 | E91: 0 | F91: 0 | H91: JACK PRINCIPAL DECISION, 7 Sep 2026. Set to nil. No synergy credit may exist unless the seller cost eliminated is explicitly represented in the bottom-up seller organisation and is not already consumed by another savings line. The two-seat redundancy is not so represented. The schedule below it is retained as an uncredited [OQ] upside; seller leadership seats must not be invented to preserve it. The separate roster-duplication analysis of approximately $2.99m is likewise ununderwritten pending target roster evidence. | I91: JACK DECISION
A92: CAPITAL STRUCTURE, COVENANTS AND EXIT
A93: Maximum senior leverage on DealCo EBITDA | B93: x | C93: [A] | D93: 2.25 | E93: 2.75 | F93: 3.15 | I93: ASSUMPTION
A94: Minimum lender DSCR on cash available for debt service | B94: x | C94: [A] | D94: 1.4 | E94: 1.25 | F94: 1.18 | H94: Binding. Debt funded is the lower of the leverage test and this CFADS test. | I94: ASSUMPTION
A95: Target senior debt share of acquisition EV | B95: % | C95: [A] | D95: 0.35 | E95: 0.35 | F95: 0.35 | H95: A target, not an entitlement. Frozen across cases because it is a deal fact. | I95: ASSUMPTION
A96: Senior debt interest rate | B96: % | C96: [A] | D96: 0.105 | E96: 0.095 | F96: 0.087 | I96: ASSUMPTION
A97: Senior amortisation, share of each vintage original principal | B97: % | C97: [A] | D97: 0.1 | E97: 0.1 | F97: 0.1 | I97: ASSUMPTION
A98: Seller note share of acquisition EV | B98: % | C98: [D] | D98: 0.15 | E98: 0.15 | F98: 0.15 | I98: JACK DECISION
A99: Seller note interest rate | B99: % | C99: [A] | D99: 0.077 | E99: 0.07 | F99: 0.063 | I99: ASSUMPTION
A100: Seller note maturity from its own vintage | B100: years | C100: [D] | D100: 5 | E100: 5 | F100: 5 | I100: JACK DECISION
A101: Minimum cash balance — HoldCo reserve | B101: $ | C101: [D] | D101: 1500000 | E101: 1500000 | F101: 1500000 | H101: Platform reserve. Separate from property-owner and trust cash, which never appears in this model. | I101: JACK DECISION
A102: Effective cash tax rate | B102: % | C102: [A] | D102: 0.26 | E102: 0.26 | F102: 0.26 | I102: ASSUMPTION
A103: Exit multiple | B103: x | C103: [D] | D103: 8.5 | E103: 9.5 | F103: 10.5 | H103: Valuation sensitivity, not an operating outcome. | I103: JACK DECISION
A104: Common platform exit multiple for the operating comparison | B104: x | C104: [D] | D104: 9.5 | E104: 9.5 | F104: 9.5 | H104: Holds valuation constant so operating performance is not confused with pricing. | I104: JACK DECISION
A105: Multiple applied to buyer-created EBITDA | B105: x | C105: [D] | D105: 5.5 | E105: 6 | F105: 6.5 | H105: Buyer-created earnings were never purchased and carry no acquisition multiple. | I105: JACK DECISION
A106: Exit costs as share of EV | B106: % | C106: [A] | D106: 0.02 | E106: 0.02 | F106: 0.02 | I106: ASSUMPTION
...

Sheet Acquisition Schedule
A1: ACQUISITION SCHEDULE — ONE ROW PER DEAL
A2: Every field is an at-close fact and is identical in Downside, Base and Upside. Operating cases change what happens after close, never the company that was bought.
A5: Deal ID | B5: Target / type | C5: Market | D5: Class | E5: Close yr | F5: Acq EBITDA | G5: Revenue* | H5: Margin* | I5: Units* | J5: Props* | K5: Clients* | L5: Regimes | M5: Entry x | N5: EV | O5: Senior | P5: Seller note | Q5: Integr. cost | R5: Txn cost | S5: Ldrs acq | T5: Retained | U5: Redundant | V5: Density x | W5: Units x dens
A6: ANCHOR | B6: Backbone platform | C6: Dallas | D6: Clustered | E6: 0 | F6: =INDEX(Assumptions!$D$34:$F$34,1,2) -> 1000000 | G6: =I6*(INDEX(Assumptions!$D$27:$F$27,1,2)+INDEX(Assumptions!$D$28:$F$28,1,2)+INDEX(Assumptions!$D$29:$F$29,1,2)+INDEX(Assumptions!$D$30:$F$30,1,2)) -> 5105335.5 | H6: =IF(G6=0,0,F6/G6) -> 0.19587351 | I6: =F6/INDEX(Assumptions!$D$32:$F$32,1,2) -> 7812.5 | J6: =I6/INDEX(Assumptions!$D$17:$F$17,1,2) -> 31.25 | K6: =INDEX(Assumptions!$D$43:$F$43,1,2) -> 6 | L6: =K6*INDEX(Assumptions!$D$46:$F$46,1,2)/10 -> 1.5 | M6: =INDEX(Assumptions!$D$39:$F$39,1,2) -> 6 | N6: =F6*M6 -> 6000000 | O6: =N6*INDEX(Assumptions!$D$95:$F$95,1,2) -> 2100000 | P6: =N6*INDEX(Assumptions!$D$98:$F$98,1,2) -> 900000 | Q6: =INDEX(Assumptions!$D$63:$F$63,1,2) -> 175000 | R6: =INDEX(Assumptions!$D$64:$F$64,1,2)+N6*INDEX(Assumptions!$D$65:$F$65,1,2) -> 255000 | S6: 2 | T6: 1 | U6: =MAX(0,S6-T6) -> 1 | V6: =INDEX('Evidence & Market'!$F$42:$F$44,MATCH($D6,'Evidence & Market'!$A$42:$A$44,0)) -> 1 | W6: =I6*V6 -> 7812.5
A7: TK01 | B7: Large tuck-in | C7: Dallas | D7: Infill | E7: 1 | F7: =INDEX(Assumptions!$D$35:$F$35,1,2) -> 750000 | G7: =I7*(INDEX(Assumptions!$D$27:$F$27,1,2)+INDEX(Assumptions!$D$28:$F$28,1,2)+INDEX(Assumptions!$D$29:$F$29,1,2)+INDEX(Assumptions!$D$30:$F$30,1,2)) -> 3829001.6 | H7: =IF(G7=0,0,F7/G7) -> 0.19587351 | I7: =F7/INDEX(Assumptions!$D$32:$F$32,1,2) -> 5859.375 | J7: =I7/INDEX(Assumptions!$D$17:$F$17,1,2) -> 23.4375 | K7: =INDEX(Assumptions!$D$44:$F$44,1,2) -> 3.4 | L7: =K7*INDEX(Assumptions!$D$46:$F$46,1,2)/10 -> 0.85 | M7: =IF(F7<INDEX(Assumptions!$D$38:$F$38,1,2),INDEX(Assumptions!$D$40:$F$40,1,2),INDEX(Assumptions!$D$42:$F$42,1,2)) -> 4 | N7: =F7*M7 -> 3000000 | O7: =N7*INDEX(Assumptions!$D$95:$F$95,1,2) -> 1050000 | P7: =N7*INDEX(Assumptions!$D$98:$F$98,1,2) -> 450000 | Q7: =INDEX(Assumptions!$D$63:$F$63,1,2) -> 175000 | R7: =INDEX(Assumptions!$D$64:$F$64,1,2)+N7*INDEX(Assumptions!$D$65:$F$65,1,2) -> 165000 | S7: 1 | T7: 1 | U7: =MAX(0,S7-T7) -> 0 | V7: =INDEX('Evidence & Market'!$F$42:$F$44,MATCH($D7,'Evidence & Market'!$A$42:$A$44,0)) -> 0.9 | W7: =I7*V7 -> 5273.4375
A8: TK02 | B8: Large tuck-in | C8: Dallas | D8: Infill | E8: 2 | F8: =INDEX(Assumptions!$D$35:$F$35,1,2) -> 750000 | G8: =I8*(INDEX(Assumptions!$D$27:$F$27,1,2)+INDEX(Assumptions!$D$28:$F$28,1,2)+INDEX(Assumptions!$D$29:$F$29,1,2)+INDEX(Assumptions!$D$30:$F$30,1,2)) -> 3829001.6 | H8: =IF(G8=0,0,F8/G8) -> 0.19587351 | I8: =F8/INDEX(Assumptions!$D$32:$F$32,1,2) -> 5859.375 | J8: =I8/INDEX(Assumptions!$D$17:$F$17,1,2) -> 23.4375 | K8: =INDEX(Assumptions!$D$44:$F$44,1,2) -> 3.4 | L8: =K8*INDEX(Assumptions!$D$46:$F$46,1,2)/10 -> 0.85 | M8: =IF(F8<INDEX(Assumptions!$D$38:$F$38,1,2),INDEX(Assumptions!$D$40:$F$40,1,2),INDEX(Assumptions!$D$42:$F$42,1,2)) -> 4 | N8: =F8*M8 -> 3000000 | O8: =N8*INDEX(Assumptions!$D$95:$F$95,1,2) -> 1050000 | P8: =N8*INDEX(Assumptions!$D$98:$F$98,1,2) -> 450000 | Q8: =INDEX(Assumptions!$D$63:$F$63,1,2) -> 175000 | R8: =INDEX(Assumptions!$D$64:$F$64,1,2)+N8*INDEX(Assumptions!$D$65:$F$65,1,2) -> 165000 | S8: 1 | T8: 1 | U8: =MAX(0,S8-T8) -> 0 | V8: =INDEX('Evidence & Market'!$F$42:$F$44,MATCH($D8,'Evidence & Market'!$A$42:$A$44,0)) -> 0.9 | W8: =I8*V8 -> 5273.4375
A9: TK03 | B9: Large tuck-in | C9: Dallas | D9: Clustered | E9: 3 | F9: =INDEX(Assumptions!$D$35:$F$35,1,2) -> 750000 | G9: =I9*(INDEX(Assumptions!$D$27:$F$27,1,2)+INDEX(Assumptions!$D$28:$F$28,1,2)+INDEX(Assumptions!$D$29:$F$29,1,2)+INDEX(Assumptions!$D$30:$F$30,1,2)) -> 3829001.6 | H9: =IF(G9=0,0,F9/G9) -> 0.19587351 | I9: =F9/INDEX(Assumptions!$D$32:$F$32,1,2) -> 5859.375 | J9: =I9/INDEX(Assumptions!$D$17:$F$17,1,2) -> 23.4375 | K9: =INDEX(Assumptions!$D$44:$F$44,1,2) -> 3.4 | L9: =K9*INDEX(Assumptions!$D$46:$F$46,1,2)/10 -> 0.85 | M9: =IF(F9<INDEX(Assumptions!$D$38:$F$38,1,2),INDEX(Assumptions!$D$40:$F$40,1,2),INDEX(Assumptions!$D$42:$F$42,1,2)) -> 4 | N9: =F9*M9 -> 3000000 | O9: =N9*INDEX(Assumptions!$D$95:$F$95,1,2) -> 1050000 | P9: =N9*INDEX(Assumptions!$D$98:$F$98,1,2) -> 450000 | Q9: =INDEX(Assumptions!$D$63:$F$63,1,2) -> 175000 | R9: =INDEX(Assumptions!$D$64:$F$64,1,2)+N9*INDEX(Assumptions!$D$65:$F$65,1,2) -> 165000 | S9: 1 | T9: 1 | U9: =MAX(0,S9-T9) -> 0 | V9: =INDEX('Evidence & Market'!$F$42:$F$44,MATCH($D9,'Evidence & Market'!$A$42:$A$44,0)) -> 1 | W9: =I9*V9 -> 5859.375
A10: TK04 | B10: Mid-market addition | C10: Columbus | D10: Extension | E10: 3 | F10: =INDEX(Assumptions!$D$37:$F$37,1,2) -> 1250000 | G10: =I10*(INDEX(Assumptions!$D$27:$F$27,1,2)+INDEX(Assumptions!$D$28:$F$28,1,2)+INDEX(Assumptions!$D$29:$F$29,1,2)+INDEX(Assumptions!$D$30:$F$30,1,2)) -> 6381669.4 | H10: =IF(G10=0,0,F10/G10) -> 0.19587351 | I10: =F10/INDEX(Assumptions!$D$32:$F$32,1,2) -> 9765.625 | J10: =I10/INDEX(Assumptions!$D$17:$F$17,1,2) -> 39.0625 | K10: =INDEX(Assumptions!$D$44:$F$44,1,2) -> 3.4 | L10: =K10*INDEX(Assumptions!$D$46:$F$46,1,2)/10 -> 0.85 | M10: =IF(F10<INDEX(Assumptions!$D$38:$F$38,1,2),INDEX(Assumptions!$D$40:$F$40,1,2),INDEX(Assumptions!$D$42:$F$42,1,2)) -> 6 | N10: =F10*M10 -> 7500000 | O10: =N10*INDEX(Assumptions!$D$95:$F$95,1,2) -> 2625000 | P10: =N10*INDEX(Assumptions!$D$98:$F$98,1,2) -> 1125000 | Q10: =INDEX(Assumptions!$D$63:$F$63,1,2) -> 175000 | R10: =INDEX(Assumptions!$D$64:$F$64,1,2)+N10*INDEX(Assumptions!$D$65:$F$65,1,2) -> 300000 | S10: 2 | T10: 1 | U10: =MAX(0,S10-T10) -> 1 | V10: =INDEX('Evidence & Market'!$F$42:$F$44,MATCH($D10,'Evidence & Market'!$A$42:$A$44,0)) -> 1.15 | W10: =I10*V10 -> 11230.469
A11: TK05 | B11: Large tuck-in | C11: Dallas | D11: Infill | E11: 4 | F11: =INDEX(Assumptions!$D$35:$F$35,1,2) -> 750000 | G11: =I11*(INDEX(Assumptions!$D$27:$F$27,1,2)+INDEX(Assumptions!$D$28:$F$28,1,2)+INDEX(Assumptions!$D$29:$F$29,1,2)+INDEX(Assumptions!$D$30:$F$30,1,2)) -> 3829001.6 | H11: =IF(G11=0,0,F11/G11) -> 0.19587351 | I11: =F11/INDEX(Assumptions!$D$32:$F$32,1,2) -> 5859.375 | J11: =I11/INDEX(Assumptions!$D$17:$F$17,1,2) -> 23.4375 | K11: =INDEX(Assumptions!$D$44:$F$44,1,2) -> 3.4 | L11: =K11*INDEX(Assumptions!$D$46:$F$46,1,2)/10 -> 0.85 | M11: =IF(F11<INDEX(Assumptions!$D$38:$F$38,1,2),INDEX(Assumptions!$D$40:$F$40,1,2),INDEX(Assumptions!$D$42:$F$42,1,2)) -> 4 | N11: =F11*M11 -> 3000000 | O11: =N11*INDEX(Assumptions!$D$95:$F$95,1,2) -> 1050000 | P11: =N11*INDEX(Assumptions!$D$98:$F$98,1,2) -> 450000 | Q11: =INDEX(Assumptions!$D$63:$F$63,1,2) -> 175000 | R11: =INDEX(Assumptions!$D$64:$F$64,1,2)+N11*INDEX(Assumptions!$D$65:$F$65,1,2) -> 165000 | S11: 1 | T11: 1 | U11: =MAX(0,S11-T11) -> 0 | V11: =INDEX('Evidence & Market'!$F$42:$F$44,MATCH($D11,'Evidence & Market'!$A$42:$A$44,0)) -> 0.9 | W11: =I11*V11 -> 5273.4375
A12: TK06 | B12: Large tuck-in | C12: Columbus | D12: Clustered | E12: 5 | F12: =INDEX(Assumptions!$D$35:$F$35,1,2) -> 750000 | G12: =I12*(INDEX(Assumptions!$D$27:$F$27,1,2)+INDEX(Assumptions!$D$28:$F$28,1,2)+INDEX(Assumptions!$D$29:$F$29,1,2)+INDEX(Assumptions!$D$30:$F$30,1,2)) -> 3829001.6 | H12: =IF(G12=0,0,F12/G12) -> 0.19587351 | I12: =F12/INDEX(Assumptions!$D$32:$F$32,1,2) -> 5859.375 | J12: =I12/INDEX(Assumptions!$D$17:$F$17,1,2) -> 23.4375 | K12: =INDEX(Assumptions!$D$44:$F$44,1,2) -> 3.4 | L12: =K12*INDEX(Assumptions!$D$46:$F$46,1,2)/10 -> 0.85 | M12: =IF(F12<INDEX(Assumptions!$D$38:$F$38,1,2),INDEX(Assumptions!$D$40:$F$40,1,2),INDEX(Assumptions!$D$42:$F$42,1,2)) -> 4 | N12: =F12*M12 -> 3000000 | O12: =N12*INDEX(Assumptions!$D$95:$F$95,1,2) -> 1050000 | P12: =N12*INDEX(Assumptions!$D$98:$F$98,1,2) -> 450000 | Q12: =INDEX(Assumptions!$D$63:$F$63,1,2) -> 175000 | R12: =INDEX(Assumptions!$D$64:$F$64,1,2)+N12*INDEX(Assumptions!$D$65:$F$65,1,2) -> 165000 | S12: 1 | T12: 1 | U12: =MAX(0,S12-T12) -> 0 | V12: =INDEX('Evidence & Market'!$F$42:$F$44,MATCH($D12,'Evidence & Market'!$A$42:$A$44,0)) -> 1 | W12: =I12*V12 -> 5859.375
A13: TK07 | B13: Large tuck-in | C13: Columbus | D13: Infill | E13: 6 | F13: =INDEX(Assumptions!$D$35:$F$35,1,2) -> 750000 | G13: =I13*(INDEX(Assumptions!$D$27:$F$27,1,2)+INDEX(Assumptions!$D$28:$F$28,1,2)+INDEX(Assumptions!$D$29:$F$29,1,2)+INDEX(Assumptions!$D$30:$F$30,1,2)) -> 3829001.6 | H13: =IF(G13=0,0,F13/G13) -> 0.19587351 | I13: =F13/INDEX(Assumptions!$D$32:$F$32,1,2) -> 5859.375 | J13: =I13/INDEX(Assumptions!$D$17:$F$17,1,2) -> 23.4375 | K13: =INDEX(Assumptions!$D$44:$F$44,1,2) -> 3.4 | L13: =K13*INDEX(Assumptions!$D$46:$F$46,1,2)/10 -> 0.85 | M13: =IF(F13<INDEX(Assumptions!$D$38:$F$38,1,2),INDEX(Assumptions!$D$40:$F$40,1,2),INDEX(Assumptions!$D$42:$F$42,1,2)) -> 4 | N13: =F13*M13 -> 3000000 | O13: =N13*INDEX(Assumptions!$D$95:$F$95,1,2) -> 1050000 | P13: =N13*INDEX(Assumptions!$D$98:$F$98,1,2) -> 450000 | Q13: =INDEX(Assumptions!$D$63:$F$63,1,2) -> 175000 | R13: =INDEX(Assumptions!$D$64:$F$64,1,2)+N13*INDEX(Assumptions!$D$65:$F$65,1,2) -> 165000 | S13: 1 | T13: 1 | U13: =MAX(0,S13-T13) -> 0 | V13: =INDEX('Evidence & Market'!$F$42:$F$44,MATCH($D13,'Evidence & Market'!$A$42:$A$44,0)) -> 0.9 | W13: =I13*V13 -> 5273.4375
A14: TK08 | B14: Large tuck-in | C14: Columbus | D14: Infill | E14: 7 | F14: =INDEX(Assumptions!$D$35:$F$35,1,2) -> 750000 | G14: =I14*(INDEX(Assumptions!$D$27:$F$27,1,2)+INDEX(Assumptions!$D$28:$F$28,1,2)+INDEX(Assumptions!$D$29:$F$29,1,2)+INDEX(Assumptions!$D$30:$F$30,1,2)) -> 3829001.6 | H14: =IF(G14=0,0,F14/G14) -> 0.19587351 | I14: =F14/INDEX(Assumptions!$D$32:$F$32,1,2) -> 5859.375 | J14: =I14/INDEX(Assumptions!$D$17:$F$17,1,2) -> 23.4375 | K14: =INDEX(Assumptions!$D$44:$F$44,1,2) -> 3.4 | L14: =K14*INDEX(Assumptions!$D$46:$F$46,1,2)/10 -> 0.85 | M14: =IF(F14<INDEX(Assumptions!$D$38:$F$38,1,2),INDEX(Assumptions!$D$40:$F$40,1,2),INDEX(Assumptions!$D$42:$F$42,1,2)) -> 4 | N14: =F14*M14 -> 3000000 | O14: =N14*INDEX(Assumptions!$D$95:$F$95,1,2) -> 1050000 | P14: =N14*INDEX(Assumptions!$D$98:$F$98,1,2) -> 450000 | Q14: =INDEX(Assumptions!$D$63:$F$63,1,2) -> 175000 | R14: =INDEX(Assumptions!$D$64:$F$64,1,2)+N14*INDEX(Assumptions!$D$65:$F$65,1,2) -> 165000 | S14: 1 | T14: 1 | U14: =MAX(0,S14-T14) -> 0 | V14: =INDEX('Evidence & Market'!$F$42:$F$44,MATCH($D14,'Evidence & Market'!$A$42:$A$44,0)) -> 0.9 | W14: =I14*V14 -> 5273.4375
A15: TOTAL | F15: =SUM(F6:F14) -> 7500000 | G15: =SUM(G6:G14) -> 38290016 | I15: =SUM(I6:I14) -> 58593.75 | J15: =SUM(J6:J14) -> 234.375 | K15: =SUM(K6:K14) -> 33.2 | N15: =SUM(N6:N14) -> 34500000 | O15: =SUM(O6:O14) -> 12075000 | P15: =SUM(P6:P14) -> 5175000 | Q15: =SUM(Q6:Q14) -> 1575000 | R15: =SUM(R6:R14) -> 1710000 | S15: =SUM(S6:S14) -> 11 | T15: =SUM(T6:T14) -> 9 | U15: =SUM(U6:U14) -> 2
A17: PROGRAMME BY YEAR
A18: Line | F18: Close | G18: Y1 | H18: Y2 | I18: Y3 | J18: Y4 | K18: Y5 | L18: Y6 | M18: Y7 | N18: Y8 | O18: Y9 | P18: Y10
A19: Deals closed | B19: deals | C19: [D] | F19: =COUNTIFS($E$6:$E$14,0) -> 1 | G19: =COUNTIFS($E$6:$E$14,1) -> 1 | H19: =COUNTIFS($E$6:$E$14,2) -> 1 | I19: =COUNTIFS($E$6:$E$14,3) -> 2 | J19: =COUNTIFS($E$6:$E$14,4) -> 1 | K19: =COUNTIFS($E$6:$E$14,5) -> 1 | L19: =COUNTIFS($E$6:$E$14,6) -> 1 | M19: =COUNTIFS($E$6:$E$14,7) -> 1 | N19: =COUNTIFS($E$6:$E$14,8) -> 0 | O19: =COUNTIFS($E$6:$E$14,9) -> 0 | P19: =COUNTIFS($E$6:$E$14,10) -> 0
A20: Acquired EBITDA at acquisition | B20: $ | C20: [OQ] | F20: =SUMIFS($F$6:$F$14,$E$6:$E$14,0) -> 1000000 | G20: =SUMIFS($F$6:$F$14,$E$6:$E$14,1) -> 750000 | H20: =SUMIFS($F$6:$F$14,$E$6:$E$14,2) -> 750000 | I20: =SUMIFS($F$6:$F$14,$E$6:$E$14,3) -> 2000000 | J20: =SUMIFS($F$6:$F$14,$E$6:$E$14,4) -> 750000 | K20: =SUMIFS($F$6:$F$14,$E$6:$E$14,5) -> 750000 | L20: =SUMIFS($F$6:$F$14,$E$6:$E$14,6) -> 750000 | M20: =SUMIFS($F$6:$F$14,$E$6:$E$14,7) -> 750000 | N20: =SUMIFS($F$6:$F$14,$E$6:$E$14,8) -> 0 | O20: =SUMIFS($F$6:$F$14,$E$6:$E$14,9) -> 0 | P20: =SUMIFS($F$6:$F$14,$E$6:$E$14,10) -> 0
A21: Acquired recurring revenue | B21: $ | C21: [C] | F21: =SUMIFS($G$6:$G$14,$E$6:$E$14,0) -> 5105335.5 | G21: =SUMIFS($G$6:$G$14,$E$6:$E$14,1) -> 3829001.6 | H21: =SUMIFS($G$6:$G$14,$E$6:$E$14,2) -> 3829001.6 | I21: =SUMIFS($G$6:$G$14,$E$6:$E$14,3) -> 10210671 | J21: =SUMIFS($G$6:$G$14,$E$6:$E$14,4) -> 3829001.6 | K21: =SUMIFS($G$6:$G$14,$E$6:$E$14,5) -> 3829001.6 | L21: =SUMIFS($G$6:$G$14,$E$6:$E$14,6) -> 3829001.6 | M21: =SUMIFS($G$6:$G$14,$E$6:$E$14,7) -> 3829001.6 | N21: =SUMIFS($G$6:$G$14,$E$6:$E$14,8) -> 0 | O21: =SUMIFS($G$6:$G$14,$E$6:$E$14,9) -> 0 | P21: =SUMIFS($G$6:$G$14,$E$6:$E$14,10) -> 0
A22: Units acquired | B22: units | C22: [C] | F22: =SUMIFS($I$6:$I$14,$E$6:$E$14,0) -> 7812.5 | G22: =SUMIFS($I$6:$I$14,$E$6:$E$14,1) -> 5859.375 | H22: =SUMIFS($I$6:$I$14,$E$6:$E$14,2) -> 5859.375 | I22: =SUMIFS($I$6:$I$14,$E$6:$E$14,3) -> 15625 | J22: =SUMIFS($I$6:$I$14,$E$6:$E$14,4) -> 5859.375 | K22: =SUMIFS($I$6:$I$14,$E$6:$E$14,5) -> 5859.375 | L22: =SUMIFS($I$6:$I$14,$E$6:$E$14,6) -> 5859.375 | M22: =SUMIFS($I$6:$I$14,$E$6:$E$14,7) -> 5859.375 | N22: =SUMIFS($I$6:$I$14,$E$6:$E$14,8) -> 0 | O22: =SUMIFS($I$6:$I$14,$E$6:$E$14,9) -> 0 | P22: =SUMIFS($I$6:$I$14,$E$6:$E$14,10) -> 0
A23: Properties acquired | B23: props | C23: [C] | F23: =SUMIFS($J$6:$J$14,$E$6:$E$14,0) -> 31.25 | G23: =SUMIFS($J$6:$J$14,$E$6:$E$14,1) -> 23.4375 | H23: =SUMIFS($J$6:$J$14,$E$6:$E$14,2) -> 23.4375 | I23: =SUMIFS($J$6:$J$14,$E$6:$E$14,3) -> 62.5 | J23: =SUMIFS($J$6:$J$14,$E$6:$E$14,4) -> 23.4375 | K23: =SUMIFS($J$6:$J$14,$E$6:$E$14,5) -> 23.4375 | L23: =SUMIFS($J$6:$J$14,$E$6:$E$14,6) -> 23.4375 | M23: =SUMIFS($J$6:$J$14,$E$6:$E$14,7) -> 23.4375 | N23: =SUMIFS($J$6:$J$14,$E$6:$E$14,8) -> 0 | O23: =SUMIFS($J$6:$J$14,$E$6:$E$14,9) -> 0 | P23: =SUMIFS($J$6:$J$14,$E$6:$E$14,10) -> 0
A24: Clients acquired | B24: clients | C24: [OQ] | F24: =SUMIFS($K$6:$K$14,$E$6:$E$14,0) -> 6 | G24: =SUMIFS($K$6:$K$14,$E$6:$E$14,1) -> 3.4 | H24: =SUMIFS($K$6:$K$14,$E$6:$E$14,2) -> 3.4 | I24: =SUMIFS($K$6:$K$14,$E$6:$E$14,3) -> 6.8 | J24: =SUMIFS($K$6:$K$14,$E$6:$E$14,4) -> 3.4 | K24: =SUMIFS($K$6:$K$14,$E$6:$E$14,5) -> 3.4 | L24: =SUMIFS($K$6:$K$14,$E$6:$E$14,6) -> 3.4 | M24: =SUMIFS($K$6:$K$14,$E$6:$E$14,7) -> 3.4 | N24: =SUMIFS($K$6:$K$14,$E$6:$E$14,8) -> 0 | O24: =SUMIFS($K$6:$K$14,$E$6:$E$14,9) -> 0 | P24: =SUMIFS($K$6:$K$14,$E$6:$E$14,10) -> 0
A25: Regimes acquired | B25: regimes | C25: [E] | F25: =SUMIFS($L$6:$L$14,$E$6:$E$14,0) -> 1.5 | G25: =SUMIFS($L$6:$L$14,$E$6:$E$14,1) -> 0.85 | H25: =SUMIFS($L$6:$L$14,$E$6:$E$14,2) -> 0.85 | I25: =SUMIFS($L$6:$L$14,$E$6:$E$14,3) -> 1.7 | J25: =SUMIFS($L$6:$L$14,$E$6:$E$14,4) -> 0.85 | K25: =SUMIFS($L$6:$L$14,$E$6:$E$14,5) -> 0.85 | L25: =SUMIFS($L$6:$L$14,$E$6:$E$14,6) -> 0.85 | M25: =SUMIFS($L$6:$L$14,$E$6:$E$14,7) -> 0.85 | N25: =SUMIFS($L$6:$L$14,$E$6:$E$14,8) -> 0 | O25: =SUMIFS($L$6:$L$14,$E$6:$E$14,9) -> 0 | P25: =SUMIFS($L$6:$L$14,$E$6:$E$14,10) -> 0
A26: Acquisition enterprise value | B26: $ | C26: [C] | F26: =SUMIFS($N$6:$N$14,$E$6:$E$14,0) -> 6000000 | G26: =SUMIFS($N$6:$N$14,$E$6:$E$14,1) -> 3000000 | H26: =SUMIFS($N$6:$N$14,$E$6:$E$14,2) -> 3000000 | I26: =SUMIFS($N$6:$N$14,$E$6:$E$14,3) -> 10500000 | J26: =SUMIFS($N$6:$N$14,$E$6:$E$14,4) -> 3000000 | K26: =SUMIFS($N$6:$N$14,$E$6:$E$14,5) -> 3000000 | L26: =SUMIFS($N$6:$N$14,$E$6:$E$14,6) -> 3000000 | M26: =SUMIFS($N$6:$N$14,$E$6:$E$14,7) -> 3000000 | N26: =SUMIFS($N$6:$N$14,$E$6:$E$14,8) -> 0 | O26: =SUMIFS($N$6:$N$14,$E$6:$E$14,9) -> 0 | P26: =SUMIFS($N$6:$N$14,$E$6:$E$14,10) -> 0
A27: Senior debt target | B27: $ | C27: [C] | F27: =SUMIFS($O$6:$O$14,$E$6:$E$14,0) -> 2100000 | G27: =SUMIFS($O$6:$O$14,$E$6:$E$14,1) -> 1050000 | H27: =SUMIFS($O$6:$O$14,$E$6:$E$14,2) -> 1050000 | I27: =SUMIFS($O$6:$O$14,$E$6:$E$14,3) -> 3675000 | J27: =SUMIFS($O$6:$O$14,$E$6:$E$14,4) -> 1050000 | K27: =SUMIFS($O$6:$O$14,$E$6:$E$14,5) -> 1050000 | L27: =SUMIFS($O$6:$O$14,$E$6:$E$14,6) -> 1050000 | M27: =SUMIFS($O$6:$O$14,$E$6:$E$14,7) -> 1050000 | N27: =SUMIFS($O$6:$O$14,$E$6:$E$14,8) -> 0 | O27: =SUMIFS($O$6:$O$14,$E$6:$E$14,9) -> 0 | P27: =SUMIFS($O$6:$O$14,$E$6:$E$14,10) -> 0
A28: Seller notes issued | B28: $ | C28: [C] | F28: =SUMIFS($P$6:$P$14,$E$6:$E$14,0) -> 900000 | G28: =SUMIFS($P$6:$P$14,$E$6:$E$14,1) -> 450000 | H28: =SUMIFS($P$6:$P$14,$E$6:$E$14,2) -> 450000 | I28: =SUMIFS($P$6:$P$14,$E$6:$E$14,3) -> 1575000 | J28: =SUMIFS($P$6:$P$14,$E$6:$E$14,4) -> 450000 | K28: =SUMIFS($P$6:$P$14,$E$6:$E$14,5) -> 450000 | L28: =SUMIFS($P$6:$P$14,$E$6:$E$14,6) -> 450000 | M28: =SUMIFS($P$6:$P$14,$E$6:$E$14,7) -> 450000 | N28: =SUMIFS($P$6:$P$14,$E$6:$E$14,8) -> 0 | O28: =SUMIFS($P$6:$P$14,$E$6:$E$14,9) -> 0 | P28: =SUMIFS($P$6:$P$14,$E$6:$E$14,10) -> 0
A29: Integration cost | B29: $ | C29: [A] | F29: =SUMIFS($Q$6:$Q$14,$E$6:$E$14,0) -> 175000 | G29: =SUMIFS($Q$6:$Q$14,$E$6:$E$14,1) -> 175000 | H29: =SUMIFS($Q$6:$Q$14,$E$6:$E$14,2) -> 175000 | I29: =SUMIFS($Q$6:$Q$14,$E$6:$E$14,3) -> 350000 | J29: =SUMIFS($Q$6:$Q$14,$E$6:$E$14,4) -> 175000 | K29: =SUMIFS($Q$6:$Q$14,$E$6:$E$14,5) -> 175000 | L29: =SUMIFS($Q$6:$Q$14,$E$6:$E$14,6) -> 175000 | M29: =SUMIFS($Q$6:$Q$14,$E$6:$E$14,7) -> 175000 | N29: =SUMIFS($Q$6:$Q$14,$E$6:$E$14,8) -> 0 | O29: =SUMIFS($Q$6:$Q$14,$E$6:$E$14,9) -> 0 | P29: =SUMIFS($Q$6:$Q$14,$E$6:$E$14,10) -> 0
A30: Transaction cost | B30: $ | C30: [A] | F30: =SUMIFS($R$6:$R$14,$E$6:$E$14,0) -> 255000 | G30: =SUMIFS($R$6:$R$14,$E$6:$E$14,1) -> 165000 | H30: =SUMIFS($R$6:$R$14,$E$6:$E$14,2) -> 165000 | I30: =SUMIFS($R$6:$R$14,$E$6:$E$14,3) -> 465000 | J30: =SUMIFS($R$6:$R$14,$E$6:$E$14,4) -> 165000 | K30: =SUMIFS($R$6:$R$14,$E$6:$E$14,5) -> 165000 | L30: =SUMIFS($R$6:$R$14,$E$6:$E$14,6) -> 165000 | M30: =SUMIFS($R$6:$R$14,$E$6:$E$14,7) -> 165000 | N30: =SUMIFS($R$6:$R$14,$E$6:$E$14,8) -> 0 | O30: =SUMIFS($R$6:$R$14,$E$6:$E$14,9) -> 0 | P30: =SUMIFS($R$6:$R$14,$E$6:$E$14,10) -> 0
A31: Senior leaders acquired | B31: FTE | C31: [A] | F31: =SUMIFS($S$6:$S$14,$E$6:$E$14,0) -> 2 | G31: =SUMIFS($S$6:$S$14,$E$6:$E$14,1) -> 1 | H31: =SUMIFS($S$6:$S$14,$E$6:$E$14,2) -> 1 | I31: =SUMIFS($S$6:$S$14,$E$6:$E$14,3) -> 3 | J31: =SUMIFS($S$6:$S$14,$E$6:$E$14,4) -> 1 | K31: =SUMIFS($S$6:$S$14,$E$6:$E$14,5) -> 1 | L31: =SUMIFS($S$6:$S$14,$E$6:$E$14,6) -> 1 | M31: =SUMIFS($S$6:$S$14,$E$6:$E$14,7) -> 1 | N31: =SUMIFS($S$6:$S$14,$E$6:$E$14,8) -> 0 | O31: =SUMIFS($S$6:$S$14,$E$6:$E$14,9) -> 0 | P31: =SUMIFS($S$6:$S$14,$E$6:$E$14,10) -> 0
A32: Senior leaders retained locally | B32: FTE | C32: [A] | F32: =SUMIFS($T$6:$T$14,$E$6:$E$14,0) -> 1 | G32: =SUMIFS($T$6:$T$14,$E$6:$E$14,1) -> 1 | H32: =SUMIFS($T$6:$T$14,$E$6:$E$14,2) -> 1 | I32: =SUMIFS($T$6:$T$14,$E$6:$E$14,3) -> 2 | J32: =SUMIFS($T$6:$T$14,$E$6:$E$14,4) -> 1 | K32: =SUMIFS($T$6:$T$14,$E$6:$E$14,5) -> 1 | L32: =SUMIFS($T$6:$T$14,$E$6:$E$14,6) -> 1 | M32: =SUMIFS($T$6:$T$14,$E$6:$E$14,7) -> 1 | N32: =SUMIFS($T$6:$T$14,$E$6:$E$14,8) -> 0 | O32: =SUMIFS($T$6:$T$14,$E$6:$E$14,9) -> 0 | P32: =SUMIFS($T$6:$T$14,$E$6:$E$14,10) -> 0
A33: Redundant senior leaders | B33: FTE | C33: [A] | F33: =SUMIFS($U$6:$U$14,$E$6:$E$14,0) -> 1 | G33: =SUMIFS($U$6:$U$14,$E$6:$E$14,1) -> 0 | H33: =SUMIFS($U$6:$U$14,$E$6:$E$14,2) -> 0 | I33: =SUMIFS($U$6:$U$14,$E$6:$E$14,3) -> 1 | J33: =SUMIFS($U$6:$U$14,$E$6:$E$14,4) -> 0 | K33: =SUMIFS($U$6:$U$14,$E$6:$E$14,5) -> 0 | L33: =SUMIFS($U$6:$U$14,$E$6:$E$14,6) -> 0 | M33: =SUMIFS($U$6:$U$14,$E$6:$E$14,7) -> 0 | N33: =SUMIFS($U$6:$U$14,$E$6:$E$14,8) -> 0 | O33: =SUMIFS($U$6:$U$14,$E$6:$E$14,9) -> 0 | P33: =SUMIFS($U$6:$U$14,$E$6:$E$14,10) -> 0
A34: Integration pods required | B34: pods | C34: [C] | F34: =IF(F19=0,0,CEILING(F19/INDEX(Assumptions!$D$84:$F$84,1,2),1)) -> 1 | G34: =IF(G19=0,0,CEILING(G19/INDEX(Assumptions!$D$84:$F$84,1,2),1)) -> 1 | H34: =IF(H19=0,0,CEILING(H19/INDEX(Assumptions!$D$84:$F$84,1,2),1)) -> 1 | I34: =IF(I19=0,0,CEILING(I19/INDEX(Assumptions!$D$84:$F$84,1,2),1)) -> 1 | J34: =IF(J19=0,0,CEILING(J19/INDEX(Assumptions!$D$84:$F$84,1,2),1)) -> 1 | K34: =IF(K19=0,0,CEILING(K19/INDEX(Assumptions!$D$84:$F$84,1,2),1)) -> 1 | L34: =IF(L19=0,0,CEILING(L19/INDEX(Assumptions!$D$84:$F$84,1,2),1)) -> 1 | M34: =IF(M19=0,0,CEILING(M19/INDEX(Assumptions!$D$84:$F$84,1,2),1)) -> 1 | ... P34: =IF(P19=0,0,CEILING(P19/INDEX(Assumptions!$D$84:$F$84,1,2),1)) -> 0
A35: Weighted market-support multiplier | B35: x | C35: [E] | F35: =IF(F22=0,1,SUMIFS($W$6:$W$14,$E$6:$E$14,0)/F22) -> 1 | G35: =IF(G22=0,1,SUMIFS($W$6:$W$14,$E$6:$E$14,1)/G22) -> 0.9 | H35: =IF(H22=0,1,SUMIFS($W$6:$W$14,$E$6:$E$14,2)/H22) -> 0.9 | I35: =IF(I22=0,1,SUMIFS($W$6:$W$14,$E$6:$E$14,3)/I22) -> 1.09375 | J35: =IF(J22=0,1,SUMIFS($W$6:$W$14,$E$6:$E$14,4)/J22) -> 0.9 | K35: =IF(K22=0,1,SUMIFS($W$6:$W$14,$E$6:$E$14,5)/K22) -> 1 | L35: =IF(L22=0,1,SUMIFS($W$6:$W$14,$E$6:$E$14,6)/L22) -> 0.9 | M35: =IF(M22=0,1,SUMIFS($W$6:$W$14,$E$6:$E$14,7)/M22) -> 0.9 | N35: =IF(N22=0,1,SUMIFS($W$6:$W$14,$E$6:$E$14,8)/N22) -> 1 | O35: =IF(O22=0,1,SUMIFS($W$6:$W$14,$E$6:$E$14,9)/O22) -> 1 | P35: =IF(P22=0,1,SUMIFS($W$6:$W$14,$E$6:$E$14,10)/P22) -> 1
A36: INDEPENDENT RECONSTRUCTION FROM PRIMITIVES (controls read these; none reads the column it is testing)
A37: Seller notes rebuilt from EV x share | B37: $ | C37: [C] | F37: =F26*INDEX(Assumptions!$D$98:$F$98,1,2) -> 900000 | G37: =G26*INDEX(Assumptions!$D$98:$F$98,1,2) -> 450000 | H37: =H26*INDEX(Assumptions!$D$98:$F$98,1,2) -> 450000 | I37: =I26*INDEX(Assumptions!$D$98:$F$98,1,2) -> 1575000 | J37: =J26*INDEX(Assumptions!$D$98:$F$98,1,2) -> 450000 | K37: =K26*INDEX(Assumptions!$D$98:$F$98,1,2) -> 450000 | L37: =L26*INDEX(Assumptions!$D$98:$F$98,1,2) -> 450000 | M37: =M26*INDEX(Assumptions!$D$98:$F$98,1,2) -> 450000 | ... P37: =P26*INDEX(Assumptions!$D$98:$F$98,1,2) -> 0
A38: Integration cost rebuilt from close count | B38: $ | C38: [C] | F38: =F19*INDEX(Assumptions!$D$63:$F$63,1,2) -> 175000 | G38: =G19*INDEX(Assumptions!$D$63:$F$63,1,2) -> 175000 | H38: =H19*INDEX(Assumptions!$D$63:$F$63,1,2) -> 175000 | I38: =I19*INDEX(Assumptions!$D$63:$F$63,1,2) -> 350000 | J38: =J19*INDEX(Assumptions!$D$63:$F$63,1,2) -> 175000 | K38: =K19*INDEX(Assumptions!$D$63:$F$63,1,2) -> 175000 | L38: =L19*INDEX(Assumptions!$D$63:$F$63,1,2) -> 175000 | M38: =M19*INDEX(Assumptions!$D$63:$F$63,1,2) -> 175000 | ... P38: =P19*INDEX(Assumptions!$D$63:$F$63,1,2) -> 0
A39: Transaction cost rebuilt from close count and EV | B39: $ | C39: [C] | F39: =F19*INDEX(Assumptions!$D$64:$F$64,1,2)+F26*INDEX(Assumptions!$D$65:$F$65,1,2) -> 255000 | G39: =G19*INDEX(Assumptions!$D$64:$F$64,1,2)+G26*INDEX(Assumptions!$D$65:$F$65,1,2) -> 165000 | H39: =H19*INDEX(Assumptions!$D$64:$F$64,1,2)+H26*INDEX(Assumptions!$D$65:$F$65,1,2) -> 165000 | I39: =I19*INDEX(Assumptions!$D$64:$F$64,1,2)+I26*INDEX(Assumptions!$D$65:$F$65,1,2) -> 465000 | J39: =J19*INDEX(Assumptions!$D$64:$F$64,1,2)+J26*INDEX(Assumptions!$D$65:$F$65,1,2) -> 165000 | K39: =K19*INDEX(Assumptions!$D$64:$F$64,1,2)+K26*INDEX(Assumptions!$D$65:$F$65,1,2) -> 165000 | L39: =L19*INDEX(Assumptions!$D$64:$F$64,1,2)+L26*INDEX(Assumptions!$D$65:$F$65,1,2) -> 165000 | M39: =M19*INDEX(Assumptions!$D$64:$F$64,1,2)+M26*INDEX(Assumptions!$D$65:$F$65,1,2) -> 165000 | ... P39: =P19*INDEX(Assumptions!$D$64:$F$64,1,2)+P26*INDEX(Assumptions!$D$65:$F$65,1,2) -> 0
A40: Roll-up versus reconstruction — must be nil | B40: $ | C40: [C] | F40: =ABS(F28-F37)+ABS(F29-F38)+ABS(F30-F39) -> 0 | G40: =ABS(G28-G37)+ABS(G29-G38)+ABS(G30-G39) -> 0 | H40: =ABS(H28-H37)+ABS(H29-H38)+ABS(H30-H39) -> 0 | I40: =ABS(I28-I37)+ABS(I29-I38)+ABS(I30-I39) -> 0 | J40: =ABS(J28-J37)+ABS(J29-J38)+ABS(J30-J39) -> 0 | K40: =ABS(K28-K37)+ABS(K29-K38)+ABS(K30-K39) -> 0 | L40: =ABS(L28-L37)+ABS(L29-L38)+ABS(L30-L39) -> 0 | M40: =ABS(M28-M37)+ABS(M29-M38)+ABS(M30-M39) -> 0 | ... P40: =ABS(P28-P37)+ABS(P29-P38)+ABS(P30-P39) -> 0
A41: Maximum reconstruction difference across all years | B41: $ | C41: [C] | F41: =MAX(F40:P40) -> 0
A42: PROGRAMME CONSTRAINT DIAGNOSTIC — cadence and the Year-7 managed-unit ceiling
A43: The ceiling is a Year-7 MANAGED-unit constraint, not a cap on cumulative units ever purchased. Attrition, change-of-control loss and vintage retention sit between the two, so gross acquired units are shown as a memo only.
A44: Large tuck-ins in the programme | B44: n / units | C44: [C] | F44: =COUNTIFS($B$6:$B$14,"Large tuck-in") -> 7
A45: Years in the acquisition window | B45: n / units | C45: [C] | F45: =INDEX(Assumptions!$D$13:$F$13,1,2) -> 7
A46: One large deal per year satisfied | B46: n / units | C46: [C] | F46: =IF(F44>=F45,"YES","NO") -> YES
A47: Cumulative gross units acquired — memo only | B47: n / units | C47: [C] | F47: =SUM($I$6:$I$14) -> 58593.75
A48: The ceiling is a Year-7 MANAGED-unit constraint. Gross units acquired are a memo only; the headroom test and filler capacity are computed on Operating Case where retained units live. | B48: n / units | C48: [C] | F48: =INDEX(Assumptions!$D$36:$F$36,1,2)/INDEX(Assumptions!$D$32:$F$32,1,2) -> 3906.25
A50: Units-weighted from each deal acquisition class. Applied on Org & Capacity only to field supervision, local recruiting and training, client coverage and travel — never to property accounting, AP/AR or centralised technology.

Sheet Anchor QoE
A1: ANCHOR QoE AND CONTRACT DURABILITY
A2: Durability is underwritten on retained recurring revenue, contract rights, concentration and EBITDA contribution. No synthetic client gross profit is invented until a target GL supports direct cost allocation.
A4: Line | D4: Close | E4: Year 1 | F4: Year 2 | G4: Year 3 | H4: Year 4 | I4: Year 5 | J4: Year 6 | K4: Year 7 | L4: Year 8 | M4: Year 9 | N4: Year 10
A6: CONTRACT DURABILITY BY PMA CATEGORY
E7: Downside | F7: Base | G7: Upside | I7: Downside retention | J7: Base retention | K7: Upside retention
A8: Institutional owner | B8: % / % | C8: [C]/[A] | E8: =INDEX(Assumptions!$D$50:$F$50,1,1) -> 0.35 | F8: =INDEX(Assumptions!$D$50:$F$50,1,2) -> 0.35 | G8: =INDEX(Assumptions!$D$50:$F$50,1,3) -> 0.35 | I8: =INDEX(Assumptions!$D$51:$F$51,1,1) -> 0.85 | J8: =INDEX(Assumptions!$D$51:$F$51,1,2) -> 0.88 | K8: =INDEX(Assumptions!$D$51:$F$51,1,3) -> 0.91 | N8: 30-day termination without cause; assignment consent required
A9: Regional owner | B9: % / % | C9: [C]/[A] | E9: =INDEX(Assumptions!$D$52:$F$52,1,1) -> 0.4 | F9: =INDEX(Assumptions!$D$52:$F$52,1,2) -> 0.4 | G9: =INDEX(Assumptions!$D$52:$F$52,1,3) -> 0.4 | I9: =INDEX(Assumptions!$D$53:$F$53,1,1) -> 0.9 | J9: =INDEX(Assumptions!$D$53:$F$53,1,2) -> 0.92 | K9: =INDEX(Assumptions!$D$53:$F$53,1,3) -> 0.94 | N9: 60-90 day termination; change-of-control consent
A10: Developer / lease-up | B10: % / % | C10: [C]/[A] | E10: =INDEX(Assumptions!$D$54:$F$54,1,1) -> 0.25 | F10: =INDEX(Assumptions!$D$54:$F$54,1,2) -> 0.25 | G10: =INDEX(Assumptions!$D$54:$F$54,1,3) -> 0.25 | I10: =INDEX(Assumptions!$D$55:$F$55,1,1) -> 0.92 | J10: =INDEX(Assumptions!$D$55:$F$55,1,2) -> 0.94 | K10: =INDEX(Assumptions!$D$55:$F$55,1,3) -> 0.96 | N10: Term contract to stabilisation; assignment generally permitted
A11: Category shares sum to 100% | B11: % | C11: [C] | E11: =SUM(E8:E10) -> 1 | F11: =SUM(F8:F10) -> 1 | G11: =SUM(G8:G10) -> 1
A12: Blended annual revenue retention | B12: % | C12: [C] | E12: =SUMPRODUCT(E8:E10,I8:I10)/E11 -> 0.8875 | F12: =SUMPRODUCT(F8:F10,J8:J10)/F11 -> 0.911 | G12: =SUMPRODUCT(G8:G10,K8:K10)/G11 -> 0.9345
A13: Implied average contract life | B13: years | C13: [C] | E13: =IF(E12>=1,99,1/(1-E12)) -> 8.8888889 | F13: =IF(F12>=1,99,1/(1-F12)) -> 11.235955 | G13: =IF(G12>=1,99,1/(1-G12)) -> 15.267176
A14: Change-of-control loss at close | B14: % | C14: [A] | E14: =INDEX(Assumptions!$D$56:$F$56,1,1) -> 0.09 | F14: =INDEX(Assumptions!$D$56:$F$56,1,2) -> 0.06 | G14: =INDEX(Assumptions!$D$56:$F$56,1,3) -> 0.04
A16: ANCHOR ACQUISITION BASIS (at-close facts, frozen across cases)
A17: Normalized EBITDA at close | B17: $ / x | C17: [OQ] | D17: ='Acquisition Schedule'!$F$6 -> 1000000
A18: Recurring revenue at close | B18: $ / x | C18: [OQ] | D18: ='Acquisition Schedule'!$G$6 -> 5105335.5
A19: Normalized EBITDA margin | B19: $ / x | C19: [OQ] | D19: ='Acquisition Schedule'!$H$6 -> 0.19587351
A20: Units at close | B20: $ / x | C20: [OQ] | D20: ='Acquisition Schedule'!$I$6 -> 7812.5
A21: Properties at close | B21: $ / x | C21: [OQ] | D21: ='Acquisition Schedule'!$J$6 -> 31.25
A22: Clients at close | B22: $ / x | C22: [OQ] | D22: ='Acquisition Schedule'!$K$6 -> 6
A23: Entry multiple | B23: $ / x | C23: [OQ] | D23: ='Acquisition Schedule'!$M$6 -> 6
A24: Enterprise value | B24: $ / x | C24: [OQ] | D24: ='Acquisition Schedule'!$N$6 -> 6000000
A25: EV as a multiple of recurring revenue | B25: x | C25: [C] | D25: =D24/D18 -> 1.1752411
A26: Largest client share of acquired revenue | B26: % | C26: [OQ] | D26: =1/D22 -> 0.16666667 | N26: Equal-share proxy. Replace with the target client schedule.

Sheet Revenue & Durability
A1: REVENUE AND DURABILITY — VINTAGE RETENTION BY CASE
A2: Net factor = retention x (1 + standalone wins + platform uplift). New business is separated into what the target wins on its own capability, which is purchased, and what the platform adds, which is buyer-created and switches off with the evidence flag.
A3: Revenue, EBITDA margin and EBITDA reconcile by construction. Third-party pass-through sits in revenue and is excluded from EBITDA contribution.
A5: Line | D5: Close | E5: Year 1 | F5: Year 2 | G5: Year 3 | H5: Year 4 | I5: Year 5 | J5: Year 6 | K5: Year 7 | L5: Year 8 | M5: Year 9 | N5: Year 10
A7: DOWNSIDE
A8: Blended annual contract retention | B8: % | C8: [C] | D8: ='Anchor QoE'!E$12 -> 0.8875
A9: Gross annual contract churn | B9: % | C9: [C] | D9: =1-D8 -> 0.1125
A10: Gross new-business wins — target standalone capability | B10: % | C10: [C] | D10: =INDEX(Assumptions!$D$57:$F$57,1,1) -> 0.08
A11: Gross new-business wins — platform uplift | B11: % | C11: [A] | D11: =(INDEX(Assumptions!$D$58:$F$58,1,1)*(1-Assumptions!$D$8)) -> 0.02
A12: Net annual factor — standalone counterfactual | B12: x | C12: [C] | D12: =D8*(1+D10) -> 0.9585
A13: NET ANNUAL FACTOR INSIDE THE PLATFORM | B13: x | C13: [C] | D13: =D8*(1+D10+D11) -> 0.97625
A14: Platform growth advantage over standalone | B14: pts | C14: [A] | D14: =D13-D12 -> 0.01775
A15: Ownership must not make an acquired business grow more slowly than it would have alone. The advantage line is the platform contribution, and it can never be negative by construction because the uplift is additive.
A16: Close-year part-period factor | B16: % | C16: [C] | D16: =(1-INDEX(Assumptions!$D$56:$F$56,1,1))*INDEX(Assumptions!$D$20:$F$20,1,1) -> 0.455
A17: Not a retention rate. A deal closing mid-year contributes only part of a full year of EBITDA in its close year, and the book that survives change of control is smaller. Half a year of ownership at 94 percent surviving change of control gives 47 percent of a full year. The anchor is grossed back to a full year because it is owned from day one.
A18: Contracted vintage — anchor at close | B18: $ | C18: [C] | D18: ='Acquisition Schedule'!F$20*$D$16/INDEX(Assumptions!$D$20:$F$20,1,1) -> 910000 | E18: ='Acquisition Schedule'!F$20*(1-INDEX(Assumptions!$D$56:$F$56,1,1))*$D$8^0 -> 910000 | F18: ='Acquisition Schedule'!F$20*(1-INDEX(Assumptions!$D$56:$F$56,1,1))*$D$8^1 -> 807625 | G18: ='Acquisition Schedule'!F$20*(1-INDEX(Assumptions!$D$56:$F$56,1,1))*$D$8^2 -> 716767.19 | H18: ='Acquisition Schedule'!F$20*(1-INDEX(Assumptions!$D$56:$F$56,1,1))*$D$8^3 -> 636130.88 | I18: ='Acquisition Schedule'!F$20*(1-INDEX(Assumptions!$D$56:$F$56,1,1))*$D$8^4 -> 564566.16 | J18: ='Acquisition Schedule'!F$20*(1-INDEX(Assumptions!$D$56:$F$56,1,1))*$D$8^5 -> 501052.46 | K18: ='Acquisition Schedule'!F$20*(1-INDEX(Assumptions!$D$56:$F$56,1,1))*$D$8^6 -> 444684.06 | L18: ='Acquisition Schedule'!F$20*(1-INDEX(Assumptions!$D$56:$F$56,1,1))*$D$8^7 -> 394657.1 | M18: ='Acquisition Schedule'!F$20*(1-INDEX(Assumptions!$D$56:$F$56,1,1))*$D$8^8 -> 350258.18 | N18: ='Acquisition Schedule'!F$20*(1-INDEX(Assumptions!$D$56:$F$56,1,1))*$D$8^9 -> 310854.13
A19: Contracted vintage Year 1 | B19: $ | C19: [C] | D19: =0 -> 0 | E19: ='Acquisition Schedule'!G$20*$D$16 -> 341250 | F19: ='Acquisition Schedule'!G$20*(1-INDEX(Assumptions!$D$56:$F$56,1,1))*$D$8^0 -> 682500 | G19: ='Acquisition Schedule'!G$20*(1-INDEX(Assumptions!$D$56:$F$56,1,1))*$D$8^1 -> 605718.75 | H19: ='Acquisition Schedule'!G$20*(1-INDEX(Assumptions!$D$56:$F$56,1,1))*$D$8^2 -> 537575.39 | I19: ='Acquisition Schedule'!G$20*(1-INDEX(Assumptions!$D$56:$F$56,1,1))*$D$8^3 -> 477098.16 | J19: ='Acquisition Schedule'!G$20*(1-INDEX(Assumptions!$D$56:$F$56,1,1))*$D$8^4 -> 423424.62 | K19: ='Acquisition Schedule'!G$20*(1-INDEX(Assumptions!$D$56:$F$56,1,1))*$D$8^5 -> 375789.35 | L19: ='Acquisition Schedule'!G$20*(1-INDEX(Assumptions!$D$56:$F$56,1,1))*$D$8^6 -> 333513.05 | M19: ='Acquisition Schedule'!G$20*(1-INDEX(Assumptions!$D$56:$F$56,1,1))*$D$8^7 -> 295992.83 | N19: ='Acquisition Schedule'!G$20*(1-INDEX(Assumptions!$D$56:$F$56,1,1))*$D$8^8 -> 262693.63
A20: Contracted vintage Year 2 | B20: $ | C20: [C] | D20: =0 -> 0 | E20: =0 -> 0 | F20: ='Acquisition Schedule'!H$20*$D$16 -> 341250 | G20: ='Acquisition Schedule'!H$20*(1-INDEX(Assumptions!$D$56:$F$56,1,1))*$D$8^0 -> 682500 | H20: ='Acquisition Schedule'!H$20*(1-INDEX(Assumptions!$D$56:$F$56,1,1))*$D$8^1 -> 605718.75 | I20: ='Acquisition Schedule'!H$20*(1-INDEX(Assumptions!$D$56:$F$56,1,1))*$D$8^2 -> 537575.39 | J20: ='Acquisition Schedule'!H$20*(1-INDEX(Assumptions!$D$56:$F$56,1,1))*$D$8^3 -> 477098.16 | K20: ='Acquisition Schedule'!H$20*(1-INDEX(Assumptions!$D$56:$F$56,1,1))*$D$8^4 -> 423424.62 | L20: ='Acquisition Schedule'!H$20*(1-INDEX(Assumptions!$D$56:$F$56,1,1))*$D$8^5 -> 375789.35 | M20: ='Acquisition Schedule'!H$20*(1-INDEX(Assumptions!$D$56:$F$56,1,1))*$D$8^6 -> 333513.05 | N20: ='Acquisition Schedule'!H$20*(1-INDEX(Assumptions!$D$56:$F$56,1,1))*$D$8^7 -> 295992.83
A21: Contracted vintage Year 3 | B21: $ | C21: [C] | D21: =0 -> 0 | E21: =0 -> 0 | F21: =0 -> 0 | G21: ='Acquisition Schedule'!I$20*$D$16 -> 910000 | H21: ='Acquisition Schedule'!I$20*(1-INDEX(Assumptions!$D$56:$F$56,1,1))*$D$8^0 -> 1820000 | I21: ='Acquisition Schedule'!I$20*(1-INDEX(Assumptions!$D$56:$F$56,1,1))*$D$8^1 -> 1615250 | J21: ='Acquisition Schedule'!I$20*(1-INDEX(Assumptions!$D$56:$F$56,1,1))*$D$8^2 -> 1433534.4 | K21: ='Acquisition Schedule'!I$20*(1-INDEX(Assumptions!$D$56:$F$56,1,1))*$D$8^3 -> 1272261.8 | L21: ='Acquisition Schedule'!I$20*(1-INDEX(Assumptions!$D$56:$F$56,1,1))*$D$8^4 -> 1129132.3 | M21: ='Acquisition Schedule'!I$20*(1-INDEX(Assumptions!$D$56:$F$56,1,1))*$D$8^5 -> 1002104.9 | N21: ='Acquisition Schedule'!I$20*(1-INDEX(Assumptions!$D$56:$F$56,1,1))*$D$8^6 -> 889368.12
A22: Contracted vintage Year 4 | B22: $ | C22: [C] | D22: =0 -> 0 | E22: =0 -> 0 | F22: =0 -> 0 | G22: =0 -> 0 | H22: ='Acquisition Schedule'!J$20*$D$16 -> 341250 | I22: ='Acquisition Schedule'!J$20*(1-INDEX(Assumptions!$D$56:$F$56,1,1))*$D$8^0 -> 682500 | J22: ='Acquisition Schedule'!J$20*(1-INDEX(Assumptions!$D$56:$F$56,1,1))*$D$8^1 -> 605718.75 | K22: ='Acquisition Schedule'!J$20*(1-INDEX(Assumptions!$D$56:$F$56,1,1))*$D$8^2 -> 537575.39 | L22: ='Acquisition Schedule'!J$20*(1-INDEX(Assumptions!$D$56:$F$56,1,1))*$D$8^3 -> 477098.16 | M22: ='Acquisition Schedule'!J$20*(1-INDEX(Assumptions!$D$56:$F$56,1,1))*$D$8^4 -> 423424.62 | N22: ='Acquisition Schedule'!J$20*(1-INDEX(Assumptions!$D$56:$F$56,1,1))*$D$8^5 -> 375789.35
A23: Contracted vintage Year 5 | B23: $ | C23: [C] | D23: =0 -> 0 | E23: =0 -> 0 | F23: =0 -> 0 | G23: =0 -> 0 | H23: =0 -> 0 | I23: ='Acquisition Schedule'!K$20*$D$16 -> 341250 | J23: ='Acquisition Schedule'!K$20*(1-INDEX(Assumptions!$D$56:$F$56,1,1))*$D$8^0 -> 682500 | K23: ='Acquisition Schedule'!K$20*(1-INDEX(Assumptions!$D$56:$F$56,1,1))*$D$8^1 -> 605718.75 | L23: ='Acquisition Schedule'!K$20*(1-INDEX(Assumptions!$D$56:$F$56,1,1))*$D$8^2 -> 537575.39 | M23: ='Acquisition Schedule'!K$20*(1-INDEX(Assumptions!$D$56:$F$56,1,1))*$D$8^3 -> 477098.16 | N23: ='Acquisition Schedule'!K$20*(1-INDEX(Assumptions!$D$56:$F$56,1,1))*$D$8^4 -> 423424.62
A24: Contracted vintage Year 6 | B24: $ | C24: [C] | D24: =0 -> 0 | E24: =0 -> 0 | F24: =0 -> 0 | G24: =0 -> 0 | H24: =0 -> 0 | I24: =0 -> 0 | J24: ='Acquisition Schedule'!L$20*$D$16 -> 341250 | K24: ='Acquisition Schedule'!L$20*(1-INDEX(Assumptions!$D$56:$F$56,1,1))*$D$8^0 -> 682500 | L24: ='Acquisition Schedule'!L$20*(1-INDEX(Assumptions!$D$56:$F$56,1,1))*$D$8^1 -> 605718.75 | M24: ='Acquisition Schedule'!L$20*(1-INDEX(Assumptions!$D$56:$F$56,1,1))*$D$8^2 -> 537575.39 | N24: ='Acquisition Schedule'!L$20*(1-INDEX(Assumptions!$D$56:$F$56,1,1))*$D$8^3 -> 477098.16
A25: Contracted vintage Year 7 | B25: $ | C25: [C] | D25: =0 -> 0 | E25: =0 -> 0 | F25: =0 -> 0 | G25: =0 -> 0 | H25: =0 -> 0 | I25: =0 -> 0 | J25: =0 -> 0 | K25: ='Acquisition Schedule'!M$20*$D$16 -> 341250 | L25: ='Acquisition Schedule'!M$20*(1-INDEX(Assumptions!$D$56:$F$56,1,1))*$D$8^0 -> 682500 | M25: ='Acquisition Schedule'!M$20*(1-INDEX(Assumptions!$D$56:$F$56,1,1))*$D$8^1 -> 605718.75 | N25: ='Acquisition Schedule'!M$20*(1-INDEX(Assumptions!$D$56:$F$56,1,1))*$D$8^2 -> 537575.39
A26: Contracted business only: change-of-control loss once at close, then contractual retention. No new business. This is what was purchased and it is what the source-specific valuation capitalises at the multiple actually paid.
A27: Organic wins on the anchor | B27: $ | C27: [A] | D27: =0 -> 0 | E27: ='Acquisition Schedule'!F$20*(1-INDEX(Assumptions!$D$56:$F$56,1,1))*($D$13^0-$D$8^0) -> 0 | F27: ='Acquisition Schedule'!F$20*(1-INDEX(Assumptions!$D$56:$F$56,1,1))*($D$13^1-$D$8^1) -> 80762.5 | G27: ='Acquisition Schedule'!F$20*(1-INDEX(Assumptions!$D$56:$F$56,1,1))*($D$13^2-$D$8^2) -> 150521.11 | H27: ='Acquisition Schedule'!F$20*(1-INDEX(Assumptions!$D$56:$F$56,1,1))*($D$13^3-$D$8^3) -> 210559.32 | I27: ='Acquisition Schedule'!F$20*(1-INDEX(Assumptions!$D$56:$F$56,1,1))*($D$13^4-$D$8^4) -> 262015.15 | J27: ='Acquisition Schedule'!F$20*(1-INDEX(Assumptions!$D$56:$F$56,1,1))*($D$13^5-$D$8^5) -> 305897.54 | K27: ='Acquisition Schedule'!F$20*(1-INDEX(Assumptions!$D$56:$F$56,1,1))*($D$13^6-$D$8^6) -> 343100.88 | L27: ='Acquisition Schedule'!F$20*(1-INDEX(Assumptions!$D$56:$F$56,1,1))*($D$13^7-$D$8^7) -> 374417.94 | M27: ='Acquisition Schedule'!F$20*(1-INDEX(Assumptions!$D$56:$F$56,1,1))*($D$13^8-$D$8^8) -> 400551.33 | N27: ='Acquisition Schedule'!F$20*(1-INDEX(Assumptions!$D$56:$F$56,1,1))*($D$13^9-$D$8^9) -> 422123.65
A28: Organic wins on the Year 1 vintage | B28: $ | C28: [A] | D28: =0 -> 0 | E28: =0 -> 0 | F28: ='Acquisition Schedule'!G$20*(1-INDEX(Assumptions!$D$56:$F$56,1,1))*($D$13^0-$D$8^0) -> 0 | G28: ='Acquisition Schedule'!G$20*(1-INDEX(Assumptions!$D$56:$F$56,1,1))*($D$13^1-$D$8^1) -> 60571.875 | H28: ='Acquisition Schedule'!G$20*(1-INDEX(Assumptions!$D$56:$F$56,1,1))*($D$13^2-$D$8^2) -> 112890.83 | I28: ='Acquisition Schedule'!G$20*(1-INDEX(Assumptions!$D$56:$F$56,1,1))*($D$13^3-$D$8^3) -> 157919.49 | J28: ='Acquisition Schedule'!G$20*(1-INDEX(Assumptions!$D$56:$F$56,1,1))*($D$13^4-$D$8^4) -> 196511.36 | K28: ='Acquisition Schedule'!G$20*(1-INDEX(Assumptions!$D$56:$F$56,1,1))*($D$13^5-$D$8^5) -> 229423.15 | L28: ='Acquisition Schedule'!G$20*(1-INDEX(Assumptions!$D$56:$F$56,1,1))*($D$13^6-$D$8^6) -> 257325.66 | M28: ='Acquisition Schedule'!G$20*(1-INDEX(Assumptions!$D$56:$F$56,1,1))*($D$13^7-$D$8^7) -> 280813.46 | N28: ='Acquisition Schedule'!G$20*(1-INDEX(Assumptions!$D$56:$F$56,1,1))*($D$13^8-$D$8^8) -> 300413.5
A29: Organic wins on the Year 2 vintage | B29: $ | C29: [A] | D29: =0 -> 0 | E29: =0 -> 0 | F29: =0 -> 0 | G29: ='Acquisition Schedule'!H$20*(1-INDEX(Assumptions!$D$56:$F$56,1,1))*($D$13^0-$D$8^0) -> 0 | H29: ='Acquisition Schedule'!H$20*(1-INDEX(Assumptions!$D$56:$F$56,1,1))*($D$13^1-$D$8^1) -> 60571.875 | I29: ='Acquisition Schedule'!H$20*(1-INDEX(Assumptions!$D$56:$F$56,1,1))*($D$13^2-$D$8^2) -> 112890.83 | J29: ='Acquisition Schedule'!H$20*(1-INDEX(Assumptions!$D$56:$F$56,1,1))*($D$13^3-$D$8^3) -> 157919.49 | K29: ='Acquisition Schedule'!H$20*(1-INDEX(Assumptions!$D$56:$F$56,1,1))*($D$13^4-$D$8^4) -> 196511.36 | L29: ='Acquisition Schedule'!H$20*(1-INDEX(Assumptions!$D$56:$F$56,1,1))*($D$13^5-$D$8^5) -> 229423.15 | M29: ='Acquisition Schedule'!H$20*(1-INDEX(Assumptions!$D$56:$F$56,1,1))*($D$13^6-$D$8^6) -> 257325.66 | N29: ='Acquisition Schedule'!H$20*(1-INDEX(Assumptions!$D$56:$F$56,1,1))*($D$13^7-$D$8^7) -> 280813.46
A30: Organic wins on the Year 3 vintage | B30: $ | C30: [A] | D30: =0 -> 0 | E30: =0 -> 0 | F30: =0 -> 0 | G30: =0 -> 0 | H30: ='Acquisition Schedule'!I$20*(1-INDEX(Assumptions!$D$56:$F$56,1,1))*($D$13^0-$D$8^0) -> 0 | I30: ='Acquisition Schedule'!I$20*(1-INDEX(Assumptions!$D$56:$F$56,1,1))*($D$13^1-$D$8^1) -> 161525 | J30: ='Acquisition Schedule'!I$20*(1-INDEX(Assumptions!$D$56:$F$56,1,1))*($D$13^2-$D$8^2) -> 301042.22 | K30: ='Acquisition Schedule'!I$20*(1-INDEX(Assumptions!$D$56:$F$56,1,1))*($D$13^3-$D$8^3) -> 421118.64 | L30: ='Acquisition Schedule'!I$20*(1-INDEX(Assumptions!$D$56:$F$56,1,1))*($D$13^4-$D$8^4) -> 524030.31 | M30: ='Acquisition Schedule'!I$20*(1-INDEX(Assumptions!$D$56:$F$56,1,1))*($D$13^5-$D$8^5) -> 611795.08 | N30: ='Acquisition Schedule'!I$20*(1-INDEX(Assumptions!$D$56:$F$56,1,1))*($D$13^6-$D$8^6) -> 686201.76
A31: Organic wins on the Year 4 vintage | B31: $ | C31: [A] | D31: =0 -> 0 | E31: =0 -> 0 | F31: =0 -> 0 | G31: =0 -> 0 | H31: =0 -> 0 | I31: ='Acquisition Schedule'!J$20*(1-INDEX(Assumptions!$D$56:$F$56,1,1))*($D$13^0-$D$8^0) -> 0 | J31: ='Acquisition Schedule'!J$20*(1-INDEX(Assumptions!$D$56:$F$56,1,1))*($D$13^1-$D$8^1) -> 60571.875 | K31: ='Acquisition Schedule'!J$20*(1-INDEX(Assumptions!$D$56:$F$56,1,1))*($D$13^2-$D$8^2) -> 112890.83 | L31: ='Acquisition Schedule'!J$20*(1-INDEX(Assumptions!$D$56:$F$56,1,1))*($D$13^3-$D$8^3) -> 157919.49 | M31: ='Acquisition Schedule'!J$20*(1-INDEX(Assumptions!$D$56:$F$56,1,1))*($D$13^4-$D$8^4) -> 196511.36 | N31: ='Acquisition Schedule'!J$20*(1-INDEX(Assumptions!$D$56:$F$56,1,1))*($D$13^5-$D$8^5) -> 229423.15
A32: Organic wins on the Year 5 vintage | B32: $ | C32: [A] | D32: =0 -> 0 | E32: =0 -> 0 | F32: =0 -> 0 | G32: =0 -> 0 | H32: =0 -> 0 | I32: =0 -> 0 | J32: ='Acquisition Schedule'!K$20*(1-INDEX(Assumptions!$D$56:$F$56,1,1))*($D$13^0-$D$8^0) -> 0 | K32: ='Acquisition Schedule'!K$20*(1-INDEX(Assumptions!$D$56:$F$56,1,1))*($D$13^1-$D$8^1) -> 60571.875 | L32: ='Acquisition Schedule'!K$20*(1-INDEX(Assumptions!$D$56:$F$56,1,1))*($D$13^2-$D$8^2) -> 112890.83 | M32: ='Acquisition Schedule'!K$20*(1-INDEX(Assumptions!$D$56:$F$56,1,1))*($D$13^3-$D$8^3) -> 157919.49 | N32: ='Acquisition Schedule'!K$20*(1-INDEX(Assumptions!$D$56:$F$56,1,1))*($D$13^4-$D$8^4) -> 196511.36
A33: Organic wins on the Year 6 vintage | B33: $ | C33: [A] | D33: =0 -> 0 | E33: =0 -> 0 | F33: =0 -> 0 | G33: =0 -> 0 | H33: =0 -> 0 | I33: =0 -> 0 | J33: =0 -> 0 | K33: ='Acquisition Schedule'!L$20*(1-INDEX(Assumptions!$D$56:$F$56,1,1))*($D$13^0-$D$8^0) -> 0 | L33: ='Acquisition Schedule'!L$20*(1-INDEX(Assumptions!$D$56:$F$56,1,1))*($D$13^1-$D$8^1) -> 60571.875 | M33: ='Acquisition Schedule'!L$20*(1-INDEX(Assumptions!$D$56:$F$56,1,1))*($D$13^2-$D$8^2) -> 112890.83 | N33: ='Acquisition Schedule'!L$20*(1-INDEX(Assumptions!$D$56:$F$56,1,1))*($D$13^3-$D$8^3) -> 157919.49
A34: Organic wins on the Year 7 vintage | B34: $ | C34: [A] | D34: =0 -> 0 | E34: =0 -> 0 | F34: =0 -> 0 | G34: =0 -> 0 | H34: =0 -> 0 | I34: =0 -> 0 | J34: =0 -> 0 | K34: =0 -> 0 | L34: ='Acquisition Schedule'!M$20*(1-INDEX(Assumptions!$D$56:$F$56,1,1))*($D$13^0-$D$8^0) -> 0 | M34: ='Acquisition Schedule'!M$20*(1-INDEX(Assumptions!$D$56:$F$56,1,1))*($D$13^1-$D$8^1) -> 60571.875 | N34: ='Acquisition Schedule'!M$20*(1-INDEX(Assumptions!$D$56:$F$56,1,1))*($D$13^2-$D$8^2) -> 112890.83
A35: Gross new business the book wins after close, contracted roll-forward removed. Buyer-created, subject to the capacity ceiling and zeroed by the evidence switch.
A36: CONTRACTED ACQUIRED EBITDA | B36: $ | C36: [C] | D36: =SUM(D18:D25) -> 910000 | E36: =SUM(E18:E25) -> 1251250 | F36: =SUM(F18:F25) -> 1831375 | G36: =SUM(G18:G25) -> 2914985.9 | H36: =SUM(H18:H25) -> 3940675 | I36: =SUM(I18:I25) -> 4218239.7 | J36: =SUM(J18:J25) -> 4464578.4 | K36: =SUM(K18:K25) -> 4683203.9 | ... N36: =SUM(N18:N25) -> 3572796.2
A37: Contracted managed units | B37: units | C37: [C] | D37: =D36/INDEX(Assumptions!$D$32:$F$32,1,1) -> 7109.375 | E37: =E36/INDEX(Assumptions!$D$32:$F$32,1,1) -> 9775.3906 | F37: =F36/INDEX(Assumptions!$D$32:$F$32,1,1) -> 14307.617 | G37: =G36/INDEX(Assumptions!$D$32:$F$32,1,1) -> 22773.328 | H37: =H36/INDEX(Assumptions!$D$32:$F$32,1,1) -> 30786.524 | I37: =I36/INDEX(Assumptions!$D$32:$F$32,1,1) -> 32954.998 | J37: =J36/INDEX(Assumptions!$D$32:$F$32,1,1) -> 34879.518 | K37: =K36/INDEX(Assumptions!$D$32:$F$32,1,1) -> 36587.531 | ... N37: =N36/INDEX(Assumptions!$D$32:$F$32,1,1) -> 27912.471
A38: Gross organic-win EBITDA before the ceiling | B38: $ | C38: [A] | D38: =SUM(D27:D34) -> 0 | E38: =SUM(E27:E34) -> 0 | F38: =SUM(F27:F34) -> 80762.5 | G38: =SUM(G27:G34) -> 211092.98 | H38: =SUM(H27:H34) -> 384022.03 | I38: =SUM(I27:I34) -> 694350.48 | J38: =SUM(J27:J34) -> 1021942.5 | K38: =SUM(K27:K34) -> 1363616.7 | ... N38: =SUM(N27:N34) -> 2386297.2
A39: Gross organic-win units before the ceiling | B39: units | C39: [A] | D39: =D38/INDEX(Assumptions!$D$32:$F$32,1,1) -> 0 | E39: =E38/INDEX(Assumptions!$D$32:$F$32,1,1) -> 0 | F39: =F38/INDEX(Assumptions!$D$32:$F$32,1,1) -> 630.95703 | G39: =G38/INDEX(Assumptions!$D$32:$F$32,1,1) -> 1649.1639 | H39: =H38/INDEX(Assumptions!$D$32:$F$32,1,1) -> 3000.1721 | I39: =I38/INDEX(Assumptions!$D$32:$F$32,1,1) -> 5424.6131 | J39: =J38/INDEX(Assumptions!$D$32:$F$32,1,1) -> 7983.9257 | K39: =K38/INDEX(Assumptions!$D$32:$F$32,1,1) -> 10653.256 | ... N39: =N38/INDEX(Assumptions!$D$32:$F$32,1,1) -> 18642.947
A40: Managed units before the capacity ceiling | B40: units | C40: [C] | D40: =D37+D39 -> 7109.375 | E40: =E37+E39 -> 9775.3906 | F40: =F37+F39 -> 14938.574 | G40: =G37+G39 -> 24422.492 | H40: =H37+H39 -> 33786.696 | I40: =I37+I39 -> 38379.611 | J40: =J37+J39 -> 42863.444 | K40: =K37+K39 -> 47240.786 | ... N40: =N37+N39 -> 46555.418
A41: Organic capacity headroom | B41: units | C41: [D] | D41: =MAX(0,INDEX(Assumptions!$D$16:$F$16,1,1)-D37) -> 42890.625 | E41: =MAX(0,INDEX(Assumptions!$D$16:$F$16,1,1)-E37) -> 40224.609 | F41: =MAX(0,INDEX(Assumptions!$D$16:$F$16,1,1)-F37) -> 35692.383 | G41: =MAX(0,INDEX(Assumptions!$D$16:$F$16,1,1)-G37) -> 27226.672 | H41: =MAX(0,INDEX(Assumptions!$D$16:$F$16,1,1)-H37) -> 19213.476 | I41: =MAX(0,INDEX(Assumptions!$D$16:$F$16,1,1)-I37) -> 17045.002 | J41: =MAX(0,INDEX(Assumptions!$D$16:$F$16,1,1)-J37) -> 15120.482 | K41: =MAX(0,INDEX(Assumptions!$D$16:$F$16,1,1)-K37) -> 13412.469 | ... N41: =MAX(0,INDEX(Assumptions!$D$16:$F$16,1,1)-N37) -> 22087.529
A42: Capacity constrains new business only. Contracted acquired units are never dropped; if the acquired book alone exceeded the ceiling that would be a programme failure, and a control tests for it.
A43: Served organic-win units | B43: units | C43: [A] | D43: =MIN(D39,D41) -> 0 | E43: =MIN(E39,E41) -> 0 | F43: =MIN(F39,F41) -> 630.95703 | G43: =MIN(G39,G41) -> 1649.1639 | H43: =MIN(H39,H41) -> 3000.1721 | I43: =MIN(I39,I41) -> 5424.6131 | J43: =MIN(J39,J41) -> 7983.9257 | K43: =MIN(K39,K41) -> 10653.256 | ... N43: =MIN(N39,N41) -> 18642.947
A44: Deferred / unserved pipeline units | B44: units | C44: [D] | D44: =D39-D43 -> 0 | E44: =E39-E43 -> 0 | F44: =F39-F43 -> 0 | G44: =G39-G43 -> 0 | H44: =H39-H43 -> 0 | I44: =I39-I43 -> 0 | J44: =J39-J43 -> 0 | K44: =K39-K43 -> 0 | ... N44: =N39-N43 -> 0
A45: Organic capacity factor — applies to new business only | B45: x | C45: [D] | D45: =IF(D39<=0,1,D43/D39) -> 1 | E45: =IF(E39<=0,1,E43/E39) -> 1 | F45: =IF(F39<=0,1,F43/F39) -> 1 | G45: =IF(G39<=0,1,G43/G39) -> 1 | H45: =IF(H39<=0,1,H43/H39) -> 1 | I45: =IF(I39<=0,1,I43/I39) -> 1 | J45: =IF(J39<=0,1,J43/J39) -> 1 | K45: =IF(K39<=0,1,K43/K39) -> 1 | ... N45: =IF(N39<=0,1,N43/N39) -> 1
A46: BUYER-CREATED ORGANIC EBITDA | B46: $ | C46: [A] | D46: =D43*INDEX(Assumptions!$D$32:$F$32,1,1) -> 0 | E46: =E43*INDEX(Assumptions!$D$32:$F$32,1,1) -> 0 | F46: =F43*INDEX(Assumptions!$D$32:$F$32,1,1) -> 80762.5 | G46: =G43*INDEX(Assumptions!$D$32:$F$32,1,1) -> 211092.98 | H46: =H43*INDEX(Assumptions!$D$32:$F$32,1,1) -> 384022.03 | I46: =I43*INDEX(Assumptions!$D$32:$F$32,1,1) -> 694350.48 | J46: =J43*INDEX(Assumptions!$D$32:$F$32,1,1) -> 1021942.5 | K46: =K43*INDEX(Assumptions!$D$32:$F$32,1,1) -> 1363616.7 | ... N46: =N43*INDEX(Assumptions!$D$32:$F$32,1,1) -> 2386297.2
A47: Total retained EBITDA — contracted plus served organic | B47: $ | C47: [C] | D47: =D36+D46 -> 910000 | E47: =E36+E46 -> 1251250 | F47: =F36+F46 -> 1912137.5 | G47: =G36+G46 -> 3126078.9 | H47: =H36+H46 -> 4324697 | I47: =I36+I46 -> 4912590.2 | J47: =J36+J46 -> 5486520.9 | K47: =K36+K46 -> 6046820.7 | ... N47: =N36+N46 -> 5959093.4
A48: Contracted retention factor versus acquired | B48: % | C48: [C] | D48: =IF(('Acquisition Schedule'!F$20)=0,0,D36/('Acquisition Schedule'!F$20)) -> 0.91 | E48: =IF(('Acquisition Schedule'!F$20+'Acquisition Schedule'!G$20)=0,0,E36/('Acquisition Schedule'!F$20+'Acquisition Schedule'!G$20)) -> 0.715 | F48: =IF(('Acquisition Schedule'!F$20+'Acquisition Schedule'!G$20+'Acquisition Schedule'!H$20)=0,0,F36/('Acquisition Schedule'!F$20+'Acquisition Schedule'!G$20+'Acquisition Schedule'!H$20)) -> 0.73255 | G48: =IF(('Acquisition Schedule'!F$20+'Acquisition Schedule'!G$20+'Acquisition Schedule'!H$20+'Acquisition Schedule'!I$20)=0,0,G36/('Acquisition Schedule'!F$20+'Acquisition Schedule'!G$20+'Acquisition Schedule'!H$20+'Acquisition Schedule'!I$20)) -> 0.64777465 | H48: =IF(('Acquisition Schedule'!F$20+'Acquisition Schedule'!G$20+'Acquisition Schedule'!H$20+'Acquisition Schedule'!I$20+'Acquisition Schedule'!J$20)=0,0,H36/('Acquisition Schedule'!F$20+'Acquisition Schedule'!G$20+'Acquisition Schedule'!H$20+'Acquisition Schedule'!I$20+'Acquisition Schedule'!J$20)) -> 0.75060477 | I48: =IF(('Acquisition Schedule'!F$20+'Acquisition Schedule'!G$20+'Acquisition Schedule'!H$20+'Acquisition Schedule'!I$20+'Acquisition Schedule'!J$20+'Acquisition Schedule'!K$20)=0,0,I36/('Acquisition Schedule'!F$20+'Acquisition Schedule'!G$20+'Acquisition Schedule'!H$20+'Acquisition Schedule'!I$20+'Acquisition Schedule'!J$20+'Acquisition Schedule'!K$20)) -> 0.70303995 | J48: =IF(('Acquisition Schedule'!F$20+'Acquisition Schedule'!G$20+'Acquisition Schedule'!H$20+'Acquisition Schedule'!I$20+'Acquisition Schedule'!J$20+'Acquisition Schedule'!K$20+'Acquisition Schedule'!L$20)=0,0,J36/('Acquisition Schedule'!F$20+'Acquisition Schedule'!G$20+'Acquisition Schedule'!H$20+'Acquisition Schedule'!I$20+'Acquisition Schedule'!J$20+'Acquisition Schedule'!K$20+'Acquisition Schedule'!L$20)) -> 0.66141902 | K48: =IF(('Acquisition Schedule'!F$20+'Acquisition Schedule'!G$20+'Acquisition Schedule'!H$20+'Acquisition Schedule'!I$20+'Acquisition Schedule'!J$20+'Acquisition Schedule'!K$20+'Acquisition Schedule'!L$20+'Acquisition Schedule'!M$20)=0,0,K36/('Acquisition Schedule'!F$20+'Acquisition Schedule'!G$20+'Acquisition Schedule'!H$20+'Acquisition Schedule'!I$20+'Acquisition Schedule'!J$20+'Acquisition Schedule'!K$20+'Acquisition Schedule'!L$20+'Acquisition Schedule'!M$20)) -> 0.62442719 | L48: =IF(('Acquisition Schedule'!F$20+'Acquisition Schedule'!G$20+'Acquisition Schedule'!H$20+'Acquisition Schedule'!I$20+'Acquisition Schedule'!J$20+'Acquisition Schedule'!K$20+'Acquisition Schedule'!L$20+'Acquisition Schedule'!M$20+'Acquisition Schedule'!N$20)=0,0,L36/('Acquisition Schedule'!F$20+'Acquisition Schedule'!G$20+'Acquisition Schedule'!H$20+'Acquisition Schedule'!I$20+'Acquisition Schedule'!J$20+'Acquisition Schedule'!K$20+'Acquisition Schedule'!L$20+'Acquisition Schedule'!M$20+'Acquisition Schedule'!N$20)) -> 0.60479788 | M48: =IF(('Acquisition Schedule'!F$20+'Acquisition Schedule'!G$20+'Acquisition Schedule'!H$20+'Acquisition Schedule'!I$20+'Acquisition Schedule'!J$20+'Acquisition Schedule'!K$20+'Acquisition Schedule'!L$20+'Acquisition Schedule'!M$20+'Acquisition Schedule'!N$20+'Acquisition Schedule'!O$20)=0,0,M36/('Acquisition Schedule'!F$20+'Acquisition Schedule'!G$20+'Acquisition Schedule'!H$20+'Acquisition Schedule'!I$20+'Acquisition Schedule'!J$20+'Acquisition Schedule'!K$20+'Acquisition Schedule'!L$20+'Acquisition Schedule'!M$20+'Acquisition Schedule'!N$20+'Acquisition Schedule'!O$20)) -> 0.53675812 | N48: =IF(('Acquisition Schedule'!F$20+'Acquisition Schedule'!G$20+'Acquisition Schedule'!H$20+'Acquisition Schedule'!I$20+'Acquisition Schedule'!J$20+'Acquisition Schedule'!K$20+'Acquisition Schedule'!L$20+'Acquisition Schedule'!M$20+'Acquisition Schedule'!N$20+'Acquisition Schedule'!O$20+'Acquisition Schedule'!P$20)=0,0,N36/('Acquisition Schedule'!F$20+'Acquisition Schedule'!G$20+'Acquisition Schedule'!H$20+'Acquisition Schedule'!I$20+'Acquisition Schedule'!J$20+'Acquisition Schedule'!K$20+'Acquisition Schedule'!L$20+'Acquisition Schedule'!M$20+'Acquisition Schedule'!N$20+'Acquisition Schedule'!O$20+'Acquisition Schedule'!P$20)) -> 0.47637283
A49: MANAGED UNITS | B49: units | C49: [C] | D49: =D37+D43 -> 7109.375 | E49: =E37+E43 -> 9775.3906 | F49: =F37+F43 -> 14938.574 | G49: =G37+G43 -> 24422.492 | H49: =H37+H43 -> 33786.696 | I49: =I37+I43 -> 38379.611 | J49: =J37+J43 -> 42863.444 | K49: =K37+K43 -> 47240.786 | ... N49: =N37+N43 -> 46555.418
A50: Opening managed units | B50: units | C50: [C] | D50: =0 -> 0 | E50: =D49 -> 7109.375 | F50: =E49 -> 9775.3906 | G50: =F49 -> 14938.574 | H50: =G49 -> 24422.492 | I50: =H49 -> 33786.696 | J50: =I49 -> 38379.611 | K50: =J49 -> 42863.444 | L50: =K49 -> 47240.786 | ... N50: =M49 -> 47688.008
A51: Units acquired in the year | B51: units | C51: [C] | D51: ='Acquisition Schedule'!F$22*(1-INDEX(Assumptions!$D$56:$F$56,1,1)) -> 7109.375 | E51: ='Acquisition Schedule'!G$22*(1-INDEX(Assumptions!$D$56:$F$56,1,1))*INDEX(Assumptions!$D$20:$F$20,1,1) -> 2666.0156 | F51: ='Acquisition Schedule'!H$22*(1-INDEX(Assumptions!$D$56:$F$56,1,1))*INDEX(Assumptions!$D$20:$F$20,1,1) -> 2666.0156 | G51: ='Acquisition Schedule'!I$22*(1-INDEX(Assumptions!$D$56:$F$56,1,1))*INDEX(Assumptions!$D$20:$F$20,1,1) -> 7109.375 | H51: ='Acquisition Schedule'!J$22*(1-INDEX(Assumptions!$D$56:$F$56,1,1))*INDEX(Assumptions!$D$20:$F$20,1,1) -> 2666.0156 | I51: ='Acquisition Schedule'!K$22*(1-INDEX(Assumptions!$D$56:$F$56,1,1))*INDEX(Assumptions!$D$20:$F$20,1,1) -> 2666.0156 | J51: ='Acquisition Schedule'!L$22*(1-INDEX(Assumptions!$D$56:$F$56,1,1))*INDEX(Assumptions!$D$20:$F$20,1,1) -> 2666.0156 | K51: ='Acquisition Schedule'!M$22*(1-INDEX(Assumptions!$D$56:$F$56,1,1))*INDEX(Assumptions!$D$20:$F$20,1,1) -> 2666.0156 | L51: ='Acquisition Schedule'!N$22*(1-INDEX(Assumptions!$D$56:$F$56,1,1))*INDEX(Assumptions!$D$20:$F$20,1,1) -> 0 | ... N51: ='Acquisition Schedule'!P$22*(1-INDEX(Assumptions!$D$56:$F$56,1,1))*INDEX(Assumptions!$D$20:$F$20,1,1) -> 0
A52: Units lost to contract churn | B52: units | C52: [C] | D52: =-D50*$D$9 -> 0 | E52: =-E50*$D$9 -> -799.80469 | F52: =-F50*$D$9 -> -1099.7314 | G52: =-G50*$D$9 -> -1680.5896 | H52: =-H50*$D$9 -> -2747.5303 | I52: =-I50*$D$9 -> -3801.0033 | J52: =-J50*$D$9 -> -4317.7062 | K52: =-K50*$D$9 -> -4822.1375 | ... N52: =-N50*$D$9 -> -5364.9009
A53: Units won — target standalone capability | B53: units | C53: [C] | D53: =D50*$D$8*$D$10 -> 0 | E53: =E50*$D$8*$D$10 -> 504.76562 | F53: =F50*$D$8*$D$10 -> 694.05273 | G53: =G50*$D$8*$D$10 -> 1060.6388 | H53: =H50*$D$8*$D$10 -> 1733.9969 | I53: =I50*$D$8*$D$10 -> 2398.8554 | J53: =J50*$D$8*$D$10 -> 2724.9524 | K53: =K50*$D$8*$D$10 -> 3043.3045 | ... N53: =N50*$D$8*$D$10 -> 3385.8485
A54: Units won — platform uplift | B54: units | C54: [A] | D54: =D50*$D$8*$D$11 -> 0 | E54: =E50*$D$8*$D$11 -> 126.19141 | F54: =F50*$D$8*$D$11 -> 173.51318 | G54: =G50*$D$8*$D$11 -> 265.15969 | H54: =H50*$D$8*$D$11 -> 433.49923 | I54: =I50*$D$8*$D$11 -> 599.71385 | J54: =J50*$D$8*$D$11 -> 681.23809 | K54: =K50*$D$8*$D$11 -> 760.82613 | ... N54: =N50*$D$8*$D$11 -> 846.46214
A55: Mid-year close timing and capacity deferral | B55: units | C55: [C] | D55: =D49-(D50+D51+D52+D53+D54) -> 0 | E55: =E49-(E50+E51+E52+E53+E54) -> 168.84766 | F55: =F49-(F50+F51+F52+F53+F54) -> 2729.3335 | G55: =G49-(G50+G51+G52+G53+G54) -> 2729.3335 | H55: =H49-(H50+H51+H52+H53+H54) -> 7278.2227 | I55: =I49-(I50+I51+I52+I53+I54) -> 2729.3335 | J55: =J49-(J50+J51+J52+J53+J54) -> 2729.3335 | K55: =K49-(K50+K51+K52+K53+K54) -> 2729.3335 | ... N55: =N49-(N50+N51+N52+N53+N54) -> 0
A56: Net change in managed units | B56: units | C56: [C] | D56: =D49-D50 -> 7109.375 | E56: =E49-E50 -> 2666.0156 | F56: =F49-F50 -> 5163.1836 | G56: =G49-G50 -> 9483.9174 | H56: =H49-H50 -> 9364.2041 | I56: =I49-I50 -> 4592.9151 | J56: =J49-J50 -> 4483.8334 | K56: =K49-K50 -> 4377.3423 | ... N56: =N49-N50 -> -1132.5902
A57: Gross movement disclosure. Opening plus acquired, less churn, plus standalone wins, plus platform uplift. The final line is the residual between that simple roll and the vintage engine: acquisitions close mid-year and each vintage compounds from its own close date, and capacity deferral sits here once the ceiling binds. The retained line above is the live calculation.
A58: Retained properties | B58: properties | C58: [C] | D58: =D49/INDEX(Assumptions!$D$17:$F$17,1,1) -> 28.4375 | E58: =E49/INDEX(Assumptions!$D$17:$F$17,1,1) -> 39.101562 | F58: =F49/INDEX(Assumptions!$D$17:$F$17,1,1) -> 59.754297 | G58: =G49/INDEX(Assumptions!$D$17:$F$17,1,1) -> 97.689966 | H58: =H49/INDEX(Assumptions!$D$17:$F$17,1,1) -> 135.14678 | I58: =I49/INDEX(Assumptions!$D$17:$F$17,1,1) -> 153.51844 | J58: =J49/INDEX(Assumptions!$D$17:$F$17,1,1) -> 171.45378 | K58: =K49/INDEX(Assumptions!$D$17:$F$17,1,1) -> 188.96315 | ... N58: =N49/INDEX(Assumptions!$D$17:$F$17,1,1) -> 186.22167
A59: Arithmetic from managed units and units per property, never an independent roll-forward.
A60: Managed units per client, acquired mix | B60: units | C60: [C] | D60: =IF(('Acquisition Schedule'!F$24)=0,0,('Acquisition Schedule'!F$22)/('Acquisition Schedule'!F$24)) -> 1302.0833 | E60: =IF(('Acquisition Schedule'!F$24+'Acquisition Schedule'!G$24)=0,0,('Acquisition Schedule'!F$22+'Acquisition Schedule'!G$22)/('Acquisition Schedule'!F$24+'Acquisition Schedule'!G$24)) -> 1454.4548 | F60: =IF(('Acquisition Schedule'!F$24+'Acquisition Schedule'!G$24+'Acquisition Schedule'!H$24)=0,0,('Acquisition Schedule'!F$22+'Acquisition Schedule'!G$22+'Acquisition Schedule'!H$22)/('Acquisition Schedule'!F$24+'Acquisition Schedule'!G$24+'Acquisition Schedule'!H$24)) -> 1525.8789 | G60: =IF(('Acquisition Schedule'!F$24+'Acquisition Schedule'!G$24+'Acquisition Schedule'!H$24+'Acquisition Schedule'!I$24)=0,0,('Acquisition Schedule'!F$22+'Acquisition Schedule'!G$22+'Acquisition Schedule'!H$22+'Acquisition Schedule'!I$22)/('Acquisition Schedule'!F$24+'Acquisition Schedule'!G$24+'Acquisition Schedule'!H$24+'Acquisition Schedule'!I$24)) -> 1793.6862 | H60: =IF(('Acquisition Schedule'!F$24+'Acquisition Schedule'!G$24+'Acquisition Schedule'!H$24+'Acquisition Schedule'!I$24+'Acquisition Schedule'!J$24)=0,0,('Acquisition Schedule'!F$22+'Acquisition Schedule'!G$22+'Acquisition Schedule'!H$22+'Acquisition Schedule'!I$22+'Acquisition Schedule'!J$22)/('Acquisition Schedule'!F$24+'Acquisition Schedule'!G$24+'Acquisition Schedule'!H$24+'Acquisition Schedule'!I$24+'Acquisition Schedule'!J$24)) -> 1783.288 | I60: =IF(('Acquisition Schedule'!F$24+'Acquisition Schedule'!G$24+'Acquisition Schedule'!H$24+'Acquisition Schedule'!I$24+'Acquisition Schedule'!J$24+'Acquisition Schedule'!K$24)=0,0,('Acquisition Schedule'!F$22+'Acquisition Schedule'!G$22+'Acquisition Schedule'!H$22+'Acquisition Schedule'!I$22+'Acquisition Schedule'!J$22+'Acquisition Schedule'!K$22)/('Acquisition Schedule'!F$24+'Acquisition Schedule'!G$24+'Acquisition Schedule'!H$24+'Acquisition Schedule'!I$24+'Acquisition Schedule'!J$24+'Acquisition Schedule'!K$24)) -> 1775.5682 | J60: =IF(('Acquisition Schedule'!F$24+'Acquisition Schedule'!G$24+'Acquisition Schedule'!H$24+'Acquisition Schedule'!I$24+'Acquisition Schedule'!J$24+'Acquisition Schedule'!K$24+'Acquisition Schedule'!L$24)=0,0,('Acquisition Schedule'!F$22+'Acquisition Schedule'!G$22+'Acquisition Schedule'!H$22+'Acquisition Schedule'!I$22+'Acquisition Schedule'!J$22+'Acquisition Schedule'!K$22+'Acquisition Schedule'!L$22)/('Acquisition Schedule'!F$24+'Acquisition Schedule'!G$24+'Acquisition Schedule'!H$24+'Acquisition Schedule'!I$24+'Acquisition Schedule'!J$24+'Acquisition Schedule'!K$24+'Acquisition Schedule'!L$24)) -> 1769.6099 | K60: =IF(('Acquisition Schedule'!F$24+'Acquisition Schedule'!G$24+'Acquisition Schedule'!H$24+'Acquisition Schedule'!I$24+'Acquisition Schedule'!J$24+'Acquisition Schedule'!K$24+'Acquisition Schedule'!L$24+'Acquisition Schedule'!M$24)=0,0,('Acquisition Schedule'!F$22+'Acquisition Schedule'!G$22+'Acquisition Schedule'!H$22+'Acquisition Schedule'!I$22+'Acquisition Schedule'!J$22+'Acquisition Schedule'!K$22+'Acquisition Schedule'!L$22+'Acquisition Schedule'!M$22)/('Acquisition Schedule'!F$24+'Acquisition Schedule'!G$24+'Acquisition Schedule'!H$24+'Acquisition Schedule'!I$24+'Acquisition Schedule'!J$24+'Acquisition Schedule'!K$24+'Acquisition Schedule'!L$24+'Acquisition Schedule'!M$24)) -> 1764.872 | L60: =IF(('Acquisition Schedule'!F$24+'Acquisition Schedule'!G$24+'Acquisition Schedule'!H$24+'Acquisition Schedule'!I$24+'Acquisition Schedule'!J$24+'Acquisition Schedule'!K$24+'Acquisition Schedule'!L$24+'Acquisition Schedule'!M$24+'Acquisition Schedule'!N$24)=0,0,('Acquisition Schedule'!F$22+'Acquisition Schedule'!G$22+'Acquisition Schedule'!H$22+'Acquisition Schedule'!I$22+'Acquisition Schedule'!J$22+'Acquisition Schedule'!K$22+'Acquisition Schedule'!L$22+'Acquisition Schedule'!M$22+'Acquisition Schedule'!N$22)/('Acquisition Schedule'!F$24+'Acquisition Schedule'!G$24+'Acquisition Schedule'!H$24+'Acquisition Schedule'!I$24+'Acquisition Schedule'!J$24+'Acquisition Schedule'!K$24+'Acquisition Schedule'!L$24+'Acquisition Schedule'!M$24+'Acquisition Schedule'!N$24)) -> 1764.872 | M60: =IF(('Acquisition Schedule'!F$24+'Acquisition Schedule'!G$24+'Acquisition Schedule'!H$24+'Acquisition Schedule'!I$24+'Acquisition Schedule'!J$24+'Acquisition Schedule'!K$24+'Acquisition Schedule'!L$24+'Acquisition Schedule'!M$24+'Acquisition Schedule'!N$24+'Acquisition Schedule'!O$24)=0,0,('Acquisition Schedule'!F$22+'Acquisition Schedule'!G$22+'Acquisition Schedule'!H$22+'Acquisition Schedule'!I$22+'Acquisition Schedule'!J$22+'Acquisition Schedule'!K$22+'Acquisition Schedule'!L$22+'Acquisition Schedule'!M$22+'Acquisition Schedule'!N$22+'Acquisition Schedule'!O$22)/('Acquisition Schedule'!F$24+'Acquisition Schedule'!G$24+'Acquisition Schedule'!H$24+'Acquisition Schedule'!I$24+'Acquisition Schedule'!J$24+'Acquisition Schedule'!K$24+'Acquisition Schedule'!L$24+'Acquisition Schedule'!M$24+'Acquisition Schedule'!N$24+'Acquisition Schedule'!O$24)) -> 1764.872 | N60: =IF(('Acquisition Schedule'!F$24+'Acquisition Schedule'!G$24+'Acquisition Schedule'!H$24+'Acquisition Schedule'!I$24+'Acquisition Schedule'!J$24+'Acquisition Schedule'!K$24+'Acquisition Schedule'!L$24+'Acquisition Schedule'!M$24+'Acquisition Schedule'!N$24+'Acquisition Schedule'!O$24+'Acquisition Schedule'!P$24)=0,0,('Acquisition Schedule'!F$22+'Acquisition Schedule'!G$22+'Acquisition Schedule'!H$22+'Acquisition Schedule'!I$22+'Acquisition Schedule'!J$22+'Acquisition Schedule'!K$22+'Acquisition Schedule'!L$22+'Acquisition Schedule'!M$22+'Acquisition Schedule'!N$22+'Acquisition Schedule'!O$22+'Acquisition Schedule'!P$22)/('Acquisition Schedule'!F$24+'Acquisition Schedule'!G$24+'Acquisition Schedule'!H$24+'Acquisition Schedule'!I$24+'Acquisition Schedule'!J$24+'Acquisition Schedule'!K$24+'Acquisition Schedule'!L$24+'Acquisition Schedule'!M$24+'Acquisition Schedule'!N$24+'Acquisition Schedule'!O$24+'Acquisition Schedule'!P$24)) -> 1764.872
A61: Retained clients | B61: clients | C61: [C] | D61: =IF(D60=0,0,D49/D60) -> 5.46 | E61: =IF(E60=0,0,E49/E60) -> 6.721 | F61: =IF(F60=0,0,F49/F60) -> 9.790144 | G61: =IF(G60=0,0,G49/G60) -> 13.61581 | H61: =IF(H60=0,0,H49/H60) -> 18.946292 | I61: =IF(I60=0,0,I49/I60) -> 21.615397 | J61: =IF(J60=0,0,J49/J60) -> 24.221974 | K61: =IF(K60=0,0,K49/K60) -> 26.767259 | ... N61: =IF(N60=0,0,N49/N60) -> 26.37892
A62: Managed units divided by the acquired units-per-client density, so clients track the served book. Never the product of a contracted retention factor and an organic capacity factor, which have no joint meaning.
A63: Retained regimes | B63: regimes | C63: [E] | D63: =IF(('Acquisition Schedule'!F$24)=0,0,D61*('Acquisition Schedule'!F$25)/('Acquisition Schedule'!F$24)) -> 1.365 | E63: =IF(('Acquisition Schedule'!F$24+'Acquisition Schedule'!G$24)=0,0,E61*('Acquisition Schedule'!F$25+'Acquisition Schedule'!G$25)/('Acquisition Schedule'!F$24+'Acquisition Schedule'!G$24)) -> 1.68025 | F63: =IF(('Acquisition Schedule'!F$24+'Acquisition Schedule'!G$24+'Acquisition Schedule'!H$24)=0,0,F61*('Acquisition Schedule'!F$25+'Acquisition Schedule'!G$25+'Acquisition Schedule'!H$25)/('Acquisition Schedule'!F$24+'Acquisition Schedule'!G$24+'Acquisition Schedule'!H$24)) -> 2.447536 | G63: =IF(('Acquisition Schedule'!F$24+'Acquisition Schedule'!G$24+'Acquisition Schedule'!H$24+'Acquisition Schedule'!I$24)=0,0,G61*('Acquisition Schedule'!F$25+'Acquisition Schedule'!G$25+'Acquisition Schedule'!H$25+'Acquisition Schedule'!I$25)/('Acquisition Schedule'!F$24+'Acquisition Schedule'!G$24+'Acquisition Schedule'!H$24+'Acquisition Schedule'!I$24)) -> 3.4039526 | H63: =IF(('Acquisition Schedule'!F$24+'Acquisition Schedule'!G$24+'Acquisition Schedule'!H$24+'Acquisition Schedule'!I$24+'Acquisition Schedule'!J$24)=0,0,H61*('Acquisition Schedule'!F$25+'Acquisition Schedule'!G$25+'Acquisition Schedule'!H$25+'Acquisition Schedule'!I$25+'Acquisition Schedule'!J$25)/('Acquisition Schedule'!F$24+'Acquisition Schedule'!G$24+'Acquisition Schedule'!H$24+'Acquisition Schedule'!I$24+'Acquisition Schedule'!J$24)) -> 4.736573 | I63: =IF(('Acquisition Schedule'!F$24+'Acquisition Schedule'!G$24+'Acquisition Schedule'!H$24+'Acquisition Schedule'!I$24+'Acquisition Schedule'!J$24+'Acquisition Schedule'!K$24)=0,0,I61*('Acquisition Schedule'!F$25+'Acquisition Schedule'!G$25+'Acquisition Schedule'!H$25+'Acquisition Schedule'!I$25+'Acquisition Schedule'!J$25+'Acquisition Schedule'!K$25)/('Acquisition Schedule'!F$24+'Acquisition Schedule'!G$24+'Acquisition Schedule'!H$24+'Acquisition Schedule'!I$24+'Acquisition Schedule'!J$24+'Acquisition Schedule'!K$24)) -> 5.4038492 | J63: =IF(('Acquisition Schedule'!F$24+'Acquisition Schedule'!G$24+'Acquisition Schedule'!H$24+'Acquisition Schedule'!I$24+'Acquisition Schedule'!J$24+'Acquisition Schedule'!K$24+'Acquisition Schedule'!L$24)=0,0,J61*('Acquisition Schedule'!F$25+'Acquisition Schedule'!G$25+'Acquisition Schedule'!H$25+'Acquisition Schedule'!I$25+'Acquisition Schedule'!J$25+'Acquisition Schedule'!K$25+'Acquisition Schedule'!L$25)/('Acquisition Schedule'!F$24+'Acquisition Schedule'!G$24+'Acquisition Schedule'!H$24+'Acquisition Schedule'!I$24+'Acquisition Schedule'!J$24+'Acquisition Schedule'!K$24+'Acquisition Schedule'!L$24)) -> 6.0554934 | K63: =IF(('Acquisition Schedule'!F$24+'Acquisition Schedule'!G$24+'Acquisition Schedule'!H$24+'Acquisition Schedule'!I$24+'Acquisition Schedule'!J$24+'Acquisition Schedule'!K$24+'Acquisition Schedule'!L$24+'Acquisition Schedule'!M$24)=0,0,K61*('Acquisition Schedule'!F$25+'Acquisition Schedule'!G$25+'Acquisition Schedule'!H$25+'Acquisition Schedule'!I$25+'Acquisition Schedule'!J$25+'Acquisition Schedule'!K$25+'Acquisition Schedule'!L$25+'Acquisition Schedule'!M$25)/('Acquisition Schedule'!F$24+'Acquisition Schedule'!G$24+'Acquisition Schedule'!H$24+'Acquisition Schedule'!I$24+'Acquisition Schedule'!J$24+'Acquisition Schedule'!K$24+'Acquisition Schedule'!L$24+'Acquisition Schedule'!M$24)) -> 6.6918149 | L63: =IF(('Acquisition Schedule'!F$24+'Acquisition Schedule'!G$24+'Acquisition Schedule'!H$24+'Acquisition Schedule'!I$24+'Acquisition Schedule'!J$24+'Acquisition Schedule'!K$24+'Acquisition Schedule'!L$24+'Acquisition Schedule'!M$24+'Acquisition Schedule'!N$24)=0,0,L61*('Acquisition Schedule'!F$25+'Acquisition Schedule'!G$25+'Acquisition Schedule'!H$25+'Acquisition Schedule'!I$25+'Acquisition Schedule'!J$25+'Acquisition Schedule'!K$25+'Acquisition Schedule'!L$25+'Acquisition Schedule'!M$25+'Acquisition Schedule'!N$25)/('Acquisition Schedule'!F$24+'Acquisition Schedule'!G$24+'Acquisition Schedule'!H$24+'Acquisition Schedule'!I$24+'Acquisition Schedule'!J$24+'Acquisition Schedule'!K$24+'Acquisition Schedule'!L$24+'Acquisition Schedule'!M$24+'Acquisition Schedule'!N$24)) -> 6.9195035 | M63: =IF(('Acquisition Schedule'!F$24+'Acquisition Schedule'!G$24+'Acquisition Schedule'!H$24+'Acquisition Schedule'!I$24+'Acquisition Schedule'!J$24+'Acquisition Schedule'!K$24+'Acquisition Schedule'!L$24+'Acquisition Schedule'!M$24+'Acquisition Schedule'!N$24+'Acquisition Schedule'!O$24)=0,0,M61*('Acquisition Schedule'!F$25+'Acquisition Schedule'!G$25+'Acquisition Schedule'!H$25+'Acquisition Schedule'!I$25+'Acquisition Schedule'!J$25+'Acquisition Schedule'!K$25+'Acquisition Schedule'!L$25+'Acquisition Schedule'!M$25+'Acquisition Schedule'!N$25+'Acquisition Schedule'!O$25)/('Acquisition Schedule'!F$24+'Acquisition Schedule'!G$24+'Acquisition Schedule'!H$24+'Acquisition Schedule'!I$24+'Acquisition Schedule'!J$24+'Acquisition Schedule'!K$24+'Acquisition Schedule'!L$24+'Acquisition Schedule'!M$24+'Acquisition Schedule'!N$24+'Acquisition Schedule'!O$24)) -> 6.7551652 | N63: =IF(('Acquisition Schedule'!F$24+'Acquisition Schedule'!G$24+'Acquisition Schedule'!H$24+'Acquisition Schedule'!I$24+'Acquisition Schedule'!J$24+'Acquisition Schedule'!K$24+'Acquisition Schedule'!L$24+'Acquisition Schedule'!M$24+'Acquisition Schedule'!N$24+'Acquisition Schedule'!O$24+'Acquisition Schedule'!P$24)=0,0,N61*('Acquisition Schedule'!F$25+'Acquisition Schedule'!G$25+'Acquisition Schedule'!H$25+'Acquisition Schedule'!I$25+'Acquisition Schedule'!J$25+'Acquisition Schedule'!K$25+'Acquisition Schedule'!L$25+'Acquisition Schedule'!M$25+'Acquisition Schedule'!N$25+'Acquisition Schedule'!O$25+'Acquisition Schedule'!P$25)/('Acquisition Schedule'!F$24+'Acquisition Schedule'!G$24+'Acquisition Schedule'!H$24+'Acquisition Schedule'!I$24+'Acquisition Schedule'!J$24+'Acquisition Schedule'!K$24+'Acquisition Schedule'!L$24+'Acquisition Schedule'!M$24+'Acquisition Schedule'!N$24+'Acquisition Schedule'!O$24+'Acquisition Schedule'!P$24)) -> 6.5947301
A64: Equivalent regimes above baseline | B64: regimes | C64: [E] | D64: =MAX(0,D63*INDEX(Assumptions!$D$47:$F$47,1,1)-INDEX(Assumptions!$D$45:$F$45,1,1)) -> 0.7745 | E64: =MAX(0,E63*INDEX(Assumptions!$D$47:$F$47,1,1)-INDEX(Assumptions!$D$45:$F$45,1,1)) -> 1.184325 | F64: =MAX(0,F63*INDEX(Assumptions!$D$47:$F$47,1,1)-INDEX(Assumptions!$D$45:$F$45,1,1)) -> 2.1817968 | G64: =MAX(0,G63*INDEX(Assumptions!$D$47:$F$47,1,1)-INDEX(Assumptions!$D$45:$F$45,1,1)) -> 3.4251384 | H64: =MAX(0,H63*INDEX(Assumptions!$D$47:$F$47,1,1)-INDEX(Assumptions!$D$45:$F$45,1,1)) -> 5.1575448 | I64: =MAX(0,I63*INDEX(Assumptions!$D$47:$F$47,1,1)-INDEX(Assumptions!$D$45:$F$45,1,1)) -> 6.025004 | J64: =MAX(0,J63*INDEX(Assumptions!$D$47:$F$47,1,1)-INDEX(Assumptions!$D$45:$F$45,1,1)) -> 6.8721414 | K64: =MAX(0,K63*INDEX(Assumptions!$D$47:$F$47,1,1)-INDEX(Assumptions!$D$45:$F$45,1,1)) -> 7.6993593 | ... N64: =MAX(0,N63*INDEX(Assumptions!$D$47:$F$47,1,1)-INDEX(Assumptions!$D$45:$F$45,1,1)) -> 7.5731491
A65: Retained recurring revenue — excludes episodic | B65: $ | C65: [C] | D65: =D49*(INDEX(Assumptions!$D$27:$F$27,1,1)+INDEX(Assumptions!$D$28:$F$28,1,1)+INDEX(Assumptions!$D$29:$F$29,1,1)+INDEX(Assumptions!$D$79:$F$79,1,1)) -> 4645855.3 | E65: =E49*(INDEX(Assumptions!$D$27:$F$27,1,1)+INDEX(Assumptions!$D$28:$F$28,1,1)+INDEX(Assumptions!$D$29:$F$29,1,1)+INDEX(Assumptions!$D$79:$F$79,1,1)) -> 6388051 | F65: =F49*(INDEX(Assumptions!$D$27:$F$27,1,1)+INDEX(Assumptions!$D$28:$F$28,1,1)+INDEX(Assumptions!$D$29:$F$29,1,1)+INDEX(Assumptions!$D$79:$F$79,1,1)) -> 9762103.5 | G65: =G49*(INDEX(Assumptions!$D$27:$F$27,1,1)+INDEX(Assumptions!$D$28:$F$28,1,1)+INDEX(Assumptions!$D$29:$F$29,1,1)+INDEX(Assumptions!$D$79:$F$79,1,1)) -> 15959682 | H65: =H49*(INDEX(Assumptions!$D$27:$F$27,1,1)+INDEX(Assumptions!$D$28:$F$28,1,1)+INDEX(Assumptions!$D$29:$F$29,1,1)+INDEX(Assumptions!$D$79:$F$79,1,1)) -> 22079029 | I65: =I49*(INDEX(Assumptions!$D$27:$F$27,1,1)+INDEX(Assumptions!$D$28:$F$28,1,1)+INDEX(Assumptions!$D$29:$F$29,1,1)+INDEX(Assumptions!$D$79:$F$79,1,1)) -> 25080421 | J65: =J49*(INDEX(Assumptions!$D$27:$F$27,1,1)+INDEX(Assumptions!$D$28:$F$28,1,1)+INDEX(Assumptions!$D$29:$F$29,1,1)+INDEX(Assumptions!$D$79:$F$79,1,1)) -> 28010530 | K65: =K49*(INDEX(Assumptions!$D$27:$F$27,1,1)+INDEX(Assumptions!$D$28:$F$28,1,1)+INDEX(Assumptions!$D$29:$F$29,1,1)+INDEX(Assumptions!$D$79:$F$79,1,1)) -> 30871048 | ... N65: =N49*(INDEX(Assumptions!$D$27:$F$27,1,1)+INDEX(Assumptions!$D$28:$F$28,1,1)+INDEX(Assumptions!$D$29:$F$29,1,1)+INDEX(Assumptions!$D$79:$F$79,1,1)) -> 30423171
A66: of which third-party pass-through | B66: $ | C66: [C] | D66: =D49*INDEX(Assumptions!$D$29:$F$29,1,1) -> 387002.08 | E66: =E49*INDEX(Assumptions!$D$29:$F$29,1,1) -> 532127.86 | F66: =F49*INDEX(Assumptions!$D$29:$F$29,1,1) -> 813188.12 | G66: =G49*INDEX(Assumptions!$D$29:$F$29,1,1) -> 1329449.5 | H66: =H49*INDEX(Assumptions!$D$29:$F$29,1,1) -> 1839194.2 | I66: =I49*INDEX(Assumptions!$D$29:$F$29,1,1) -> 2089211.7 | J66: =J49*INDEX(Assumptions!$D$29:$F$29,1,1) -> 2333291.2 | K66: =K49*INDEX(Assumptions!$D$29:$F$29,1,1) -> 2571573.8 | ... N66: =N49*INDEX(Assumptions!$D$29:$F$29,1,1) -> 2534265.4
A67: Realised EBITDA margin on recurring revenue | B67: % | C67: [C] | D67: =IF(D65=0,0,D36/D65) -> 0.19587351 | E67: =IF(E65=0,0,E36/E65) -> 0.19587351 | F67: =IF(F65=0,0,F36/F65) -> 0.18760045 | G67: =IF(G65=0,0,G36/G65) -> 0.18264687 | H67: =IF(H65=0,0,H36/H65) -> 0.17848045 | I67: =IF(I65=0,0,I36/I65) -> 0.16818855 | J67: =IF(J65=0,0,J36/J65) -> 0.15938929 | K67: =IF(K65=0,0,K36/K65) -> 0.15170213 | ... N67: =IF(N65=0,0,N36/N65) -> 0.11743668
A68: Run-rate retained EBITDA at year end | B68: $ | C68: [C] | D68: =0 -> 0 | E68: =E36+E46+'Acquisition Schedule'!G$20*(1-INDEX(Assumptions!$D$56:$F$56,1,1))*(1-INDEX(Assumptions!$D$20:$F$20,1,1)) -> 1592500 | F68: =F36+F46+'Acquisition Schedule'!H$20*(1-INDEX(Assumptions!$D$56:$F$56,1,1))*(1-INDEX(Assumptions!$D$20:$F$20,1,1)) -> 2253387.5 | G68: =G36+G46+'Acquisition Schedule'!I$20*(1-INDEX(Assumptions!$D$56:$F$56,1,1))*(1-INDEX(Assumptions!$D$20:$F$20,1,1)) -> 4036078.9 | H68: =H36+H46+'Acquisition Schedule'!J$20*(1-INDEX(Assumptions!$D$56:$F$56,1,1))*(1-INDEX(Assumptions!$D$20:$F$20,1,1)) -> 4665947 | I68: =I36+I46+'Acquisition Schedule'!K$20*(1-INDEX(Assumptions!$D$56:$F$56,1,1))*(1-INDEX(Assumptions!$D$20:$F$20,1,1)) -> 5253840.2 | J68: =J36+J46+'Acquisition Schedule'!L$20*(1-INDEX(Assumptions!$D$56:$F$56,1,1))*(1-INDEX(Assumptions!$D$20:$F$20,1,1)) -> 5827770.9 | K68: =K36+K46+'Acquisition Schedule'!M$20*(1-INDEX(Assumptions!$D$56:$F$56,1,1))*(1-INDEX(Assumptions!$D$20:$F$20,1,1)) -> 6388070.7 | L68: =L36+L46+'Acquisition Schedule'!N$20*(1-INDEX(Assumptions!$D$56:$F$56,1,1))*(1-INDEX(Assumptions!$D$20:$F$20,1,1)) -> 6252563.4 | ... N68: =N36+N46+'Acquisition Schedule'!P$20*(1-INDEX(Assumptions!$D$56:$F$56,1,1))*(1-INDEX(Assumptions!$D$20:$F$20,1,1)) -> 5959093.4
A70: BASE
A71: Blended annual contract retention | B71: % | C71: [C] | D71: ='Anchor QoE'!F$12 -> 0.911
A72: Gross annual contract churn | B72: % | C72: [C] | D72: =1-D71 -> 0.089
A73: Gross new-business wins — target standalone capability | B73: % | C73: [C] | D73: =INDEX(Assumptions!$D$57:$F$57,1,2) -> 0.1
A74: Gross new-business wins — platform uplift | B74: % | C74: [A] | D74: =(INDEX(Assumptions!$D$58:$F$58,1,2)*(1-Assumptions!$D$8)) -> 0.04
A75: Net annual factor — standalone counterfactual | B75: x | C75: [C] | D75: =D71*(1+D73) -> 1.0021
A76: NET ANNUAL FACTOR INSIDE THE PLATFORM | B76: x | C76: [C] | D76: =D71*(1+D73+D74) -> 1.03854
A77: Platform growth advantage over standalone | B77: pts | C77: [A] | D77: =D76-D75 -> 0.03644
A78: Ownership must not make an acquired business grow more slowly than it would have alone. The advantage line is the platform contribution, and it can never be negative by construction because the uplift is additive.
A79: Close-year part-period factor | B79: % | C79: [C] | D79: =(1-INDEX(Assumptions!$D$56:$F$56,1,2))*INDEX(Assumptions!$D$20:$F$20,1,2) -> 0.47
A80: Not a retention rate. A deal closing mid-year contributes only part of a full year of EBITDA in its close year, and the book that survives change of control is smaller. Half a year of ownership at 94 percent surviving change of control gives 47 percent of a full year. The anchor is grossed back to a full year because it is owned from day one.
A81: Contracted vintage — anchor at close | B81: $ | C81: [C] | D81: ='Acquisition Schedule'!F$20*$D$79/INDEX(Assumptions!$D$20:$F$20,1,2) -> 940000 | E81: ='Acquisition Schedule'!F$20*(1-INDEX(Assumptions!$D$56:$F$56,1,2))*$D$71^0 -> 940000 | F81: ='Acquisition Schedule'!F$20*(1-INDEX(Assumptions!$D$56:$F$56,1,2))*$D$71^1 -> 856340 | G81: ='Acquisition Schedule'!F$20*(1-INDEX(Assumptions!$D$56:$F$56,1,2))*$D$71^2 -> 780125.74 | H81: ='Acquisition Schedule'!F$20*(1-INDEX(Assumptions!$D$56:$F$56,1,2))*$D$71^3 -> 710694.55 | I81: ='Acquisition Schedule'!F$20*(1-INDEX(Assumptions!$D$56:$F$56,1,2))*$D$71^4 -> 647442.73 | J81: ='Acquisition Schedule'!F$20*(1-INDEX(Assumptions!$D$56:$F$56,1,2))*$D$71^5 -> 589820.33 | K81: ='Acquisition Schedule'!F$20*(1-INDEX(Assumptions!$D$56:$F$56,1,2))*$D$71^6 -> 537326.32 | L81: ='Acquisition Schedule'!F$20*(1-INDEX(Assumptions!$D$56:$F$56,1,2))*$D$71^7 -> 489504.28 | M81: ='Acquisition Schedule'!F$20*(1-INDEX(Assumptions!$D$56:$F$56,1,2))*$D$71^8 -> 445938.4 | N81: ='Acquisition Schedule'!F$20*(1-INDEX(Assumptions!$D$56:$F$56,1,2))*$D$71^9 -> 406249.88
A82: Contracted vintage Year 1 | B82: $ | C82: [C] | D82: =0 -> 0 | E82: ='Acquisition Schedule'!G$20*$D$79 -> 352500 | F82: ='Acquisition Schedule'!G$20*(1-INDEX(Assumptions!$D$56:$F$56,1,2))*$D$71^0 -> 705000 | G82: ='Acquisition Schedule'!G$20*(1-INDEX(Assumptions!$D$56:$F$56,1,2))*$D$71^1 -> 642255 | H82: ='Acquisition Schedule'!G$20*(1-INDEX(Assumptions!$D$56:$F$56,1,2))*$D$71^2 -> 585094.31 | I82: ='Acquisition Schedule'!G$20*(1-INDEX(Assumptions!$D$56:$F$56,1,2))*$D$71^3 -> 533020.91 | J82: ='Acquisition Schedule'!G$20*(1-INDEX(Assumptions!$D$56:$F$56,1,2))*$D$71^4 -> 485582.05 | K82: ='Acquisition Schedule'!G$20*(1-INDEX(Assumptions!$D$56:$F$56,1,2))*$D$71^5 -> 442365.25 | L82: ='Acquisition Schedule'!G$20*(1-INDEX(Assumptions!$D$56:$F$56,1,2))*$D$71^6 -> 402994.74 | M82: ='Acquisition Schedule'!G$20*(1-INDEX(Assumptions!$D$56:$F$56,1,2))*$D$71^7 -> 367128.21 | N82: ='Acquisition Schedule'!G$20*(1-INDEX(Assumptions!$D$56:$F$56,1,2))*$D$71^8 -> 334453.8
A83: Contracted vintage Year 2 | B83: $ | C83: [C] | D83: =0 -> 0 | E83: =0 -> 0 | F83: ='Acquisition Schedule'!H$20*$D$79 -> 352500 | G83: ='Acquisition Schedule'!H$20*(1-INDEX(Assumptions!$D$56:$F$56,1,2))*$D$71^0 -> 705000 | H83: ='Acquisition Schedule'!H$20*(1-INDEX(Assumptions!$D$56:$F$56,1,2))*$D$71^1 -> 642255 | I83: ='Acquisition Schedule'!H$20*(1-INDEX(Assumptions!$D$56:$F$56,1,2))*$D$71^2 -> 585094.31 | J83: ='Acquisition Schedule'!H$20*(1-INDEX(Assumptions!$D$56:$F$56,1,2))*$D$71^3 -> 533020.91 | K83: ='Acquisition Schedule'!H$20*(1-INDEX(Assumptions!$D$56:$F$56,1,2))*$D$71^4 -> 485582.05 | L83: ='Acquisition Schedule'!H$20*(1-INDEX(Assumptions!$D$56:$F$56,1,2))*$D$71^5 -> 442365.25 | M83: ='Acquisition Schedule'!H$20*(1-INDEX(Assumptions!$D$56:$F$56,1,2))*$D$71^6 -> 402994.74 | N83: ='Acquisition Schedule'!H$20*(1-INDEX(Assumptions!$D$56:$F$56,1,2))*$D$71^7 -> 367128.21
A84: Contracted vintage Year 3 | B84: $ | C84: [C] | D84: =0 -> 0 | E84: =0 -> 0 | F84: =0 -> 0 | G84: ='Acquisition Schedule'!I$20*$D$79 -> 940000 | H84: ='Acquisition Schedule'!I$20*(1-INDEX(Assumptions!$D$56:$F$56,1,2))*$D$71^0 -> 1880000 | I84: ='Acquisition Schedule'!I$20*(1-INDEX(Assumptions!$D$56:$F$56,1,2))*$D$71^1 -> 1712680 | J84: ='Acquisition Schedule'!I$20*(1-INDEX(Assumptions!$D$56:$F$56,1,2))*$D$71^2 -> 1560251.5 | K84: ='Acquisition Schedule'!I$20*(1-INDEX(Assumptions!$D$56:$F$56,1,2))*$D$71^3 -> 1421389.1 | L84: ='Acquisition Schedule'!I$20*(1-INDEX(Assumptions!$D$56:$F$56,1,2))*$D$71^4 -> 1294885.5 | M84: ='Acquisition Schedule'!I$20*(1-INDEX(Assumptions!$D$56:$F$56,1,2))*$D$71^5 -> 1179640.7 | N84: ='Acquisition Schedule'!I$20*(1-INDEX(Assumptions!$D$56:$F$56,1,2))*$D$71^6 -> 1074652.6
A85: Contracted vintage Year 4 | B85: $ | C85: [C] | D85: =0 -> 0 | E85: =0 -> 0 | F85: =0 -> 0 | G85: =0 -> 0 | H85: ='Acquisition Schedule'!J$20*$D$79 -> 352500 | I85: ='Acquisition Schedule'!J$20*(1-INDEX(Assumptions!$D$56:$F$56,1,2))*$D$71^0 -> 705000 | J85: ='Acquisition Schedule'!J$20*(1-INDEX(Assumptions!$D$56:$F$56,1,2))*$D$71^1 -> 642255 | K85: ='Acquisition Schedule'!J$20*(1-INDEX(Assumptions!$D$56:$F$56,1,2))*$D$71^2 -> 585094.31 | L85: ='Acquisition Schedule'!J$20*(1-INDEX(Assumptions!$D$56:$F$56,1,2))*$D$71^3 -> 533020.91 | M85: ='Acquisition Schedule'!J$20*(1-INDEX(Assumptions!$D$56:$F$56,1,2))*$D$71^4 -> 485582.05 | N85: ='Acquisition Schedule'!J$20*(1-INDEX(Assumptions!$D$56:$F$56,1,2))*$D$71^5 -> 442365.25
A86: Contracted vintage Year 5 | B86: $ | C86: [C] | D86: =0 -> 0 | E86: =0 -> 0 | F86: =0 -> 0 | G86: =0 -> 0 | H86: =0 -> 0 | I86: ='Acquisition Schedule'!K$20*$D$79 -> 352500 | J86: ='Acquisition Schedule'!K$20*(1-INDEX(Assumptions!$D$56:$F$56,1,2))*$D$71^0 -> 705000 | K86: ='Acquisition Schedule'!K$20*(1-INDEX(Assumptions!$D$56:$F$56,1,2))*$D$71^1 -> 642255 | L86: ='Acquisition Schedule'!K$20*(1-INDEX(Assumptions!$D$56:$F$56,1,2))*$D$71^2 -> 585094.31 | M86: ='Acquisition Schedule'!K$20*(1-INDEX(Assumptions!$D$56:$F$56,1,2))*$D$71^3 -> 533020.91 | N86: ='Acquisition Schedule'!K$20*(1-INDEX(Assumptions!$D$56:$F$56,1,2))*$D$71^4 -> 485582.05
A87: Contracted vintage Year 6 | B87: $ | C87: [C] | D87: =0 -> 0 | E87: =0 -> 0 | F87: =0 -> 0 | G87: =0 -> 0 | H87: =0 -> 0 | I87: =0 -> 0 | J87: ='Acquisition Schedule'!L$20*$D$79 -> 352500 | K87: ='Acquisition Schedule'!L$20*(1-INDEX(Assumptions!$D$56:$F$56,1,2))*$D$71^0 -> 705000 | L87: ='Acquisition Schedule'!L$20*(1-INDEX(Assumptions!$D$56:$F$56,1,2))*$D$71^1 -> 642255 | M87: ='Acquisition Schedule'!L$20*(1-INDEX(Assumptions!$D$56:$F$56,1,2))*$D$71^2 -> 585094.31 | N87: ='Acquisition Schedule'!L$20*(1-INDEX(Assumptions!$D$56:$F$56,1,2))*$D$71^3 -> 533020.91
A88: Contracted vintage Year 7 | B88: $ | C88: [C] | D88: =0 -> 0 | E88: =0 -> 0 | F88: =0 -> 0 | G88: =0 -> 0 | H88: =0 -> 0 | I88: =0 -> 0 | J88: =0 -> 0 | K88: ='Acquisition Schedule'!M$20*$D$79 -> 352500 | L88: ='Acquisition Schedule'!M$20*(1-INDEX(Assumptions!$D$56:$F$56,1,2))*$D$71^0 -> 705000 | M88: ='Acquisition Schedule'!M$20*(1-INDEX(Assumptions!$D$56:$F$56,1,2))*$D$71^1 -> 642255 | N88: ='Acquisition Schedule'!M$20*(1-INDEX(Assumptions!$D$56:$F$56,1,2))*$D$71^2 -> 585094.31
A89: Contracted business only: change-of-control loss once at close, then contractual retention. No new business. This is what was purchased and it is what the source-specific valuation capitalises at the multiple actually paid.
A90: Organic wins on the anchor | B90: $ | C90: [A] | D90: =0 -> 0 | E90: ='Acquisition Schedule'!F$20*(1-INDEX(Assumptions!$D$56:$F$56,1,2))*($D$76^0-$D$71^0) -> 0 | F90: ='Acquisition Schedule'!F$20*(1-INDEX(Assumptions!$D$56:$F$56,1,2))*($D$76^1-$D$71^1) -> 119887.6 | G90: ='Acquisition Schedule'!F$20*(1-INDEX(Assumptions!$D$56:$F$56,1,2))*($D$76^2-$D$71^2) -> 233725.67 | H90: ='Acquisition Schedule'!F$20*(1-INDEX(Assumptions!$D$56:$F$56,1,2))*($D$76^3-$D$71^3) -> 342230.7 | I90: ='Acquisition Schedule'!F$20*(1-INDEX(Assumptions!$D$56:$F$56,1,2))*($D$76^4-$D$71^4) -> 446062.25 | J90: ='Acquisition Schedule'!F$20*(1-INDEX(Assumptions!$D$56:$F$56,1,2))*($D$76^5-$D$71^5) -> 545828.34 | K90: ='Acquisition Schedule'!F$20*(1-INDEX(Assumptions!$D$56:$F$56,1,2))*($D$76^6-$D$71^6) -> 642090.24 | L90: ='Acquisition Schedule'!F$20*(1-INDEX(Assumptions!$D$56:$F$56,1,2))*($D$76^7-$D$71^7) -> 735367 | M90: ='Acquisition Schedule'!F$20*(1-INDEX(Assumptions!$D$56:$F$56,1,2))*($D$76^8-$D$71^8) -> 826139.42 | N90: ='Acquisition Schedule'!F$20*(1-INDEX(Assumptions!$D$56:$F$56,1,2))*($D$76^9-$D$71^9) -> 914853.82
A91: Organic wins on the Year 1 vintage | B91: $ | C91: [A] | D91: =0 -> 0 | E91: =0 -> 0 | F91: ='Acquisition Schedule'!G$20*(1-INDEX(Assumptions!$D$56:$F$56,1,2))*($D$76^0-$D$71^0) -> 0 | G91: ='Acquisition Schedule'!G$20*(1-INDEX(Assumptions!$D$56:$F$56,1,2))*($D$76^1-$D$71^1) -> 89915.7 | H91: ='Acquisition Schedule'!G$20*(1-INDEX(Assumptions!$D$56:$F$56,1,2))*($D$76^2-$D$71^2) -> 175294.25 | I91: ='Acquisition Schedule'!G$20*(1-INDEX(Assumptions!$D$56:$F$56,1,2))*($D$76^3-$D$71^3) -> 256673.02 | J91: ='Acquisition Schedule'!G$20*(1-INDEX(Assumptions!$D$56:$F$56,1,2))*($D$76^4-$D$71^4) -> 334546.69 | K91: ='Acquisition Schedule'!G$20*(1-INDEX(Assumptions!$D$56:$F$56,1,2))*($D$76^5-$D$71^5) -> 409371.25 | L91: ='Acquisition Schedule'!G$20*(1-INDEX(Assumptions!$D$56:$F$56,1,2))*($D$76^6-$D$71^6) -> 481567.68 | M91: ='Acquisition Schedule'!G$20*(1-INDEX(Assumptions!$D$56:$F$56,1,2))*($D$76^7-$D$71^7) -> 551525.25 | N91: ='Acquisition Schedule'!G$20*(1-INDEX(Assumptions!$D$56:$F$56,1,2))*($D$76^8-$D$71^8) -> 619604.57
A92: Organic wins on the Year 2 vintage | B92: $ | C92: [A] | D92: =0 -> 0 | E92: =0 -> 0 | F92: =0 -> 0 | G92: ='Acquisition Schedule'!H$20*(1-INDEX(Assumptions!$D$56:$F$56,1,2))*($D$76^0-$D$71^0) -> 0 | H92: ='Acquisition Schedule'!H$20*(1-INDEX(Assumptions!$D$56:$F$56,1,2))*($D$76^1-$D$71^1) -> 89915.7 | I92: ='Acquisition Schedule'!H$20*(1-INDEX(Assumptions!$D$56:$F$56,1,2))*($D$76^2-$D$71^2) -> 175294.25 | J92: ='Acquisition Schedule'!H$20*(1-INDEX(Assumptions!$D$56:$F$56,1,2))*($D$76^3-$D$71^3) -> 256673.02 | K92: ='Acquisition Schedule'!H$20*(1-INDEX(Assumptions!$D$56:$F$56,1,2))*($D$76^4-$D$71^4) -> 334546.69 | L92: ='Acquisition Schedule'!H$20*(1-INDEX(Assumptions!$D$56:$F$56,1,2))*($D$76^5-$D$71^5) -> 409371.25 | M92: ='Acquisition Schedule'!H$20*(1-INDEX(Assumptions!$D$56:$F$56,1,2))*($D$76^6-$D$71^6) -> 481567.68 | N92: ='Acquisition Schedule'!H$20*(1-INDEX(Assumptions!$D$56:$F$56,1,2))*($D$76^7-$D$71^7) -> 551525.25
A93: Organic wins on the Year 3 vintage | B93: $ | C93: [A] | D93: =0 -> 0 | E93: =0 -> 0 | F93: =0 -> 0 | G93: =0 -> 0 | H93: ='Acquisition Schedule'!I$20*(1-INDEX(Assumptions!$D$56:$F$56,1,2))*($D$76^0-$D$71^0) -> 0 | I93: ='Acquisition Schedule'!I$20*(1-INDEX(Assumptions!$D$56:$F$56,1,2))*($D$76^1-$D$71^1) -> 239775.2 | J93: ='Acquisition Schedule'!I$20*(1-INDEX(Assumptions!$D$56:$F$56,1,2))*($D$76^2-$D$71^2) -> 467451.34 | K93: ='Acquisition Schedule'!I$20*(1-INDEX(Assumptions!$D$56:$F$56,1,2))*($D$76^3-$D$71^3) -> 684461.39 | L93: ='Acquisition Schedule'!I$20*(1-INDEX(Assumptions!$D$56:$F$56,1,2))*($D$76^4-$D$71^4) -> 892124.5 | M93: ='Acquisition Schedule'!I$20*(1-INDEX(Assumptions!$D$56:$F$56,1,2))*($D$76^5-$D$71^5) -> 1091656.7 | N93: ='Acquisition Schedule'!I$20*(1-INDEX(Assumptions!$D$56:$F$56,1,2))*($D$76^6-$D$71^6) -> 1284180.5
A94: Organic wins on the Year 4 vintage | B94: $ | C94: [A] | D94: =0 -> 0 | E94: =0 -> 0 | F94: =0 -> 0 | G94: =0 -> 0 | H94: =0 -> 0 | I94: ='Acquisition Schedule'!J$20*(1-INDEX(Assumptions!$D$56:$F$56,1,2))*($D$76^0-$D$71^0) -> 0 | J94: ='Acquisition Schedule'!J$20*(1-INDEX(Assumptions!$D$56:$F$56,1,2))*($D$76^1-$D$71^1) -> 89915.7 | K94: ='Acquisition Schedule'!J$20*(1-INDEX(Assumptions!$D$56:$F$56,1,2))*($D$76^2-$D$71^2) -> 175294.25 | L94: ='Acquisition Schedule'!J$20*(1-INDEX(Assumptions!$D$56:$F$56,1,2))*($D$76^3-$D$71^3) -> 256673.02 | M94: ='Acquisition Schedule'!J$20*(1-INDEX(Assumptions!$D$56:$F$56,1,2))*($D$76^4-$D$71^4) -> 334546.69 | N94: ='Acquisition Schedule'!J$20*(1-INDEX(Assumptions!$D$56:$F$56,1,2))*($D$76^5-$D$71^5) -> 409371.25
A95: Organic wins on the Year 5 vintage | B95: $ | C95: [A] | D95: =0 -> 0 | E95: =0 -> 0 | F95: =0 -> 0 | G95: =0 -> 0 | H95: =0 -> 0 | I95: =0 -> 0 | J95: ='Acquisition Schedule'!K$20*(1-INDEX(Assumptions!$D$56:$F$56,1,2))*($D$76^0-$D$71^0) -> 0 | K95: ='Acquisition Schedule'!K$20*(1-INDEX(Assumptions!$D$56:$F$56,1,2))*($D$76^1-$D$71^1) -> 89915.7 | L95: ='Acquisition Schedule'!K$20*(1-INDEX(Assumptions!$D$56:$F$56,1,2))*($D$76^2-$D$71^2) -> 175294.25 | M95: ='Acquisition Schedule'!K$20*(1-INDEX(Assumptions!$D$56:$F$56,1,2))*($D$76^3-$D$71^3) -> 256673.02 | N95: ='Acquisition Schedule'!K$20*(1-INDEX(Assumptions!$D$56:$F$56,1,2))*($D$76^4-$D$71^4) -> 334546.69
A96: Organic wins on the Year 6 vintage | B96: $ | C96: [A] | D96: =0 -> 0 | E96: =0 -> 0 | F96: =0 -> 0 | G96: =0 -> 0 | H96: =0 -> 0 | I96: =0 -> 0 | J96: =0 -> 0 | K96: ='Acquisition Schedule'!L$20*(1-INDEX(Assumptions!$D$56:$F$56,1,2))*($D$76^0-$D$71^0) -> 0 | L96: ='Acquisition Schedule'!L$20*(1-INDEX(Assumptions!$D$56:$F$56,1,2))*($D$76^1-$D$71^1) -> 89915.7 | M96: ='Acquisition Schedule'!L$20*(1-INDEX(Assumptions!$D$56:$F$56,1,2))*($D$76^2-$D$71^2) -> 175294.25 | N96: ='Acquisition Schedule'!L$20*(1-INDEX(Assumptions!$D$56:$F$56,1,2))*($D$76^3-$D$71^3) -> 256673.02
A97: Organic wins on the Year 7 vintage | B97: $ | C97: [A] | D97: =0 -> 0 | E97: =0 -> 0 | F97: =0 -> 0 | G97: =0 -> 0 | H97: =0 -> 0 | I97: =0 -> 0 | J97: =0 -> 0 | K97: =0 -> 0 | L97: ='Acquisition Schedule'!M$20*(1-INDEX(Assumptions!$D$56:$F$56,1,2))*($D$76^0-$D$71^0) -> 0 | M97: ='Acquisition Schedule'!M$20*(1-INDEX(Assumptions!$D$56:$F$56,1,2))*($D$76^1-$D$71^1) -> 89915.7 | N97: ='Acquisition Schedule'!M$20*(1-INDEX(Assumptions!$D$56:$F$56,1,2))*($D$76^2-$D$71^2) -> 175294.25
A98: Gross new business the book wins after close, contracted roll-forward removed. Buyer-created, subject to the capacity ceiling and zeroed by the evidence switch.
A99: CONTRACTED ACQUIRED EBITDA | B99: $ | C99: [C] | D99: =SUM(D81:D88) -> 940000 | E99: =SUM(E81:E88) -> 1292500 | F99: =SUM(F81:F88) -> 1913840 | G99: =SUM(G81:G88) -> 3067380.7 | H99: =SUM(H81:H88) -> 4170543.9 | I99: =SUM(I81:I88) -> 4535738 | J99: =SUM(J81:J88) -> 4868429.8 | K99: =SUM(K81:K88) -> 5171512 | ... N99: =SUM(N81:N88) -> 4228547
A100: Contracted managed units | B100: units | C100: [C] | D100: =D99/INDEX(Assumptions!$D$32:$F$32,1,2) -> 7343.75 | E100: =E99/INDEX(Assumptions!$D$32:$F$32,1,2) -> 10097.656 | F100: =F99/INDEX(Assumptions!$D$32:$F$32,1,2) -> 14951.875 | G100: =G99/INDEX(Assumptions!$D$32:$F$32,1,2) -> 23963.912 | H100: =H99/INDEX(Assumptions!$D$32:$F$32,1,2) -> 32582.374 | I100: =I99/INDEX(Assumptions!$D$32:$F$32,1,2) -> 35435.453 | J100: =J99/INDEX(Assumptions!$D$32:$F$32,1,2) -> 38034.608 | K100: =K99/INDEX(Assumptions!$D$32:$F$32,1,2) -> 40402.438 | ... N100: =N99/INDEX(Assumptions!$D$32:$F$32,1,2) -> 33035.524
A101: Gross organic-win EBITDA before the ceiling | B101: $ | C101: [A] | D101: =SUM(D90:D97) -> 0 | E101: =SUM(E90:E97) -> 0 | F101: =SUM(F90:F97) -> 119887.6 | G101: =SUM(G90:G97) -> 323641.37 | H101: =SUM(H90:H97) -> 607440.65 | I101: =SUM(I90:I97) -> 1117804.7 | J101: =SUM(J90:J97) -> 1694415.1 | K101: =SUM(K90:K97) -> 2335679.5 | ... N101: =SUM(N90:N97) -> 4546049.3
A102: Gross organic-win units before the ceiling | B102: units | C102: [A] | D102: =D101/INDEX(Assumptions!$D$32:$F$32,1,2) -> 0 | E102: =E101/INDEX(Assumptions!$D$32:$F$32,1,2) -> 0 | F102: =F101/INDEX(Assumptions!$D$32:$F$32,1,2) -> 936.62188 | G102: =G101/INDEX(Assumptions!$D$32:$F$32,1,2) -> 2528.4482 | H102: =H101/INDEX(Assumptions!$D$32:$F$32,1,2) -> 4745.6301 | I102: =I101/INDEX(Assumptions!$D$32:$F$32,1,2) -> 8732.8494 | J102: =J101/INDEX(Assumptions!$D$32:$F$32,1,2) -> 13237.618 | K102: =K101/INDEX(Assumptions!$D$32:$F$32,1,2) -> 18247.496 | ... N102: =N101/INDEX(Assumptions!$D$32:$F$32,1,2) -> 35516.01
A103: Managed units before the capacity ceiling | B103: units | C103: [C] | D103: =D100+D102 -> 7343.75 | E103: =E100+E102 -> 10097.656 | F103: =F100+F102 -> 15888.497 | G103: =G100+G102 -> 26492.36 | H103: =H100+H102 -> 37328.004 | I103: =I100+I102 -> 44168.302 | J103: =J100+J102 -> 51272.225 | K103: =K100+K102 -> 58649.934 | ... N103: =N100+N102 -> 68551.534
...

Sheet Org & Capacity
A1: ORG AND CAPACITY — WORKFORCE ECONOMICS
A2: Corporate payroll has no independent existence. It is the sum of the role build below, at salary-sensitive loaded cost.
A3: Owner-reimbursed onsite staff are legal employees but economically owner funded and never enter PMC EBITDA.
A5: 1. ORGANISATION-BUILD DRIVERS (ORG-01 to ORG-18)
A6: Code | B6: Driver | C6: Units | D6: Base | E6: Low | F6: High | G6: Grade | N6: Source / note
A7: ORG-01 | B7: Onsite staffing ratio | C7: units/FTE | D7: 49 | E7: 45 | F7: 50 | G7: [F/C] | N7: Executed Dayrise PMA: 344 units / 7 onsite roles. NAA planning range 45-50.
A8: ORG-02 | B8: Regional property manager span | C8: props/RPM | D8: 10 | E8: 8 | F8: 12 | G8: [E] | N8: Planning band. Density-adjusted.
A9: ORG-03 | B9: Regional maintenance span | C9: props/leader | D9: 50 | E9: 40 | F9: 60 | G9: [E] | N9: Density-adjusted.
A10: ORG-04 | B10: Variable market-support multiplier | C10: x | D10: 1 | E10: 0.9 | F10: 1.15 | G10: [E] | N10: Dense / base / dispersed. Applied only to density-eligible roles.
A11: ORG-05 | B11: Property accountant span | C11: props/FTE | D11: 10 | E11: 8 | F11: 12 | G11: [A/E] | N11: Property and entity driven. NOT density-adjusted.
A12: ORG-06 | B12: VP / Director Ops activation | C12: units | D12: 5000 | E12: 5000 | F12: 5000 | G12: [E] | N12: VP layer begins above this scale. Read by R003 activation at E49 from v2.2.5.
A13: ORG-07 | B13: VP / Director Ops incremental | C13: units/FTE | D13: 10000 | E13: 7500 | F13: 12500 | G13: [E]
A14: ORG-08 | B14: CFO activation threshold | C14: units | D14: 10000 | E14: 7500 | F14: 15000 | G14: [E] | N14: Can remain outsourced below the threshold. Read by R005, R009 and R013 activations from v2.2.7.
A15: ORG-09 | B15: Controller span | C15: props/FTE | D15: 35 | E15: 30 | F15: 45 | G15: [E]
A16: ORG-10 | B16: AP / AR / Payroll ratio | C16: FTE/property | D16: 0.06 | E16: 0.05 | F16: 0.07 | G16: [E] | N16: Approximately 1 FTE per 16.7 properties. Transaction driven, not density.
A17: ORG-11 | B17: Treasury / FP&A incremental | C17: units/FTE | D17: 5000 | E17: 4000 | F17: 7500 | G17: [E] | N17: Applies above the first 5,000 units. Read by R009 activation at E55 from v2.2.6.
A18: ORG-12 | B18: HR / Recruiting / L&D incremental | C18: units/FTE | D18: 3333 | E18: 2500 | F18: 5000 | G18: [E] | N18: Density-eligible: more markets increase recruiting cost.
A19: ORG-13 | B19: Marketing / Revenue Mgmt to 10k | C19: units/FTE | D19: 5000 | E19: 4000 | F19: 6500 | G19: [E]
A20: ORG-14 | B20: IT / PMS Admin / Data-BI | C20: units/FTE | D20: 2500 | E20: 2000 | F20: 3500 | G20: [E] | N20: Systems driven. NOT density-adjusted.
A21: ORG-15 | B21: Compliance / Risk / Procurement / Legal | C21: units/FTE | D21: 3750 | E21: 3000 | F21: 5000 | G21: [E] | N21: Density-eligible: markets and asset complexity. Also the R013 activation and step base from v2.2.6, per the v1.8.0 mechanic.
A22: ORG-16 | B22: Marketing / Revenue Mgmt above 10k | C22: units/FTE | D22: 4000 | E22: 3500 | F22: 5000 | G22: [E]
A23: ORG-17 | B23: Business development span | C23: units/FTE | D23: 10000 | E23: 7500 | F23: 12500 | G23: [E] | N23: Density-eligible: local market relationships.
A24: ORG-18 | B24: Corporate-layer activation floor | C24: units | D24: 5000 | E24: 5000 | F24: 5000 | G24: [E] | N24: Corporate-layer activation floor, named for HR and IT, which read it at E56 and E58. Compliance (R013) does not: the v1.8.0 mechanic activates it at its own first ORG-15 step of 3,750 units.
A25: ORG-21 Nearshore delivered cost — Base input (0.40x) and effective index at H25 | B25: x | C25: [A] | D25: 0.4 | G25: [A] | H25: =IF(Assumptions!$D$8=1,'Evidence & Market'!$C$38,$D$25) -> 0.4 | N25: JACK PRINCIPAL DECISION, 7 Sep 2026: Base underwrites 0.40x delivered LATAM employment cost for R006, R007 and R008. Graded [A]; no PMC-specific delivered quote exists. SUPERVISOR RULING, 7 Sep 2026: under the evidence-constrained switch the delivered index reverts to the 0.46x [C] Abacus comparable at Evidence & Market C38 — nearshore delivery is not zeroed, because a comparable exists, but the incremental 0.40x assumption disappears. Effective index in force is at H25.
A26: 2. SALARY-SENSITIVE PAYROLL BURDEN (BEN-01 to BEN-14) — replaces any flat multiple
A27: Burden is role-sensitive. A flat multiple overstates it on senior roles, where the wage base and qualified-comp cap bind, and understates it on junior roles.
A28: Code | B28: Input | C28: Units | D28: Base | E28: Low | F28: High | G28: Grade | N28: Source
A29: BEN-01 | B29: Employer Social Security rate | C29: % | D29: 0.062 | E29: 0.062 | F29: 0.062 | G29: [F] | N29: IRS Publication 15 (2026)
A30: BEN-02 | B30: Social Security wage base | C30: $ | D30: 184500 | E30: 184500 | F30: 184500 | G30: [F] | N30: SSA contribution and benefit base 2026
A31: BEN-03 | B31: Employer Medicare rate | C31: % | D31: 0.0145 | E31: 0.0145 | F31: 0.0145 | G31: [F] | N31: No wage cap
A32: BEN-04 | B32: FUTA per employee | C32: $ | D32: 42 | E32: 42 | F32: 42 | G32: [F] | N32: Federal unemployment
A33: BEN-05 | B33: State unemployment per corporate FTE | C33: $ | D33: 250 | E33: 150 | F33: 400 | G33: [A] | N33: State-specific planning allowance
A34: BEN-06 | B34: Gross health benefit cost per enrolled employee | C34: $ | D34: 18500 | E34: 15000 | F34: 20000 | G34: [F/C] | N34: Mercer / KFF basis
A35: BEN-07 | B35: Employer share of gross health cost | C35: % | D35: 0.8 | E35: 0.75 | F35: 0.85 | G35: [F] | N35: Large-firm premium share benchmark
A36: BEN-08 | B36: Corporate health-plan take-up rate | C36: % | D36: 0.9 | E36: 0.85 | F36: 0.95 | G36: [C] | N36: Eligibility and take-up benchmark
A37: BEN-09 | B37: PPO / competitive-plan buffer | C37: x | D37: 1.05 | E37: 1 | F37: 1.05 | G37: [A] | N37: Conservative plan-quality buffer
A38: BEN-11 | B38: 401(k) employer match rate | C38: % | D38: 0.04 | E38: 0.03 | F38: 0.05 | G38: [A] | N38: Applied to base salary
A39: BEN-12 | B39: Qualified-plan compensation cap | C39: $ | D39: 360000 | E39: 360000 | F39: 360000 | G39: [F] | N39: IRS 2026 limit
A40: BEN-13 | B40: PEO administration per FTE per year | C40: $ | D40: 1488 | E40: 1488 | F40: 1488 | G40: [F] | N40: $124 per FTE per month
A41: BEN-14 | B41: Workers comp and other employment insurance per FTE | C41: $ | D41: 1000 | E41: 500 | F41: 2000 | G41: [A] | N41: Low-risk corporate-role allowance
A42: BEN-10 | B42: Blended employer health cost per corporate FTE | C42: $ | D42: =D34*D35*D36*D37 -> 13986 | G42: Formula | N42: BEN-06 x BEN-07 x BEN-08 x BEN-09
A44: 3. STANDALONE TARGET ROLE ARCHITECTURE (R001 to R014) — the org an acquired PMC carries
A45: CENTRALIZE removes the local cost once and adds a replacement shared-service cost once, with both paid during the overlap window. RETAIN LOCAL stays inside acquired EBITDA. NO CREDIT is never eliminated.
A46: Role ID | B46: Function | C46: Driver | D46: Span / ratio | E46: Activation | F46: Base salary | G46: Bonus % | H46: Cash comp | I46: Loaded cost | J46: Treatment | K46: Location | L46: Density | M46: Grade | N46: Note | O46: Units/FTE equiv | P46: Density elig. | Q46: RETAIN | R46: CENTRAL | S46: NOCRED | T46: Base FTE | U46: Step base units | V46: Base FTE and step base reproduce the 5,000 / 10,000 / 20,000-unit benchmark organisation from the market and density work. | W46: SS units/FTE | X46: Seat granularity | Y46: Nearshore share | Z46: Permitted NS max
A47: R001 | B47: Regional Property Managers | C47: props/RPM | D47: =D8 -> 10 | E47: 0 | F47: 120000 | G47: 0.15 | H47: =F47*(1+G47) -> 138000 | I47: =H47+MIN(H47,$D$30)*$D$29+H47*$D$31+$D$32+$D$33+$D$42+MIN(F47,$D$39)*$D$38+$D$40+$D$41 -> 170123 | J47: RETAIN LOCAL | K47: LOCAL | L47: YES | M47: [E] | N47: Property and market operations | O47: =D47*INDEX(Assumptions!$D$17:$F$17,1,2) -> 2500 | P47: =IF(L47="YES",1,0) -> 1 | Q47: =IF(J47="RETAIN LOCAL",1,0) -> 1 | R47: =IF(J47="CENTRALIZE",1,0) -> 0 | S47: =IF(J47="NO CREDIT",1,0) -> 0 | T47: 0 | U47: 0 | W47: 0 | X47: 1 | Y47: 0 | Z47: 1
A48: R002 | B48: Regional Maintenance Director | C48: props/leader | D48: =D9 -> 50 | E48: 0 | F48: 115000 | G48: 0.15 | H48: =F48*(1+G48) -> 132250 | I48: =H48+MIN(H48,$D$30)*$D$29+H48*$D$31+$D$32+$D$33+$D$42+MIN(F48,$D$39)*$D$38+$D$40+$D$41 -> 163733.12 | J48: RETAIN LOCAL | K48: LOCAL | L48: YES | M48: [E] | N48: Regional facilities leadership | O48: =D48*INDEX(Assumptions!$D$17:$F$17,1,2) -> 12500 | P48: =IF(L48="YES",1,0) -> 1 | Q48: =IF(J48="RETAIN LOCAL",1,0) -> 1 | R48: =IF(J48="CENTRALIZE",1,0) -> 0 | S48: =IF(J48="NO CREDIT",1,0) -> 0 | T48: 0 | U48: 0 | W48: 0 | X48: 1 | Y48: 0 | Z48: 1
A49: R003 | B49: VP / Director of Operations | C49: units/FTE | D49: =D13 -> 10000 | E49: =$D$12 -> 5000 | F49: 148000 | G49: 0.2 | H49: =F49*(1+G49) -> 177600 | I49: =H49+MIN(H49,$D$30)*$D$29+H49*$D$31+$D$32+$D$33+$D$42+MIN(F49,$D$39)*$D$38+$D$40+$D$41 -> 213872.4 | J49: RETAIN LOCAL | K49: LOCAL | L49: YES | M49: [E] | N49: ORG-06 linked. Restores the pre-v2 specification (activation plus ORG-06/07 units per FTE). In isolation this takes the $750k tuck-ins to 106.52% of their own cost base. | O49: =D49 -> 10000 | P49: =IF(L49="YES",1,0) -> 1 | Q49: =IF(J49="RETAIN LOCAL",1,0) -> 1 | R49: =IF(J49="CENTRALIZE",1,0) -> 0 | S49: =IF(J49="NO CREDIT",1,0) -> 0 | T49: 0 | U49: 0 | W49: 0 | X49: 1 | Y49: 0 | Z49: 1
A50: R004 | B50: Founder / Head of Operations | C50: fixed | D50: 0 | E50: 0 | F50: 237500 | G50: 0.275 | H50: =F50*(1+G50) -> 302812.5 | I50: =H50+MIN(H50,$D$30)*$D$29+H50*$D$31+$D$32+$D$33+$D$42+MIN(F50,$D$39)*$D$38+$D$40+$D$41 -> 344908.28 | J50: NO CREDIT | K50: LOCAL | L50: NO | M50: [E] | N50: Handled by the leadership-redundancy schedule below, never by a generic percentage | O50: =0 -> 0 | P50: =IF(L50="YES",1,0) -> 0 | Q50: =IF(J50="RETAIN LOCAL",1,0) -> 0 | R50: =IF(J50="CENTRALIZE",1,0) -> 0 | S50: =IF(J50="NO CREDIT",1,0) -> 1 | T50: 1 | U50: 0 | W50: 0 | X50: 1 | Y50: 0 | Z50: 1
A51: R005 | B51: CFO | C51: activation | D51: =D14 -> 10000 | E51: =$D$14 -> 10000 | F51: 280000 | G51: 0.325 | H51: =F51*(1+G51) -> 371000 | I51: =H51+MIN(H51,$D$30)*$D$29+H51*$D$31+$D$32+$D$33+$D$42+MIN(F51,$D$39)*$D$38+$D$40+$D$41 -> 415784.5 | J51: CENTRALIZE | K51: SHARED | L51: NO | M51: [E] | N51: Absent or outsourced below the threshold | O51: =0 -> 0 | P51: =IF(L51="YES",1,0) -> 0 | Q51: =IF(J51="RETAIN LOCAL",1,0) -> 0 | R51: =IF(J51="CENTRALIZE",1,0) -> 1 | S51: =IF(J51="NO CREDIT",1,0) -> 0 | T51: 1 | U51: 0 | W51: 0 | X51: 1 | Y51: 0 | Z51: 1
A52: R006 | B52: Controller / Accounting Manager | C52: props/FTE | D52: =D15 -> 35 | E52: 0 | F52: 130000 | G52: 0.15 | H52: =F52*(1+G52) -> 149500 | I52: =H52+MIN(H52,$D$30)*$D$29+H52*$D$31+$D$32+$D$33+$D$42+MIN(F52,$D$39)*$D$38+$D$40+$D$41 -> 182902.75 | J52: CENTRALIZE | K52: SHARED | L52: NO | M52: [E] | N52: Core accounting | O52: =D52*INDEX(Assumptions!$D$17:$F$17,1,2) -> 8750 | P52: =IF(L52="YES",1,0) -> 0 | Q52: =IF(J52="RETAIN LOCAL",1,0) -> 0 | R52: =IF(J52="CENTRALIZE",1,0) -> 1 | S52: =IF(J52="NO CREDIT",1,0) -> 0 | T52: 0 | U52: 0 | W52: 15000 | X52: 1 | Y52: 1 | Z52: 1
A53: R007 | B53: Property Accountants | C53: props/FTE | D53: =D11 -> 10 | E53: 0 | F53: 75000 | G53: 0.08 | H53: =F53*(1+G53) -> 81000 | I53: =H53+MIN(H53,$D$30)*$D$29+H53*$D$31+$D$32+$D$33+$D$42+MIN(F53,$D$39)*$D$38+$D$40+$D$41 -> 106962.5 | J53: CENTRALIZE | K53: SHARED | L53: NO | M53: [E] | N53: Prime shared-services and offshore candidate | O53: =D53*INDEX(Assumptions!$D$17:$F$17,1,2) -> 2500 | P53: =IF(L53="YES",1,0) -> 0 | Q53: =IF(J53="RETAIN LOCAL",1,0) -> 0 | R53: =IF(J53="CENTRALIZE",1,0) -> 1 | S53: =IF(J53="NO CREDIT",1,0) -> 0 | T53: 0 | U53: 0 | W53: 6000 | X53: 1 | Y53: 1 | Z53: 1
A54: R008 | B54: AP / AR / Payroll | C54: FTE/property | D54: =D16 -> 0.06 | E54: 0 | F54: 60000 | G54: 0.08 | H54: =F54*(1+G54) -> 64800 | I54: =H54+MIN(H54,$D$30)*$D$29+H54*$D$31+$D$32+$D$33+$D$42+MIN(F54,$D$39)*$D$38+$D$40+$D$41 -> 88923.2 | J54: CENTRALIZE | K54: SHARED | L54: NO | M54: [E] | N54: Transaction driven | O54: =INDEX(Assumptions!$D$17:$F$17,1,2)/D54 -> 4166.6667 | P54: =IF(L54="YES",1,0) -> 0 | Q54: =IF(J54="RETAIN LOCAL",1,0) -> 0 | R54: =IF(J54="CENTRALIZE",1,0) -> 1 | S54: =IF(J54="NO CREDIT",1,0) -> 0 | T54: 0 | U54: 0 | W54: 10000 | X54: 1 | Y54: 1 | Z54: 1
A55: R009 | B55: Treasury / FP&A | C55: units/FTE | D55: =D17 -> 5000 | E55: =$D$14 -> 10000 | F55: 130000 | G55: 0.15 | H55: =F55*(1+G55) -> 149500 | I55: =H55+MIN(H55,$D$30)*$D$29+H55*$D$31+$D$32+$D$33+$D$42+MIN(F55,$D$39)*$D$38+$D$40+$D$41 -> 182902.75 | J55: CENTRALIZE | K55: SHARED | L55: NO | M55: [E] | N55: PLATFORM ROLE. Principal decision, 4 Sep 2026: acquired targets of this size do not carry a treasury or FP&A function; it appears only at platform scale. Activation linked to ORG-08 at 10,000 units, above the largest acquired company. This overrides the v1.8.0 deal-level mechanic, which is recorded rather than restored. Seat granularity remains continuous, so the figure is FTE-equivalent capacity, not literal headcount. | O55: =D55 -> 5000 | P55: =IF(L55="YES",1,0) -> 0 | Q55: =IF(J55="RETAIN LOCAL",1,0) -> 0 | R55: =IF(J55="CENTRALIZE",1,0) -> 1 | S55: =IF(J55="NO CREDIT",1,0) -> 0 | T55: 0 | U55: 5000 | W55: 12500 | X55: 1000000 | Y55: 0 | Z55: 1
A56: R010 | B56: HR / Recruiting / L&D | C56: units/FTE | D56: =D18 -> 3333 | E56: =$D$24 -> 5000 | F56: 110000 | G56: 0.15 | H56: =F56*(1+G56) -> 126500 | I56: =H56+MIN(H56,$D$30)*$D$29+H56*$D$31+$D$32+$D$33+$D$42+MIN(F56,$D$39)*$D$38+$D$40+$D$41 -> 157343.25 | J56: CENTRALIZE | K56: SHARED | L56: YES | M56: [E] | N56: People support | O56: =D56 -> 3333 | P56: =IF(L56="YES",1,0) -> 1 | Q56: =IF(J56="RETAIN LOCAL",1,0) -> 0 | R56: =IF(J56="CENTRALIZE",1,0) -> 1 | S56: =IF(J56="NO CREDIT",1,0) -> 0 | T56: 1 | U56: 5000 | W56: 6000 | X56: 1 | Y56: 0 | Z56: 1
A57: R011 | B57: Marketing / Revenue Management | C57: units/FTE | D57: =D19 -> 5000 | E57: 0 | F57: 110000 | G57: 0.15 | H57: =F57*(1+G57) -> 126500 | I57: =H57+MIN(H57,$D$30)*$D$29+H57*$D$31+$D$32+$D$33+$D$42+MIN(F57,$D$39)*$D$38+$D$40+$D$41 -> 157343.25 | J57: NO CREDIT | K57: SHARED | L57: NO | M57: [E] | N57: Becomes Layer 2 delivery; no elimination credit | O57: =D57 -> 5000 | P57: =IF(L57="YES",1,0) -> 0 | Q57: =IF(J57="RETAIN LOCAL",1,0) -> 0 | R57: =IF(J57="CENTRALIZE",1,0) -> 0 | S57: =IF(J57="NO CREDIT",1,0) -> 1 | T57: 1 | U57: 5000 | W57: 0 | X57: 1 | Y57: 0 | Z57: 1
A58: R012 | B58: IT / PMS Admin / Data-BI | C58: units/FTE | D58: =D20 -> 2500 | E58: =$D$24 -> 5000 | F58: 125000 | G58: 0.15 | H58: =F58*(1+G58) -> 143750 | I58: =H58+MIN(H58,$D$30)*$D$29+H58*$D$31+$D$32+$D$33+$D$42+MIN(F58,$D$39)*$D$38+$D$40+$D$41 -> 176512.88 | J58: CENTRALIZE | K58: SHARED | L58: NO | M58: [E] | N58: Platform systems | O58: =D58 -> 2500 | P58: =IF(L58="YES",1,0) -> 0 | Q58: =IF(J58="RETAIN LOCAL",1,0) -> 0 | R58: =IF(J58="CENTRALIZE",1,0) -> 1 | S58: =IF(J58="NO CREDIT",1,0) -> 0 | T58: 1 | U58: 5000 | W58: 6000 | X58: 1 | Y58: 0 | Z58: 1
A59: R013 | B59: Compliance / Risk / Procurement / Legal | C59: units/FTE | D59: =D21 -> 3750 | E59: =$D$14 -> 10000 | F59: 125000 | G59: 0.15 | H59: =F59*(1+G59) -> 143750 | I59: =H59+MIN(H59,$D$30)*$D$29+H59*$D$31+$D$32+$D$33+$D$42+MIN(F59,$D$39)*$D$38+$D$40+$D$41 -> 176512.88 | J59: CENTRALIZE | K59: SHARED | L59: YES | M59: [E] | N59: PLATFORM ROLE. Principal decision, 4 Sep 2026: acquired targets of this size do not carry a dedicated compliance, risk, procurement or legal function. Activation linked to ORG-08 at 10,000 units. The v1.8.0 deal-level stepped mechanic is retired rather than restored; its encoding as base FTE minus one is withdrawn because the identity ROUNDDOWN(u/s)-1 = -1+CEILING((u-s)/s) breaks at exact multiples of s. Density eligibility is inert at platform scale. | O59: =D59 -> 3750 | P59: =IF(L59="YES",1,0) -> 1 | Q59: =IF(J59="RETAIN LOCAL",1,0) -> 0 | R59: =IF(J59="CENTRALIZE",1,0) -> 1 | S59: =IF(J59="NO CREDIT",1,0) -> 0 | T59: 1 | U59: 10000 | W59: 8000 | X59: 1 | Y59: 0 | Z59: 1
A60: R014 | B60: Business Development | C60: units/FTE | D60: =D23 -> 10000 | E60: 0 | F60: 120000 | G60: 0.15 | H60: =F60*(1+G60) -> 138000 | I60: =H60+MIN(H60,$D$30)*$D$29+H60*$D$31+$D$32+$D$33+$D$42+MIN(F60,$D$39)*$D$38+$D$40+$D$41 -> 170123 | J60: RETAIN LOCAL | K60: LOCAL | L60: YES | M60: [E] | N60: Restored to one commercial seat per acquired PMC from day one plus the ORG-17 unit span, per the pre-v2 role map. In isolation this takes the $750k tuck-ins to 105.10%; the anchor and TK04 stay below 100% at 92.98% and 88.55%. | O60: =D60 -> 10000 | P60: =IF(L60="YES",1,0) -> 1 | Q60: =IF(J60="RETAIN LOCAL",1,0) -> 1 | R60: =IF(J60="CENTRALIZE",1,0) -> 0 | S60: =IF(J60="NO CREDIT",1,0) -> 0 | T60: 1 | U60: 10000 | W60: 0 | X60: 1 | Y60: 0 | Z60: 1
A61: Implied burden multiple, weighted | B61: x | I61: =SUM(I47:I60)/SUM(H47:H60) -> 1.206233 | N61: Range across roles rather than a single flat multiple. Senior roles are lower because the wage base and comp cap bind. | W61: Shared-services span per role. Each is separately evidenceable by reference call; the blended efficiency ratio below is now an OUTPUT of this column, not an input. | X61: Denominator for the seat-count rounding. 1 rounds each role up to whole seats, which is correct for a standalone company that cannot hire a fraction of a person. R009 Treasury / FP&A is restored to the continuous v1.8.0 mechanic and is the only role carrying a granularity other than 1. | Y61: PRINCIPAL DECISION, Jack, 4 Sep 2026: R006 Controller / Accounting Manager, R007 Property Accountants and R008 AP / AR / Payroll are delivered 100% nearshore. This overrides the earlier partial offshore-eligibility assumption for Controller. R009 Treasury / FP&A and the R013 operating team are nearshore-eligible on the Abacus evidence and are exposed as scenarios rather than assumed. R010 HR and R012 IT are sensitivities. H003 Finance Leadership, H006 Legal / Risk / Compliance Leadership, every local and regional operating role and any function requiring U.S. fiduciary, banking, employment or legal authority remain onshore. Oversight is not charged twice: H003 and H006 are the U.S. review and control layer and are already charged in full. | Z61: Owner-permission and data-residency cap on the nearshore share, by role. Where an owner refuses offshore handling of resident PII or trust-account access, the cap binds and the residual work is performed onshore at full U.S. loaded cost. It never suppresses the role or reduces the FTE required.
A63: 4. HOLDCO AND PLATFORM ROLES (H001 to H009) — replacement versus incremental
A64: Only the incremental share is charged above the shared-services organisation. A replacement seat is already paid for inside the acquired cost base and may not be charged twice.
A65: Role ID | B65: Role | C65: Activation units | F65: Base salary | G65: Bonus % | H65: Cash comp | I65: Loaded cost | J65: Classification | K65: Incr. share | M65: Grade | N65: Note
A66: H001 | B66: Platform CEO / President | C66: 0 | F66: 257692 | G66: 0 | H66: =F66*(1+G66) -> 257692 | I66: =H66+MIN(H66,$D$30)*$D$29+H66*$D$31+$D$32+$D$33+$D$42+MIN(F66,$D$39)*$D$38+$D$40+$D$41 -> 299941.21 | J66: Incremental | K66: 1 | M66: [E] | N66: Founder-led. Incremental from day one.
A67: H002 | B67: VP Platform Operations / Integration | C67: 0 | F67: 257692 | G67: 0 | H67: =F67*(1+G67) -> 257692 | I67: =H67+MIN(H67,$D$30)*$D$29+H67*$D$31+$D$32+$D$33+$D$42+MIN(F67,$D$39)*$D$38+$D$40+$D$41 -> 299941.21 | J67: Incremental | K67: 1 | M67: [E] | N67: Scale and integration seat.
A68: H003 | B68: Finance Leadership and Controls | C68: 10000 | F68: 169231 | G68: 0 | H68: =F68*(1+G68) -> 169231 | I68: =H68+MIN(H68,$D$30)*$D$29+H68*$D$31+$D$32+$D$33+$D$42+MIN(F68,$D$39)*$D$38+$D$40+$D$41 -> 205712.41 | J68: Incremental | K68: 1 | M68: [E] | N68: RECONCILED v2.3.0. Charged as incremental. The seller controller layer it claimed to replace is already fully consumed: R006 seller payroll is eliminated inside the centralisation credit and R006 platform replacement payroll is charged in the same-scope shared-services block. No seller dollar remains to fund a third layer.
A69: H004 | B69: Technology / Data / Product | C69: 0 | F69: 146154 | G69: 0 | H69: =F69*(1+G69) -> 146154 | I69: =H69+MIN(H69,$D$30)*$D$29+H69*$D$31+$D$32+$D$33+$D$42+MIN(F69,$D$39)*$D$38+$D$40+$D$41 -> 179946.94 | J69: Incremental | K69: 1 | M69: [E] | N69: RECONCILED v2.3.0. Charged in full. The replacement half mapped to R012 IT / PMS Admin / Data-BI, whose seller pool is already consumed by the centralisation credit and whose platform replacement is already charged in shared services.
A70: H005 | B70: People / HR / Training Leadership | C70: 5000 | F70: 103846 | G70: 0 | H70: =F70*(1+G70) -> 103846 | I70: =H70+MIN(H70,$D$30)*$D$29+H70*$D$31+$D$32+$D$33+$D$42+MIN(F70,$D$39)*$D$38+$D$40+$D$41 -> 132710.06 | J70: Incremental | K70: 1 | M70: [E] | N70: RECONCILED v2.3.0. Charged as incremental. Same reconciliation as H003 against R010 HR / Recruiting / L&D: seller pool consumed, platform replacement already charged.
A71: H006 | B71: Legal / Risk / Compliance Leadership | C71: 5000 | F71: 216667 | G71: 0 | H71: =F71*(1+G71) -> 216667 | I71: =H71+MIN(H71,$D$30)*$D$29+H71*$D$31+$D$32+$D$33+$D$42+MIN(F71,$D$39)*$D$38+$D$40+$D$41 -> 256680.35 | J71: Incremental | K71: 1 | M71: [E] | N71: RECONCILED, v2.2.8. Was Replacement at 0% incremental, noted as replacing acquired compliance leadership. Under the v2.2.7 principal decision no acquired target carries a compliance, risk, procurement or legal function, so there is nothing to replace. Treated as a distinct senior HoldCo seat above the R013 operating team, which is span-driven, and charged in full. The alternative reading, that H006 and R013 are one functional layer, would require removing H006 rather than leaving it uncharged.
A72: H007 | B72: Corporate M&A / Growth | C72: 0 | F72: 110769 | G72: 0.25 | H72: =F72*(1+G72) -> 138461.25 | I72: =H72+MIN(H72,$D$30)*$D$29+H72*$D$31+$D$32+$D$33+$D$42+MIN(F72,$D$39)*$D$38+$D$40+$D$41 -> 170250.3 | J72: Incremental | K72: 1 | M72: [E] | N72: Acquisition capability the targets do not carry.
